Workbook

Sheet Özet
B1: Salzburg ve Çevresi – IT & Cyber Security İş İlanları (CANLI TARAMA)
B2: Aday: Evren Selvi · Canlı tarama 27.09.2026 · karriere.at + LinkedIn + Red Bull resmi portalı + ACP portalı · 122 aktif ilan, her linki açılıp başlığı eşleştirildi
B4: ADAY PROFİLİ (CV'den)
B5: Konum | C5: Salzburg, Avusturya – hemen başlayabilir; Avusturya'da çalışma izni var
B6: Deneyim | C6: 15+ yıl kurumsal IT: IT Manager (Inditex, 2021–23) · ISMS Executive (2016–21) · Senior IT Project Resp. (2012–16) · M&S/GAP Retail IT Ops (2007–12)
B7: Güçlü yönler | C7: 200+ mağaza / 17.000 cihaz IT operasyonu · ISO 27001 ISMS (5 yıl) · AD / Windows Server · Hyper-V/Proxmox · backup/DR · VLAN/VPN/firewall · ITIL · bütçe & tedarikçi yönetimi
B8: Sertifikalar | C8: ISO 27001 Internal Auditor · ITIL (Axelos) · MCDBA · SQL Server 2005/2008 · Excel Expert · Linux eğitimi (İTÜ)
B9: Diller | C9: Türkçe (ana dil) · İngilizce (ileri) · Almanca B1/B2
B10: Aranan alanlar (tek liste) | C10: IT altyapı/operasyon · IT yönetimi · ISMS / Information Security · Cyber Security · IT servis (ITIL) · IT proje · sistem/ağ yönetimi · IT destek
B12: PUANLAMA AĞIRLIKLARI (sarı hücreler değiştirilebilir – tüm puanlar otomatik güncellenir)
B13: Kriter | C13: Ağırlık | D13: Açıklama
B14: Teknik uyum | C14: 0.3 | D14: İlan metnindeki beceriler ↔ CV: ISO 27001/ISMS, ITIL, AD/Windows Server, sanallaştırma, backup/DR, ağ/firewall, SQL, proje/tedarikçi/bütçe yönetimi. Eksikler (Azure, SIEM, scripting, SAP…) puan düşürür
B15: Deneyim / kıdem uyumu | C15: 0.15 | D15: 15+ yıl, yönetici seviyesi; junior / 1st-level roller düşük (overqualified)
B16: Dil uyumu | C16: 0.3 | D16: İlanın gerçek dil şartı metinden okundu (skala aşağıda). 27.09 güncellemesi: İngilizce öncelikli – ağırlık %20→%30, Almanca isteyen ilanların puanı düşürüldü
B17: Sektör / kültür | C17: 0.05 | D17: Perakende / FMCG / çok lokasyonlu kurumsal = artı
B18: Lokasyon / ulaşım | C18: 0.1 | D18: Salzburg merkezden: ≤30 dk = 5 · 30–45 = 4 · 45–60 = 3 · 60–90 = 2
B19: Maaş / kariyer | C19: 0.1 | D19: İlandaki yıllık brüt maaş (14 maaş). Sadece KV asgarisi yazıyorsa ceza yok (3–3,5)
B20: Toplam (100% olmalı) | C20: =SUM(C14:C19) -> 1
B22: DİL KODLARI (ilan metninden otomatik okundu – 'Almanca şartı' sütununda alıntı var)
B23: Kod | C23: Puan (1–5) | D23: Anlamı
B24: EN | C24: 5 | D24: İngilizce ilan, Almanca şartı yok
B25: EN (+DE artı) | C25: 5 | D25: İngilizce yeterli; Almanca sadece 'von Vorteil / a plus'
B26: EN+DE | C26: 3,5 | D26: İngilizce ilan, Almanca da isteniyor (seviye belirtilmemiş)
B27: DE+EN | C27: 2 | D27: Almanca ilan; Almanca seviyesi belirtilmemiş + İngilizce isteniyor
B28: EN+DE (akıcı DE) | C28: 1,5 | D28: İngilizce ilan ama akıcı/çok iyi Almanca şart
B29: DE | C29: 1,5 | D29: Almanca ilan, seviye belirtilmemiş, İngilizce yok
B30: DE C1 | C30: 1 | D30: 'Sehr gute / fließende / ausgezeichnete Deutschkenntnisse' ya da C1 – akıcı Almanca olmadan çok zor
B31: Türkçe | C31: +1 | D31: İlanda Türkçe geçerse +1 (bu taramada Türkçe isteyen IT ilanı çıkmadı)
B33: İSTATİSTİKLER (canlı formüller)
B34: Toplam aktif ilan (linki canlı test edildi) | C34: =COUNTA(İlanlar!$C$5:$C$126) -> 122
B35: A – Hemen başvur: İngilizce yeterli + uyum ≥70% | C35: =COUNTIF(İlanlar!$AB$5:$AB$126,"A*") -> 16
B36: B – Başvur: uyum ≥70% ama Almanca gerekli / İngilizce 60–69% | C36: =COUNTIF(İlanlar!$AB$5:$AB$126,"B*") -> 11
B37: C – Opsiyonel | C37: =COUNTIF(İlanlar!$AB$5:$AB$126,"C*") -> 95
B38: Cyber Security / ISMS ilanları | C38: =COUNTIF(İlanlar!$F$5:$F$126,"Cyber*") -> 25
B39: İngilizce yeterli (EN / EN +DE artı) | C39: =COUNTIF(İlanlar!$G$5:$G$126,"EN")+COUNTIF(İlanlar!$G$5:$G$126,"EN (+DE artı)") -> 16
B40: İngilizce + Almanca (EN+DE / DE+EN) | C40: =COUNTIF(İlanlar!$G$5:$G$126,"EN+DE")+COUNTIF(İlanlar!$G$5:$G$126,"DE+EN")+COUNTIF(İlanlar!$G$5:$G$126,"EN+DE (akıcı DE)") -> 24
B41: Sadece Almanca (DE / DE C1) | C41: =COUNTIF(İlanlar!$G$5:$G$126,"DE")+COUNTIF(İlanlar!$G$5:$G$126,"DE C1") -> 82
B42: Ortalama uyum | C42: =AVERAGE(İlanlar!$Z$5:$Z$126) -> 0.63377049
B43: En yüksek uyum | C43: =MAX(İlanlar!$Z$5:$Z$126) -> 0.91
B44: Taramada bulunup profil/ulaşım nedeniyle elenen | C44: 114
B45: Önceki listeden canlı bulunan / toplam | C45: 14 / 44
B47: İLK 30 İLAN – önce İngilizce yeterli olanlar, sonra uyum sırası (otomatik)
B48: Firma | C48: Sıra | D48: Pozisyon | E48: Lokasyon | F48: Dil | G48: Uyum % | H48: Öncelik | I48: İlan linki
B49: =INDEX(İlanlar!$B$5:$B$126,MATCH(C49,İlanlar!$AA$5:$AA$126,0)) -> Red Bull | C49: 1 | D49: =INDEX(İlanlar!$C$5:$C$126,MATCH(C49,İlanlar!$AA$5:$AA$126,0)) -> IT Sales Applications Project Manager | E49: =INDEX(İlanlar!$D$5:$D$126,MATCH(C49,İlanlar!$AA$5:$AA$126,0)) -> Elsbethen | F49: =INDEX(İlanlar!$G$5:$G$126,MATCH(C49,İlanlar!$AA$5:$AA$126,0)) -> EN (+DE artı) | G49: =INDEX(İlanlar!$Z$5:$Z$126,MATCH(C49,İlanlar!$AA$5:$AA$126,0)) -> 0.91 | H49: =INDEX(İlanlar!$AB$5:$AB$126,MATCH(C49,İlanlar!$AA$5:$AA$126,0)) -> A – Hemen başvur (İngilizce) | I49: =HYPERLINK(INDEX(İlanlar!$N$5:$N$126,MATCH(C49,İlanlar!$AA$5:$AA$126,0)),"ilanı aç") -> ilanı aç
B50: =INDEX(İlanlar!$B$5:$B$126,MATCH(C50,İlanlar!$AA$5:$AA$126,0)) -> SKIDATA GmbH | C50: 2 | D50: =INDEX(İlanlar!$C$5:$C$126,MATCH(C50,İlanlar!$AA$5:$AA$126,0)) -> Senior Project Manager - Delivery Execution & Multi-Team Governance (m/f/d) | E50: =INDEX(İlanlar!$D$5:$D$126,MATCH(C50,İlanlar!$AA$5:$AA$126,0)) -> Wals | F50: =INDEX(İlanlar!$G$5:$G$126,MATCH(C50,İlanlar!$AA$5:$AA$126,0)) -> EN | G50: =INDEX(İlanlar!$Z$5:$Z$126,MATCH(C50,İlanlar!$AA$5:$AA$126,0)) -> 0.87 | H50: =INDEX(İlanlar!$AB$5:$AB$126,MATCH(C50,İlanlar!$AA$5:$AA$126,0)) -> A – Hemen başvur (İngilizce) | I50: =HYPERLINK(INDEX(İlanlar!$N$5:$N$126,MATCH(C50,İlanlar!$AA$5:$AA$126,0)),"ilanı aç") -> ilanı aç
B51: =INDEX(İlanlar!$B$5:$B$126,MATCH(C51,İlanlar!$AA$5:$AA$126,0)) -> Red Bull | C51: 3 | D51: =INDEX(İlanlar!$C$5:$C$126,MATCH(C51,İlanlar!$AA$5:$AA$126,0)) -> IT Project Manager - Legal Solutions | E51: =INDEX(İlanlar!$D$5:$D$126,MATCH(C51,İlanlar!$AA$5:$AA$126,0)) -> Elsbethen | F51: =INDEX(İlanlar!$G$5:$G$126,MATCH(C51,İlanlar!$AA$5:$AA$126,0)) -> EN (+DE artı) | G51: =INDEX(İlanlar!$Z$5:$Z$126,MATCH(C51,İlanlar!$AA$5:$AA$126,0)) -> 0.85 | H51: =INDEX(İlanlar!$AB$5:$AB$126,MATCH(C51,İlanlar!$AA$5:$AA$126,0)) -> A – Hemen başvur (İngilizce) | I51: =HYPERLINK(INDEX(İlanlar!$N$5:$N$126,MATCH(C51,İlanlar!$AA$5:$AA$126,0)),"ilanı aç") -> ilanı aç
B52: =INDEX(İlanlar!$B$5:$B$126,MATCH(C52,İlanlar!$AA$5:$AA$126,0)) -> Red Bull | C52: 4 | D52: =INDEX(İlanlar!$C$5:$C$126,MATCH(C52,İlanlar!$AA$5:$AA$126,0)) -> Project Manager (Portfolio Management) | E52: =INDEX(İlanlar!$D$5:$D$126,MATCH(C52,İlanlar!$AA$5:$AA$126,0)) -> Elsbethen | F52: =INDEX(İlanlar!$G$5:$G$126,MATCH(C52,İlanlar!$AA$5:$AA$126,0)) -> EN | G52: =INDEX(İlanlar!$Z$5:$Z$126,MATCH(C52,İlanlar!$AA$5:$AA$126,0)) -> 0.85 | H52: =INDEX(İlanlar!$AB$5:$AB$126,MATCH(C52,İlanlar!$AA$5:$AA$126,0)) -> A – Hemen başvur (İngilizce) | I52: =HYPERLINK(INDEX(İlanlar!$N$5:$N$126,MATCH(C52,İlanlar!$AA$5:$AA$126,0)),"ilanı aç") -> ilanı aç
B53: =INDEX(İlanlar!$B$5:$B$126,MATCH(C53,İlanlar!$AA$5:$AA$126,0)) -> Red Bull | C53: 5 | D53: =INDEX(İlanlar!$C$5:$C$126,MATCH(C53,İlanlar!$AA$5:$AA$126,0)) -> Application Security Service Manager | E53: =INDEX(İlanlar!$D$5:$D$126,MATCH(C53,İlanlar!$AA$5:$AA$126,0)) -> Elsbethen | F53: =INDEX(İlanlar!$G$5:$G$126,MATCH(C53,İlanlar!$AA$5:$AA$126,0)) -> EN (+DE artı) | G53: =INDEX(İlanlar!$Z$5:$Z$126,MATCH(C53,İlanlar!$AA$5:$AA$126,0)) -> 0.85 | H53: =INDEX(İlanlar!$AB$5:$AB$126,MATCH(C53,İlanlar!$AA$5:$AA$126,0)) -> A – Hemen başvur (İngilizce) | I53: =HYPERLINK(INDEX(İlanlar!$N$5:$N$126,MATCH(C53,İlanlar!$AA$5:$AA$126,0)),"ilanı aç") -> ilanı aç
B54: =INDEX(İlanlar!$B$5:$B$126,MATCH(C54,İlanlar!$AA$5:$AA$126,0)) -> Red Bull | C54: 6 | D54: =INDEX(İlanlar!$C$5:$C$126,MATCH(C54,İlanlar!$AA$5:$AA$126,0)) -> IT Team Manager - Global Field Sales Applications | E54: =INDEX(İlanlar!$D$5:$D$126,MATCH(C54,İlanlar!$AA$5:$AA$126,0)) -> Elsbethen | F54: =INDEX(İlanlar!$G$5:$G$126,MATCH(C54,İlanlar!$AA$5:$AA$126,0)) -> EN (+DE artı) | G54: =INDEX(İlanlar!$Z$5:$Z$126,MATCH(C54,İlanlar!$AA$5:$AA$126,0)) -> 0.85 | H54: =INDEX(İlanlar!$AB$5:$AB$126,MATCH(C54,İlanlar!$AA$5:$AA$126,0)) -> A – Hemen başvur (İngilizce) | I54: =HYPERLINK(INDEX(İlanlar!$N$5:$N$126,MATCH(C54,İlanlar!$AA$5:$AA$126,0)),"ilanı aç") -> ilanı aç
B55: =INDEX(İlanlar!$B$5:$B$126,MATCH(C55,İlanlar!$AA$5:$AA$126,0)) -> TransUnion | C55: 7 | D55: =INDEX(İlanlar!$C$5:$C$126,MATCH(C55,İlanlar!$AA$5:$AA$126,0)) -> Technical Project Manager | E55: =INDEX(İlanlar!$D$5:$D$126,MATCH(C55,İlanlar!$AA$5:$AA$126,0)) -> Salzburg, Salzburg, Austria | F55: =INDEX(İlanlar!$G$5:$G$126,MATCH(C55,İlanlar!$AA$5:$AA$126,0)) -> EN | G55: =INDEX(İlanlar!$Z$5:$Z$126,MATCH(C55,İlanlar!$AA$5:$AA$126,0)) -> 0.84 | H55: =INDEX(İlanlar!$AB$5:$AB$126,MATCH(C55,İlanlar!$AA$5:$AA$126,0)) -> A – Hemen başvur (İngilizce) | I55: =HYPERLINK(INDEX(İlanlar!$N$5:$N$126,MATCH(C55,İlanlar!$AA$5:$AA$126,0)),"ilanı aç") -> ilanı aç
B56: =INDEX(İlanlar!$B$5:$B$126,MATCH(C56,İlanlar!$AA$5:$AA$126,0)) -> Red Bull | C56: 8 | D56: =INDEX(İlanlar!$C$5:$C$126,MATCH(C56,İlanlar!$AA$5:$AA$126,0)) -> IT Project / Application Manager - Production Application | E56: =INDEX(İlanlar!$D$5:$D$126,MATCH(C56,İlanlar!$AA$5:$AA$126,0)) -> Elsbethen | F56: =INDEX(İlanlar!$G$5:$G$126,MATCH(C56,İlanlar!$AA$5:$AA$126,0)) -> EN (+DE artı) | G56: =INDEX(İlanlar!$Z$5:$Z$126,MATCH(C56,İlanlar!$AA$5:$AA$126,0)) -> 0.82 | H56: =INDEX(İlanlar!$AB$5:$AB$126,MATCH(C56,İlanlar!$AA$5:$AA$126,0)) -> A – Hemen başvur (İngilizce) | I56: =HYPERLINK(INDEX(İlanlar!$N$5:$N$126,MATCH(C56,İlanlar!$AA$5:$AA$126,0)),"ilanı aç") -> ilanı aç
B57: =INDEX(İlanlar!$B$5:$B$126,MATCH(C57,İlanlar!$AA$5:$AA$126,0)) -> Amer Sports | C57: 9 | D57: =INDEX(İlanlar!$C$5:$C$126,MATCH(C57,İlanlar!$AA$5:$AA$126,0)) -> OT-Security Domain Manager(m/f/d) | E57: =INDEX(İlanlar!$D$5:$D$126,MATCH(C57,İlanlar!$AA$5:$AA$126,0)) -> Altenmarkt im Pongau, Salzburg, Austria | F57: =INDEX(İlanlar!$G$5:$G$126,MATCH(C57,İlanlar!$AA$5:$AA$126,0)) -> EN | G57: =INDEX(İlanlar!$Z$5:$Z$126,MATCH(C57,İlanlar!$AA$5:$AA$126,0)) -> 0.81 | H57: =INDEX(İlanlar!$AB$5:$AB$126,MATCH(C57,İlanlar!$AA$5:$AA$126,0)) -> A – Hemen başvur (İngilizce) | I57: =HYPERLINK(INDEX(İlanlar!$N$5:$N$126,MATCH(C57,İlanlar!$AA$5:$AA$126,0)),"ilanı aç") -> ilanı aç
B58: =INDEX(İlanlar!$B$5:$B$126,MATCH(C58,İlanlar!$AA$5:$AA$126,0)) -> epunkt GmbH | C58: 10 | D58: =INDEX(İlanlar!$C$5:$C$126,MATCH(C58,İlanlar!$AA$5:$AA$126,0)) -> IT Allrounder (w/m/x) | E58: =INDEX(İlanlar!$D$5:$D$126,MATCH(C58,İlanlar!$AA$5:$AA$126,0)) -> Bezirk Vöcklabruck | F58: =INDEX(İlanlar!$G$5:$G$126,MATCH(C58,İlanlar!$AA$5:$AA$126,0)) -> EN (+DE artı) | G58: =INDEX(İlanlar!$Z$5:$Z$126,MATCH(C58,İlanlar!$AA$5:$AA$126,0)) -> 0.805 | H58: =INDEX(İlanlar!$AB$5:$AB$126,MATCH(C58,İlanlar!$AA$5:$AA$126,0)) -> A – Hemen başvur (İngilizce) | I58: =HYPERLINK(INDEX(İlanlar!$N$5:$N$126,MATCH(C58,İlanlar!$AA$5:$AA$126,0)),"ilanı aç") -> ilanı aç
B59: =INDEX(İlanlar!$B$5:$B$126,MATCH(C59,İlanlar!$AA$5:$AA$126,0)) -> TransUnion | C59: 11 | D59: =INDEX(İlanlar!$C$5:$C$126,MATCH(C59,İlanlar!$AA$5:$AA$126,0)) -> Senior Systems Administrator | E59: =INDEX(İlanlar!$D$5:$D$126,MATCH(C59,İlanlar!$AA$5:$AA$126,0)) -> Salzburg, Salzburg, Austria | F59: =INDEX(İlanlar!$G$5:$G$126,MATCH(C59,İlanlar!$AA$5:$AA$126,0)) -> EN | G59: =INDEX(İlanlar!$Z$5:$Z$126,MATCH(C59,İlanlar!$AA$5:$AA$126,0)) -> 0.795 | H59: =INDEX(İlanlar!$AB$5:$AB$126,MATCH(C59,İlanlar!$AA$5:$AA$126,0)) -> A – Hemen başvur (İngilizce) | I59: =HYPERLINK(INDEX(İlanlar!$N$5:$N$126,MATCH(C59,İlanlar!$AA$5:$AA$126,0)),"ilanı aç") -> ilanı aç
B60: =INDEX(İlanlar!$B$5:$B$126,MATCH(C60,İlanlar!$AA$5:$AA$126,0)) -> Red Bull | C60: 12 | D60: =INDEX(İlanlar!$C$5:$C$126,MATCH(C60,İlanlar!$AA$5:$AA$126,0)) -> IT Infrastructure Engineer | E60: =INDEX(İlanlar!$D$5:$D$126,MATCH(C60,İlanlar!$AA$5:$AA$126,0)) -> Thalgau | F60: =INDEX(İlanlar!$G$5:$G$126,MATCH(C60,İlanlar!$AA$5:$AA$126,0)) -> EN (+DE artı) | G60: =INDEX(İlanlar!$Z$5:$Z$126,MATCH(C60,İlanlar!$AA$5:$AA$126,0)) -> 0.79 | H60: =INDEX(İlanlar!$AB$5:$AB$126,MATCH(C60,İlanlar!$AA$5:$AA$126,0)) -> A – Hemen başvur (İngilizce) | I60: =HYPERLINK(INDEX(İlanlar!$N$5:$N$126,MATCH(C60,İlanlar!$AA$5:$AA$126,0)),"ilanı aç") -> ilanı aç
... B78: =INDEX(İlanlar!$B$5:$B$126,MATCH(C78,İlanlar!$AA$5:$AA$126,0)) -> Arvai Plastics GmbH & CoKG | C78: 30 | D78: =INDEX(İlanlar!$C$5:$C$126,MATCH(C78,İlanlar!$AA$5:$AA$126,0)) -> IT-Systemadministrator (m/w/d) | E78: =INDEX(İlanlar!$D$5:$D$126,MATCH(C78,İlanlar!$AA$5:$AA$126,0)) -> Neumarkt am Wallersee | F78: =INDEX(İlanlar!$G$5:$G$126,MATCH(C78,İlanlar!$AA$5:$AA$126,0)) -> DE+EN | G78: =INDEX(İlanlar!$Z$5:$Z$126,MATCH(C78,İlanlar!$AA$5:$AA$126,0)) -> 0.69 | H78: =INDEX(İlanlar!$AB$5:$AB$126,MATCH(C78,İlanlar!$AA$5:$AA$126,0)) -> C – Opsiyonel | I78: =HYPERLINK(INDEX(İlanlar!$N$5:$N$126,MATCH(C78,İlanlar!$AA$5:$AA$126,0)),"ilanı aç") -> ilanı aç
B80: ÖNEMLİ NOTLAR
B81: 1) Bu sürüm SIFIRDAN canlı taramayla üretildi (27.09.2026). karriere.at'te 50+ anahtar kelime (IT, Security, ISMS, Systemadministrator, IT-Leiter, Netzwerk, Service Manager…) × Salzburg + Mondsee/Mattighofen/Braunau; LinkedIn'de 37 anahtar kelime × Salzburg 50 km (son 30 gün); Red Bull resmi iş API'si; ACP portalı. Toplam 281 ham kayıt → 234 benzersiz → 122 profile uygun ilan.
B82: 2) Her ilanın linki açıldı: karriere.at'te ilan sayfası + JobPosting verisi, LinkedIn'de 'No longer accepting applications' yokluğu, Red Bull'da resmi sayfa; ayrıca sayfa başlığı pozisyon adıyla eşleştirildi. Kapanmış ilanlar karriere.at'te arama sayfasına yönlendiği için otomatik elendi. 'Link kontrol' sütununda saat ve HTTP kodu var.
B83: 3) İNGİLİZCE ÖNCELİKLİ (27.09 güncellemesi): İngilizcenin yettiği ilanlar listenin başında; dil ağırlığı %30, Almanca isteyen ilanların dil puanı düşürüldü (akıcı Almanca = 1/5). 'A – Hemen başvur' sadece İngilizce ilanlara verilir. Dil şartı, gereksinimler, eşleşen beceriler ve eksikler ilanın TAM METNİNDEN okundu (tahmin değil). Almanca şartının alıntısı 'Almanca şartı (ilandan)' sütununda.
B84: 4) ÖNCEKİ LİSTE: 43 aktif ilanın sadece 14'ü canlı çıktı. TECHSEARCH IT-Teamleiter 2023'ten, grinnberg ilanları 2024'ten kalma; Red Bull Windows/Security Incident, Palfinger Infrastructure Ops Manager ve Wüstenrot ISM kapanmış. Ayrıntı: 'Önceki Liste Kontrolü' sayfası. Daha önce hazırlanan 6 CV'den sadece PALFINGER Cyber Security Engineer hâlâ geçerli.
B85: 5) Maaş: Avusturya'da ilanlarda yıllık/aylık brüt yazılır (14 maaş). 'Sadece KV asgarisi' = toplu sözleşme alt sınırı; gerçek teklif genelde belirgin şekilde üstündedir (Red Bull gibi).
B86: 6) StepStone.at bot koruması (403) ve AMS eJob-Room giriş şartı nedeniyle otomatik taranamadı; bu iki portalda aynı aramaları elle yapmak faydalı olur (İş Portalları sayfası).
B87: 7) İlanlar hızla kapanır: başvurmadan hemen önce linke tıkla. Liste haftada bir yeniden taranmalı.

Sheet İlanlar
A1: Aktif İş İlanları – Salzburg & Çevresi (IT + Cyber Security tek liste, uyuma göre sıralı) · canlı tarama 27.09.2026
A2: Tüm linkler açılıp test edildi · Mavi = düzenlenebilir puan (1–5) · Filtre: F (alan), G (dil), AB (öncelik)
T3: PUANLAR (1–5)
A4: No | B4: Firma | C4: Pozisyon | D4: Lokasyon | E4: Salzburg'dan ulaşım | F4: Alan | G4: Çalışma dili | H4: Almanca şartı (ilandan alıntı) | I4: Türkçe | J4: Kıdem | K4: Maaş (ilandan) | L4: Yayın / güncelleme tarihi | M4: Kaynak | N4: İLAN LİNKİ (canlı test ✓) | O4: Link kontrol | P4: Yedek link(ler) (aynı ilan, test ✓) | Q4: Temel gereksinimler (ilandan) | R4: CV ile eşleşenler | S4: Eksikler / riskler | T4: Teknik | U4: Deneyim | V4: Dil | W4: Sektör | X4: Lokasyon | Y4: Maaş | Z4: Uyum % | AA4: Sıra | AB4: Öncelik | AC4: Önerilen aksiyon | AD4: Firmanın tüm açık ilanları | AE4: Sıralama skoru (İngilizce önce)
A5: 1 | B5: Red Bull | C5: IT Sales Applications Project Manager | D5: Elsbethen | E5: ≤30 dk (Salzburg / yakın çevre) | F5: IT proje yönetimi | G5: EN (+DE artı) | H5: PMP or PRINCE2) is considered an advantage Fluent English skills, German is a plus At least five years of experience in delivering IT projects | I5: — | J5: Kıdemli / yönetici | K5: Sadece KV asgarisi: ~€33k/yıl (ab 2.362 € monatlich) – gerçek maaş belirtilmemiş, genelde üstünde | L5: 2026-09-27 | M5: Red Bull resmi | N5: https://jobs.redbull.com/at-de/it-sales-applications-project-manager-ref33553h | O5: 27.09.2026 14:14 · HTTP 200 · AÇIK | P5: https://www.karriere.at/jobs/7867234 | Q5: Vollzeit IT Sales Applications Project Manager Elsbethen, Österreich Apply now As part of our Sales Applications Team, this role involves shaping the future of our business application landscape. By leading strategic IT initiatives across Sales, Finance, and eCommerce, you'll drive digital transformation, enable business growth, and deliver solutions that create value on a global scale. As an IT Sales Applications Pr… | R5: ITIL / ITSM, Proje yönetimi, Bütçe, Risk yönetimi, Politika / uyum | S5: SAP, İş uygulaması alanı (CRM/ERP/Legal/ServiceNow…) | T5: 4 | U5: 5 | V5: 5 | W5: 5 | X5: 5 | Y5: 3.5 | Z5: =ROUND((T5*Özet!$C$14+U5*Özet!$C$15+V5*Özet!$C$16+W5*Özet!$C$17+X5*Özet!$C$18+Y5*Özet!$C$19)/5,4) -> 0.91 | AA5: =RANK(AE5,$AE$5:$AE$126)+COUNTIF($AE$5:AE5,AE5)-1 -> 1 | AB5: =IF(AND(OR(G5="EN",G5="EN (+DE artı)"),Z5>=0.7),"A – Hemen başvur (İngilizce)",IF(Z5>=0.7,"B – Başvur (Almanca gerekli)",IF(AND(OR(G5="EN",G5="EN (+DE artı)"),Z5>=0.6),"B – Başvur (İngilizce)","C – Opsiyonel"))) -> A – Hemen başvur (İngilizce) | AC5: İngilizce CV + ön yazı ile başvur | AD5: https://www.karriere.at/f/red-bull | AE5: =Z5+IF(OR(G5="EN",G5="EN (+DE artı)"),1,0) -> 1.91
A6: 2 | B6: SKIDATA GmbH | C6: Senior Project Manager - Delivery Execution & Multi-Team Governance (m/f/d) | D6: Wals | E6: ≤30 dk (Salzburg / yakın çevre) | F6: IT proje yönetimi | G6: EN | H6: Almanca şartı belirtilmemiş | I6: — | J6: Kıdemli / yönetici | K6: İlanda belirtilmemiş | L6: 2026-09-20 | M6: karriere.at | N6: https://www.karriere.at/jobs/7854275 | O6: 27.09.2026 14:14 · HTTP 200 · AÇIK | P6: https://www.linkedin.com/jobs/view/4446017342 | Q6: 10+ years of project or program management experience. Proven track record in large-scale software, cloud, or product delivery programs. Strong experience in delivery governance, execution control, and stakeholder management. Demonstrated ability to coordinate multiple development teams and complex dependencies. Excellent communication and executive reporting skills. Experience working in Agile, Waterfall, or hybrid… | R6: Ekip liderliği, Risk yönetimi, Politika / uyum | S6: 10+ yıl büyük yazılım/ürün teslimat programı yönetimi şartı | T6: 3.5 | U6: 5 | V6: 5 | W6: 4 | X6: 5 | Y6: 3.5 | Z6: =ROUND((T6*Özet!$C$14+U6*Özet!$C$15+V6*Özet!$C$16+W6*Özet!$C$17+X6*Özet!$C$18+Y6*Özet!$C$19)/5,4) -> 0.87 | AA6: =RANK(AE6,$AE$5:$AE$126)+COUNTIF($AE$5:AE6,AE6)-1 -> 2 | AB6: =IF(AND(OR(G6="EN",G6="EN (+DE artı)"),Z6>=0.7),"A – Hemen başvur (İngilizce)",IF(Z6>=0.7,"B – Başvur (Almanca gerekli)",IF(AND(OR(G6="EN",G6="EN (+DE artı)"),Z6>=0.6),"B – Başvur (İngilizce)","C – Opsiyonel"))) -> A – Hemen başvur (İngilizce) | AC6: İngilizce CV + ön yazı ile başvur | AD6: https://www.karriere.at/f/skidata | AE6: =Z6+IF(OR(G6="EN",G6="EN (+DE artı)"),1,0) -> 1.87
A7: 3 | B7: Red Bull | C7: IT Project Manager - Legal Solutions | D7: Elsbethen | E7: ≤30 dk (Salzburg / yakın çevre) | F7: IT proje yönetimi | G7: EN (+DE artı) | H7: language skills are an advantage At least three years of experience m | I7: — | J7: Kıdemli / yönetici | K7: Sadece KV asgarisi: ~€33k/yıl (ab 2.362 € monatlich) – gerçek maaş belirtilmemiş, genelde üstünde | L7: 2026-09-21 | M7: Red Bull resmi | N7: https://jobs.redbull.com/at-de/it-project-manager-legal-solutions-ref33927j | O7: 27.09.2026 14:13 · HTTP 200 · AÇIK | P7: https://www.karriere.at/jobs/7875472 https://www.linkedin.com/jobs/view/4466092730 https://www.linkedin.com/jobs/view/4472017663 | Q7: Vollzeit IT Project Manager - Legal Solutions Elsbethen, Österreich Apply now Are you ready to turn complex challenges into smart, scalable solutions and make things happen? As a technically savvy Project Manager with an analytical mindset and a passion for holistic business solutions, you'll advance the digitalisation of the Legal business domain. Join our Cross Functional & Legal Projects team (sitting in Elsbethen… | R7: ITIL / ITSM, Proje yönetimi, Tedarikçi yönetimi, Bütçe, Ekip liderliği, Risk yönetimi, Politika / uyum | S7: ANA ŞART: İş uygulaması alanı (CRM/ERP/Legal/ServiceNow…), ANA ŞART: AI / ML | T7: 3 | U7: 5 | V7: 5 | W7: 5 | X7: 5 | Y7: 3.5 | Z7: =ROUND((T7*Özet!$C$14+U7*Özet!$C$15+V7*Özet!$C$16+W7*Özet!$C$17+X7*Özet!$C$18+Y7*Özet!$C$19)/5,4) -> 0.85 | AA7: =RANK(AE7,$AE$5:$AE$126)+COUNTIF($AE$5:AE7,AE7)-1 -> 3 | AB7: =IF(AND(OR(G7="EN",G7="EN (+DE artı)"),Z7>=0.7),"A – Hemen başvur (İngilizce)",IF(Z7>=0.7,"B – Başvur (Almanca gerekli)",IF(AND(OR(G7="EN",G7="EN (+DE artı)"),Z7>=0.6),"B – Başvur (İngilizce)","C – Opsiyonel"))) -> A – Hemen başvur (İngilizce) | AC7: İngilizce CV + ön yazı ile başvur | AD7: https://www.karriere.at/f/red-bull | AE7: =Z7+IF(OR(G7="EN",G7="EN (+DE artı)"),1,0) -> 1.85
A8: 4 | B8: Red Bull | C8: Project Manager (Portfolio Management) | D8: Elsbethen | E8: ≤30 dk (Salzburg / yakın çevre) | F8: IT proje yönetimi | G8: EN | H8: Almanca şartı belirtilmemiş | I8: — | J8: Kıdemli / yönetici | K8: Sadece KV asgarisi: ~€33k/yıl (ab 2.362 € monatlich) – gerçek maaş belirtilmemiş, genelde üstünde | L8: 2026-09-26 | M8: Red Bull resmi | N8: https://jobs.redbull.com/at-de/project-manager-portfolio-management-ref34093e | O8: 27.09.2026 14:13 · HTTP 200 · AÇIK | P8: https://www.karriere.at/jobs/7878376 https://www.linkedin.com/jobs/view/4468809516 | Q8: Vollzeit Project Manager (Portfolio Management) Elsbethen, Österreich Apply now We are seeking an experienced and proactive Project Manager to lead strategic initiatives within the Supply Chain domain, operating as part of the Portfolio Management function in the CFO organization. In this pivotal role, you will be involved across the end-to-end supply chain operations and help to shape the evolution of our global sup… | R8: ITIL / ITSM, Proje yönetimi, Bütçe, Ekip liderliği, Risk yönetimi, Microsoft ortamı | S8: DİKKAT: IT rolü değil – Supply Chain / CFO portföy PMO (Red Bull'da 'Finance' fonksiyonu); supply chain alan bilgisi | T8: 3 | U8: 5 | V8: 5 | W8: 5 | X8: 5 | Y8: 3.5 | Z8: =ROUND((T8*Özet!$C$14+U8*Özet!$C$15+V8*Özet!$C$16+W8*Özet!$C$17+X8*Özet!$C$18+Y8*Özet!$C$19)/5,4) -> 0.85 | AA8: =RANK(AE8,$AE$5:$AE$126)+COUNTIF($AE$5:AE8,AE8)-1 -> 4 | AB8: =IF(AND(OR(G8="EN",G8="EN (+DE artı)"),Z8>=0.7),"A – Hemen başvur (İngilizce)",IF(Z8>=0.7,"B – Başvur (Almanca gerekli)",IF(AND(OR(G8="EN",G8="EN (+DE artı)"),Z8>=0.6),"B – Başvur (İngilizce)","C – Opsiyonel"))) -> A – Hemen başvur (İngilizce) | AC8: İngilizce CV + ön yazı ile başvur | AD8: https://www.karriere.at/f/red-bull | AE8: =Z8+IF(OR(G8="EN",G8="EN (+DE artı)"),1,0) -> 1.85
A9: 5 | B9: Red Bull | C9: Application Security Service Manager | D9: Elsbethen | E9: ≤30 dk (Salzburg / yakın çevre) | F9: Cyber Security – yönetişim / ISMS | G9: EN (+DE artı) | H9: Informatics, or equivalent experience Fluent English skills, German is a plus At least three years of experience in application security, | I9: — | J9: Kıdemli / yönetici | K9: Sadece KV asgarisi: ~€35k/yıl (ab 2.535 € monatlich) – gerçek maaş belirtilmemiş, genelde üstünde | L9: 2026-09-26 | M9: Red Bull resmi | N9: https://jobs.redbull.com/at-de/application-security-service-manager-ref33475n | O9: 27.09.2026 14:13 · HTTP 200 · AÇIK | P9: https://www.karriere.at/jobs/7865764 https://www.linkedin.com/jobs/view/4459310475 | Q9: Vollzeit Application Security Service Manager Elsbethen, Österreich Apply now Are you ready to help shape the future of secure software development at Red Bull? As part of our Digital Security team, you will play a key role in safeguarding custom software development and advancing our application security capabilities. Partnering closely with security peers, engineering, development, and product teams, you will drive… | R9: Tedarikçi yönetimi, Bütçe, Ekip liderliği, Politika / uyum | S9: ANA ŞART: Programlama, ANA ŞART: Pentest, ANA ŞART: Application security / secure SDLC, AI / ML | T9: 3 | U9: 5 | V9: 5 | W9: 5 | X9: 5 | Y9: 3.5 | Z9: =ROUND((T9*Özet!$C$14+U9*Özet!$C$15+V9*Özet!$C$16+W9*Özet!$C$17+X9*Özet!$C$18+Y9*Özet!$C$19)/5,4) -> 0.85 | AA9: =RANK(AE9,$AE$5:$AE$126)+COUNTIF($AE$5:AE9,AE9)-1 -> 5 | AB9: =IF(AND(OR(G9="EN",G9="EN (+DE artı)"),Z9>=0.7),"A – Hemen başvur (İngilizce)",IF(Z9>=0.7,"B – Başvur (Almanca gerekli)",IF(AND(OR(G9="EN",G9="EN (+DE artı)"),Z9>=0.6),"B – Başvur (İngilizce)","C – Opsiyonel"))) -> A – Hemen başvur (İngilizce) | AC9: İngilizce CV + ön yazı ile başvur | AD9: https://www.karriere.at/f/red-bull | AE9: =Z9+IF(OR(G9="EN",G9="EN (+DE artı)"),1,0) -> 1.85
A10: 6 | B10: Red Bull | C10: IT Team Manager - Global Field Sales Applications | D10: Elsbethen | E10: ≤30 dk (Salzburg / yakın çevre) | F10: IT yönetimi / liderlik | G10: EN (+DE artı) | H10: study or equivalent practical experience Fluent English skills, German is a plus At least 5 years of working experience with field sales app | I10: — | J10: Kıdemli / yönetici | K10: Sadece KV asgarisi: ~€40k/yıl (ab 2.879 € monatlich) – gerçek maaş belirtilmemiş, genelde üstünde | L10: 2026-09-21 | M10: Red Bull resmi | N10: https://jobs.redbull.com/at-de/elsbethen-it-manager-global-field-sales-applications-ref31287p | O10: 27.09.2026 14:14 · HTTP 200 · AÇIK | P10: https://www.karriere.at/jobs/7879372 | Q10: Vollzeit IT Team Manager - Global Field Sales Applications Elsbethen, Österreich Apply now To support our ambitious sales roadmap, we are looking for an IT Manager Global Field Sales Applications, who will drive the global IT field sales tool strategy with a bold, future‑focused agenda. In this role you'll sit in IT and at the frontline of Sales, turning ambitious commercial goals into a powerful, AI‑enabled applicat… | R10: Proje yönetimi, Ekip liderliği, Politika / uyum, Perakende / çok lokasyon | S10: Scripting / otomasyon (PowerShell vb.), ANA ŞART: İş uygulaması alanı (CRM/ERP/Legal/ServiceNow…), ANA ŞART: AI / ML | T10: 3 | U10: 5 | V10: 5 | W10: 5 | X10: 5 | Y10: 3.5 | Z10: =ROUND((T10*Özet!$C$14+U10*Özet!$C$15+V10*Özet!$C$16+W10*Özet!$C$17+X10*Özet!$C$18+Y10*Özet!$C$19)/5,4) -> 0.85 | AA10: =RANK(AE10,$AE$5:$AE$126)+COUNTIF($AE$5:AE10,AE10)-1 -> 6 | AB10: =IF(AND(OR(G10="EN",G10="EN (+DE artı)"),Z10>=0.7),"A – Hemen başvur (İngilizce)",IF(Z10>=0.7,"B – Başvur (Almanca gerekli)",IF(AND(OR(G10="EN",G10="EN (+DE artı)"),Z10>=0.6),"B – Başvur (İngilizce)","C – Opsiyonel"))) -> A – Hemen başvur (İngilizce) | AC10: İngilizce CV + ön yazı ile başvur | AD10: https://www.karriere.at/f/red-bull | AE10: =Z10+IF(OR(G10="EN",G10="EN (+DE artı)"),1,0) -> 1.85
A11: 7 | B11: TransUnion | C11: Technical Project Manager | D11: Salzburg, Salzburg, Austria | E11: ≤30 dk (Salzburg / yakın çevre) | F11: IT proje yönetimi | G11: EN | H11: Almanca şartı belirtilmemiş | I11: — | J11: Kıdemli / yönetici | K11: İlanda belirtilmemiş | L11: 2026-09-25 | M11: LinkedIn | N11: https://www.linkedin.com/jobs/view/4470334048 | O11: 27.09.2026 14:14 · HTTP 200 · AÇIK | Q11: TransUnion's Job Applicant Privacy Notice Team Overview Our team designs and develops solutions that strengthen secure, reliable communication across telecommunication networks. Our platforms are integrated into the ecosystem and technical infrastructure of mobile operators across Europe where our services process and analyze voice calls and messages to improve security and customer engagement for millions of end con… | R11: Ağ / Firewall / VPN, Proje yönetimi | S11: Programlama, ANA ŞART: AWS / GCP | T11: 3 | U11: 5 | V11: 5 | W11: 4 | X11: 5 | Y11: 3.5 | Z11: =ROUND((T11*Özet!$C$14+U11*Özet!$C$15+V11*Özet!$C$16+W11*Özet!$C$17+X11*Özet!$C$18+Y11*Özet!$C$19)/5,4) -> 0.84 | AA11: =RANK(AE11,$AE$5:$AE$126)+COUNTIF($AE$5:AE11,AE11)-1 -> 7 | AB11: =IF(AND(OR(G11="EN",G11="EN (+DE artı)"),Z11>=0.7),"A – Hemen başvur (İngilizce)",IF(Z11>=0.7,"B – Başvur (Almanca gerekli)",IF(AND(OR(G11="EN",G11="EN (+DE artı)"),Z11>=0.6),"B – Başvur (İngilizce)","C – Opsiyonel"))) -> A – Hemen başvur (İngilizce) | AC11: İngilizce CV + ön yazı ile başvur | AD11: https://www.linkedin.com/company/transunion | AE11: =Z11+IF(OR(G11="EN",G11="EN (+DE artı)"),1,0) -> 1.84
A12: 8 | B12: Red Bull | C12: IT Project / Application Manager - Production Application | D12: Elsbethen | E12: ≤30 dk (Salzburg / yakın çevre) | F12: IT proje yönetimi | G12: EN (+DE artı) | H12: English skills, German is a plus Sound knowledge of business processes in the field of produ | I12: — | J12: Kıdemli / yönetici | K12: Sadece KV asgarisi: ~€35k/yıl (ab 2.471 € monatlich) – gerçek maaş belirtilmemiş, genelde üstünde | L12: 2026-09-25 | M12: Red Bull resmi | N12: https://jobs.redbull.com/at-de/elsbethen-it-project-application-manager-production-application--ref26935q | O12: 27.09.2026 14:13 · HTTP 200 · AÇIK | P12: https://www.karriere.at/jobs/7709477 https://www.linkedin.com/jobs/view/4342957903 | Q12: Vollzeit IT Project / Application Manager - Production Application Elsbethen, Österreich Apply now Are you ready to make an impact where innovation meets operations? If you thrive in fast-paced environments, if you have a passion for optimizing systems, and you are ready to take ownership of transformative initiatives, we want you on our team to help us set new standards in SAP excellence! As an IT Project / Applicat… | R12: Proje yönetimi, Tedarikçi yönetimi, Bütçe | S12: ANA ŞART: SAP, ANA ŞART: İş uygulaması alanı (CRM/ERP/Legal/ServiceNow…) | T12: 2.5 | U12: 5 | V12: 5 | W12: 5 | X12: 5 | Y12: 3.5 | Z12: =ROUND((T12*Özet!$C$14+U12*Özet!$C$15+V12*Özet!$C$16+W12*Özet!$C$17+X12*Özet!$C$18+Y12*Özet!$C$19)/5,4) -> 0.82 | AA12: =RANK(AE12,$AE$5:$AE$126)+COUNTIF($AE$5:AE12,AE12)-1 -> 8 | AB12: =IF(AND(OR(G12="EN",G12="EN (+DE artı)"),Z12>=0.7),"A – Hemen başvur (İngilizce)",IF(Z12>=0.7,"B – Başvur (Almanca gerekli)",IF(AND(OR(G12="EN",G12="EN (+DE artı)"),Z12>=0.6),"B – Başvur (İngilizce)","C – Opsiyonel"))) -> A – Hemen başvur (İngilizce) | AC12: İngilizce CV + ön yazı ile başvur | AD12: https://www.karriere.at/f/red-bull | AE12: =Z12+IF(OR(G12="EN",G12="EN (+DE artı)"),1,0) -> 1.82
A13: 9 | B13: Amer Sports | C13: OT-Security Domain Manager(m/f/d) | D13: Altenmarkt im Pongau, Salzburg, Austria | E13: 60–90 dk | F13: Cyber Security – yönetişim / ISMS | G13: EN | H13: Almanca şartı belirtilmemiş | I13: — | J13: Kıdemli / yönetici | K13: İlanda belirtilmemiş | L13: 2026-09-27 | M13: LinkedIn | N13: https://www.linkedin.com/jobs/view/4438189985 | O13: 27.09.2026 14:14 · HTTP 200 · AÇIK | Q13: Hybrid / Altenmarkt im Pongau, Austria We’re looking for OT Security Domain Manager for Amer Sports ’ office in Altenmarkt im Pongau At Amer Sports, we are looking for an OT Security Domain Manager to lead and drive Operational Technology (OT) security across our global supply chain network. In this strategic role you will help safeguard manufacturing sites and distribution centers by embedding security into operatio… | R13: ISO 27001 / ISMS, ITIL / ITSM, Ağ / Firewall / VPN, Tedarikçi yönetimi, Ekip liderliği, Risk yönetimi, Politika / uyum, Denetim / audit | S13: Scripting / otomasyon (PowerShell vb.), SIEM / SOC / EDR, NIS-2 / DORA / TISAX, CISSP / CISM / CISA, ANA ŞART: OT / SCADA güvenliği | T13: 3.5 | U13: 5 | V13: 5 | W13: 4 | X13: 2 | Y13: 3.5 | Z13: =ROUND((T13*Özet!$C$14+U13*Özet!$C$15+V13*Özet!$C$16+W13*Özet!$C$17+X13*Özet!$C$18+Y13*Özet!$C$19)/5,4) -> 0.81 | AA13: =RANK(AE13,$AE$5:$AE$126)+COUNTIF($AE$5:AE13,AE13)-1 -> 9 | AB13: =IF(AND(OR(G13="EN",G13="EN (+DE artı)"),Z13>=0.7),"A – Hemen başvur (İngilizce)",IF(Z13>=0.7,"B – Başvur (Almanca gerekli)",IF(AND(OR(G13="EN",G13="EN (+DE artı)"),Z13>=0.6),"B – Başvur (İngilizce)","C – Opsiyonel"))) -> A – Hemen başvur (İngilizce) | AC13: İngilizce CV + ön yazı ile başvur · İletişim: talentacquisition@amersports.com | AD13: https://fi.linkedin.com/company/amer-sports | AE13: =Z13+IF(OR(G13="EN",G13="EN (+DE artı)"),1,0) -> 1.81
A14: 10 | B14: epunkt GmbH | C14: IT Allrounder (w/m/x) | D14: Bezirk Vöcklabruck | E14: 60–90 dk | F14: IT destek / service desk | G14: EN (+DE artı) | H14: gutes Englisch (Unternehmenssprache),Deutsch ist ein Plus, aber nicht zwingend erforderlich | I14: — | J14: Orta / giriş – aday overqualified | K14: ~€50k+/yıl (ilan: 3.600 € – 4.400 € monatlich) | L14: 2026-09-24 | M14: karriere.at | N14: https://www.karriere.at/jobs/7869100 | O14: 27.09.2026 14:14 · HTTP 200 · AÇIK | P14: https://www.karriere.at/jobs/7881199 | Q14: & Erfahrung zwischen 3.600 EUR und 4.400 EUR brutto / Monat (auf Vollzeitbasis). Brutto Netto Rechner Das Unternehmen Ein international tätiges Technologieunternehmen entwickelt ein patentiertes, wissenschaftlich validiertes Fit-System und arbeitet mit führenden Marken zusammen, um Sport- und Performance-Equipment durch präzise Passform und bessere Kraftübertragung zu optimieren. Das Unternehmen ist global aufgestell… | R14: ITIL / ITSM, Windows Server, Sanallaştırma (Hyper-V/Proxmox), Backup / DR, Ağ / Firewall / VPN, Ekip liderliği, Politika / uyum, Perakende / çok lokasyon | S14: Belirgin teknik eksik yok | T14: 4.5 | U14: 3 | V14: 5 | W14: 3.5 | X14: 2 | Y14: 3.5 | Z14: =ROUND((T14*Özet!$C$14+U14*Özet!$C$15+V14*Özet!$C$16+W14*Özet!$C$17+X14*Özet!$C$18+Y14*Özet!$C$19)/5,4) -> 0.805 | AA14: =RANK(AE14,$AE$5:$AE$126)+COUNTIF($AE$5:AE14,AE14)-1 -> 10 | AB14: =IF(AND(OR(G14="EN",G14="EN (+DE artı)"),Z14>=0.7),"A – Hemen başvur (İngilizce)",IF(Z14>=0.7,"B – Başvur (Almanca gerekli)",IF(AND(OR(G14="EN",G14="EN (+DE artı)"),Z14>=0.6),"B – Başvur (İngilizce)","C – Opsiyonel"))) -> A – Hemen başvur (İngilizce) | AC14: İngilizce CV + ön yazı ile başvur · Personel danışmanı ilanı → danışmanı telefon/e-posta ile ara, diğer açık pozisyonlarını da sor | AD14: https://www.karriere.at/f/epunkt-linz | AE14: =Z14+IF(OR(G14="EN",G14="EN (+DE artı)"),1,0) -> 1.805
A15: 11 | B15: TransUnion | C15: Senior Systems Administrator | D15: Salzburg, Salzburg, Austria | E15: ≤30 dk (Salzburg / yakın çevre) | F15: Sistem / altyapı | G15: EN | H15: Almanca şartı belirtilmemiş | I15: — | J15: Kıdemli / yönetici | K15: İlanda belirtilmemiş | L15: 2026-09-16 | M15: LinkedIn | N15: https://www.linkedin.com/jobs/view/4430598895 | O15: 27.09.2026 14:14 · HTTP 200 · AÇIK | Q15: TransUnion's Job Applicant Privacy Notice Team Overview Our team designs and develops solutions that strengthen secure, reliable communication across telecommunication networks. Our platforms are integrated into the ecosystem and technical infrastructure of mobile operators across Europe where our services process and analyze voice calls and messages to improve security and customer engagement for millions of end con… | R15: ITIL / ITSM, Sanallaştırma (Hyper-V/Proxmox), Backup / DR, Ağ / Firewall / VPN, SQL Server / DB, Proje yönetimi, Politika / uyum | S15: ANA ŞART: Scripting / otomasyon (PowerShell vb.), ANA ŞART: Linux, Container / IaC / DevOps, AWS / GCP | T15: 2.5 | U15: 4.5 | V15: 5 | W15: 4 | X15: 5 | Y15: 3.5 | Z15: =ROUND((T15*Özet!$C$14+U15*Özet!$C$15+V15*Özet!$C$16+W15*Özet!$C$17+X15*Özet!$C$18+Y15*Özet!$C$19)/5,4) -> 0.795 | AA15: =RANK(AE15,$AE$5:$AE$126)+COUNTIF($AE$5:AE15,AE15)-1 -> 11 | AB15: =IF(AND(OR(G15="EN",G15="EN (+DE artı)"),Z15>=0.7),"A – Hemen başvur (İngilizce)",IF(Z15>=0.7,"B – Başvur (Almanca gerekli)",IF(AND(OR(G15="EN",G15="EN (+DE artı)"),Z15>=0.6),"B – Başvur (İngilizce)","C – Opsiyonel"))) -> A – Hemen başvur (İngilizce) | AC15: İngilizce CV + ön yazı ile başvur | AD15: https://www.linkedin.com/company/transunion | AE15: =Z15+IF(OR(G15="EN",G15="EN (+DE artı)"),1,0) -> 1.795
A16: 12 | B16: Red Bull | C16: IT Infrastructure Engineer | D16: Thalgau | E16: 30–45 dk | F16: Sistem / altyapı | G16: EN (+DE artı) | H16: oder gleichwertige Berufserfahrung Fließende Englischkenntnisse, Deutschkenntnisse sind von Vorteil Mindestens fünf Jahre Berufserfahrung in d | I16: — | J16: Uzman (mid-senior) | K16: Sadece KV asgarisi: ~€35k/yıl (ab 2.535 € monatlich) – gerçek maaş belirtilmemiş, genelde üstünde | L16: 2026-09-25 | M16: Red Bull resmi | N16: https://jobs.redbull.com/at-de/it-infrastructure-data-platform-engineer-ref33287a | O16: 27.09.2026 14:13 · HTTP 200 · AÇIK | P16: https://www.karriere.at/jobs/7861804 https://www.linkedin.com/jobs/view/4455736906 https://www.linkedin.com/jobs/view/4455733965 | Q16: Vollzeit IT Infrastructure Engineer Thalgau, Österreich Bewerben Bist du bereit, Technologien mitzugestalten, die Höchstleistungen im Sport ermöglichen? Als IT Infrastructure Engineer spielst du eine zentrale Rolle innerhalb der Corporate Projects IT und unterstützt das Athlete Performance Center (APC) sowie dessen Plattformen, Anwendungen, Infrastruktur und spezialisierte Sporttechnologien. Mit deiner Arbeit schaffs… | R16: ITIL / ITSM, Ağ / Firewall / VPN, Tedarikçi yönetimi, Politika / uyum, Microsoft ortamı | S16: Azure / Entra ID, ANA ŞART: Scripting / otomasyon (PowerShell vb.), Programlama, AWS / GCP | T16: 3 | U16: 4 | V16: 5 | W16: 5 | X16: 4 | Y16: 3 | Z16: =ROUND((T16*Özet!$C$14+U16*Özet!$C$15+V16*Özet!$C$16+W16*Özet!$C$17+X16*Özet!$C$18+Y16*Özet!$C$19)/5,4) -> 0.79 | AA16: =RANK(AE16,$AE$5:$AE$126)+COUNTIF($AE$5:AE16,AE16)-1 -> 12 | AB16: =IF(AND(OR(G16="EN",G16="EN (+DE artı)"),Z16>=0.7),"A – Hemen başvur (İngilizce)",IF(Z16>=0.7,"B – Başvur (Almanca gerekli)",IF(AND(OR(G16="EN",G16="EN (+DE artı)"),Z16>=0.6),"B – Başvur (İngilizce)","C – Opsiyonel"))) -> A – Hemen başvur (İngilizce) | AC16: İngilizce CV + ön yazı ile başvur | AD16: https://www.karriere.at/f/red-bull | AE16: =Z16+IF(OR(G16="EN",G16="EN (+DE artı)"),1,0) -> 1.79
A17: 13 | B17: Red Bull | C17: IT Project Manager - Sales Applications | D17: Elsbethen | E17: ≤30 dk (Salzburg / yakın çevre) | F17: IT proje yönetimi | G17: EN (+DE artı) | H17: or equivalent practical experience Fluent English skills, German is a plus At least 4 years of experience in the IT environment with a | I17: — | J17: Kıdemli / yönetici | K17: Sadece KV asgarisi: ~€33k/yıl (ab 2.362 € monatlich) – gerçek maaş belirtilmemiş, genelde üstünde | L17: 2026-09-20 | M17: Red Bull resmi | N17: https://jobs.redbull.com/at-de/elsbethen-it-project-manager-sales-applications--ref31123e | O17: 27.09.2026 14:14 · HTTP 200 · AÇIK | P17: https://www.karriere.at/jobs/7871212 | Q17: Vollzeit IT Project Manager - Sales Applications Elsbethen, Österreich Apply now To support our ambitious sales roadmap with exciting IT sales projects and new initiatives, we are expanding our Global IT Sales Projects team and are looking for a driven IT Project Manager in the area of sales applications. In this role, you will equip our global sales teams with the tools and "wings" they need to sell smarter, faster,… | R17: Proje yönetimi, Tedarikçi yönetimi, Bütçe, Risk yönetimi | S17: Azure / Entra ID, Scripting / otomasyon (PowerShell vb.), SAP, AWS / GCP, ANA ŞART: İş uygulaması alanı (CRM/ERP/Legal/ServiceNow…), ANA ŞART: AI / ML | T17: 1.5 | U17: 5 | V17: 5 | W17: 5 | X17: 5 | Y17: 3.5 | Z17: =ROUND((T17*Özet!$C$14+U17*Özet!$C$15+V17*Özet!$C$16+W17*Özet!$C$17+X17*Özet!$C$18+Y17*Özet!$C$19)/5,4) -> 0.76 | AA17: =RANK(AE17,$AE$5:$AE$126)+COUNTIF($AE$5:AE17,AE17)-1 -> 13 | AB17: =IF(AND(OR(G17="EN",G17="EN (+DE artı)"),Z17>=0.7),"A – Hemen başvur (İngilizce)",IF(Z17>=0.7,"B – Başvur (Almanca gerekli)",IF(AND(OR(G17="EN",G17="EN (+DE artı)"),Z17>=0.6),"B – Başvur (İngilizce)","C – Opsiyonel"))) -> A – Hemen başvur (İngilizce) | AC17: İngilizce CV + ön yazı ile başvur | AD17: https://www.karriere.at/f/red-bull | AE17: =Z17+IF(OR(G17="EN",G17="EN (+DE artı)"),1,0) -> 1.76
A18: 14 | B18: PALFINGER | C18: Cyber Security Engineer (f/m/d) | D18: Bergheim, Salzburg, Austria | E18: ≤30 dk (Salzburg / yakın çevre) | F18: Cyber Security – teknik | G18: EN | H18: Almanca şartı belirtilmemiş | I18: — | J18: Uzman (mid-senior) | K18: ~€53k+/yıl (ilan metninden) | L18: 2026-09-01 | M18: LinkedIn | N18: https://www.linkedin.com/jobs/view/4461705351 | O18: 27.09.2026 14:14 · HTTP 200 · AÇIK | Q18: At PALFINGER, we have been lifting goods to a new level for over 90 years - with a pioneering and passionate spirit. As a global technology and engineering company, we are the world's leading manufacturer and supplier of innovative crane and lifting solutions. Our success is based on the tireless efforts of our approximately 12,350 employees, who contribute their ideas and energy to our vision. With us, you can expec… | R18: ITIL / ITSM, Active Directory, Ağ / Firewall / VPN, Tedarikçi yönetimi, Politika / uyum, Denetim / audit, Microsoft ortamı | S18: ANA ŞART: Azure / Entra ID, Intune / M365 admin, Scripting / otomasyon (PowerShell vb.), SIEM / SOC / EDR, Ağ üreticisi sertifikası (Cisco/Fortinet/Palo Alto), CISSP / CISM / CISA | T18: 2 | U18: 4 | V18: 5 | W18: 4 | X18: 5 | Y18: 4 | Z18: =ROUND((T18*Özet!$C$14+U18*Özet!$C$15+V18*Özet!$C$16+W18*Özet!$C$17+X18*Özet!$C$18+Y18*Özet!$C$19)/5,4) -> 0.76 | AA18: =RANK(AE18,$AE$5:$AE$126)+COUNTIF($AE$5:AE18,AE18)-1 -> 14 | AB18: =IF(AND(OR(G18="EN",G18="EN (+DE artı)"),Z18>=0.7),"A – Hemen başvur (İngilizce)",IF(Z18>=0.7,"B – Başvur (Almanca gerekli)",IF(AND(OR(G18="EN",G18="EN (+DE artı)"),Z18>=0.6),"B – Başvur (İngilizce)","C – Opsiyonel"))) -> A – Hemen başvur (İngilizce) | AC18: İngilizce CV + ön yazı ile başvur | AD18: https://at.linkedin.com/company/palfinger | AE18: =Z18+IF(OR(G18="EN",G18="EN (+DE artı)"),1,0) -> 1.76
A19: 15 | B19: Aptean | C19: ERP Customer Support Consultant | D19: Salzburg, Austria | E19: ≤30 dk (Salzburg / yakın çevre) | F19: IT destek / service desk | G19: EN | H19: Almanca şartı belirtilmemiş | I19: — | J19: Orta / giriş – aday overqualified | K19: Sadece KV asgarisi: ~€36k/yıl (ilan metni) – gerçek maaş belirtilmemiş, genelde üstünde | L19: 2026-09-22 | M19: LinkedIn | N19: https://www.linkedin.com/jobs/view/4459659551 | O19: 27.09.2026 14:14 · HTTP 200 · AÇIK | Q19: Customer Support Consultant (m/w/d) mit Fokus auf Rechnungswesen Bergheim bei Salzburg | Hybrid Was die Menschen bei Aptean eint, ist ihr Engagement, Kundenprozesse zu vereinfachen und Erwartungen zu übertreffen. Unsere gemeinsame Vision ist die Entwicklung modernster ERP-Softwarelösungen für Mittel- und Großbetriebe. Wir wachsen überdurchschnittlich und suchen DICH zur Verstärkung unseres Customer Service Teams. Du… | R19: SQL Server / DB, Tedarikçi yönetimi, Politika / uyum | S19: Programlama, ANA ŞART: İş uygulaması alanı (CRM/ERP/Legal/ServiceNow…), ANA ŞART: AI / ML | T19: 2.5 | U19: 3 | V19: 5 | W19: 4 | X19: 5 | Y19: 3 | Z19: =ROUND((T19*Özet!$C$14+U19*Özet!$C$15+V19*Özet!$C$16+W19*Özet!$C$17+X19*Özet!$C$18+Y19*Özet!$C$19)/5,4) -> 0.74 | AA19: =RANK(AE19,$AE$5:$AE$126)+COUNTIF($AE$5:AE19,AE19)-1 -> 15 | AB19: =IF(AND(OR(G19="EN",G19="EN (+DE artı)"),Z19>=0.7),"A – Hemen başvur (İngilizce)",IF(Z19>=0.7,"B – Başvur (Almanca gerekli)",IF(AND(OR(G19="EN",G19="EN (+DE artı)"),Z19>=0.6),"B – Başvur (İngilizce)","C – Opsiyonel"))) -> A – Hemen başvur (İngilizce) | AC19: İngilizce CV + ön yazı ile başvur | AD19: https://www.linkedin.com/company/aptean | AE19: =Z19+IF(OR(G19="EN",G19="EN (+DE artı)"),1,0) -> 1.74
A20: 16 | B20: SKIDATA | C20: Product Security Engineer (mfd) | D20: Wals-Siezenheim, Salzburg, Austria | E20: ≤30 dk (Salzburg / yakın çevre) | F20: Cyber Security – teknik | G20: EN | H20: Almanca şartı belirtilmemiş | I20: — | J20: Uzman (mid-senior) | K20: İlanda belirtilmemiş | L20: 2026-09-19 | M20: LinkedIn | N20: https://www.linkedin.com/jobs/view/4440762411 | O20: 27.09.2026 14:14 · HTTP 200 · AÇIK | Q20: Strong experience with secure coding practices and code analysis tools Solid threat modeling expertise and hands-on penetration testing experience Sound knowledge of OWASP principles and IT security standards (ISO 27001, NIST Cybersecurity, PCI DSS, or similar) Familiarity with DevOps practices and tools Proficiency in programming languages such as Java, C#, or .NET Experience with cloud services, Docker, and microse… | R20: ISO 27001 / ISMS | S20: Container / IaC / DevOps, ANA ŞART: Programlama, Pentest, ANA ŞART: Application security / secure SDLC | T20: 1.5 | U20: 4 | V20: 5 | W20: 4 | X20: 5 | Y20: 3 | Z20: =ROUND((T20*Özet!$C$14+U20*Özet!$C$15+V20*Özet!$C$16+W20*Özet!$C$17+X20*Özet!$C$18+Y20*Özet!$C$19)/5,4) -> 0.71 | AA20: =RANK(AE20,$AE$5:$AE$126)+COUNTIF($AE$5:AE20,AE20)-1 -> 16 | AB20: =IF(AND(OR(G20="EN",G20="EN (+DE artı)"),Z20>=0.7),"A – Hemen başvur (İngilizce)",IF(Z20>=0.7,"B – Başvur (Almanca gerekli)",IF(AND(OR(G20="EN",G20="EN (+DE artı)"),Z20>=0.6),"B – Başvur (İngilizce)","C – Opsiyonel"))) -> A – Hemen başvur (İngilizce) | AC20: İngilizce CV + ön yazı ile başvur | AD20: https://at.linkedin.com/company/skidata-ag | AE20: =Z20+IF(OR(G20="EN",G20="EN (+DE artı)"),1,0) -> 1.71
A21: 17 | B21: Rehrl+Partner Personalberatung GmbH | C21: Leitung IT-Infrastruktur (m/w/d) | D21: Salzburg, Salzburg, Austria | E21: ≤30 dk (Salzburg / yakın çevre) | F21: IT yönetimi / liderlik | G21: DE | H21: İlan Almanca; seviye belirtilmemiş | I21: — | J21: Kıdemli / yönetici | K21: ~€100k+/yıl (ilan metninden) | L21: 2026-09-21 | M21: LinkedIn | N21: https://www.linkedin.com/jobs/view/4462230078 | O21: 27.09.2026 14:14 · HTTP 200 · AÇIK | Q21: Abgeschlossene Ausbildung im Bereich IT, IT-Management oder Informatik Mehrjährige Berufserfahrung in der IT-Infrastruktur sowie umfangreiche Führungserfahrung Idealerweise Erfahrung in der produzierenden Industrie mit internationalen Standorten Fundierte Kenntnisse in der Koordination komplexer operativer IT-Einheiten sowie Dienstleister Sicherer Umgang mit Budget- und Vertragsangelegenheiten, hohes Kennzahlenbewuss… | R21: Ağ / Firewall / VPN, Tedarikçi yönetimi, Bütçe, Ekip liderliği, Perakende / çok lokasyon | S21: Belirgin teknik eksik yok | T21: 5 | U21: 5 | V21: 1.5 | W21: 3.5 | X21: 5 | Y21: 5 | Z21: =ROUND((T21*Özet!$C$14+U21*Özet!$C$15+V21*Özet!$C$16+W21*Özet!$C$17+X21*Özet!$C$18+Y21*Özet!$C$19)/5,4) -> 0.775 | AA21: =RANK(AE21,$AE$5:$AE$126)+COUNTIF($AE$5:AE21,AE21)-1 -> 17 | AB21: =IF(AND(OR(G21="EN",G21="EN (+DE artı)"),Z21>=0.7),"A – Hemen başvur (İngilizce)",IF(Z21>=0.7,"B – Başvur (Almanca gerekli)",IF(AND(OR(G21="EN",G21="EN (+DE artı)"),Z21>=0.6),"B – Başvur (İngilizce)","C – Opsiyonel"))) -> B – Başvur (Almanca gerekli) | AC21: Almanca CV + Anschreiben ile başvur (Almanca B1/B2 belirt) · Personel danışmanı ilanı → danışmanı telefon/e-posta ile ara, diğer açık pozisyonlarını da sor | AD21: https://at.linkedin.com/company/rehrl-partner-personalberatung-gmbh | AE21: =Z21+IF(OR(G21="EN",G21="EN (+DE artı)"),1,0) -> 0.775
A22: 18 | B22: KERN engineering careers GmbH | C22: Information Security Consultant (w/m/d) | D22: Graz, Klagenfurt, Salzburg, Wels, Wien | E22: ≤30 dk (Salzburg / yakın çevre) | F22: Cyber Security – yönetişim / ISMS | G22: DE+EN | H22: und die Fähigkeit, komplexe Sachverhalte verständlich in Deutsch & Englisch zu vermitteln Sicheres Auftreten im Kundenkontakt sowie Fr | I22: — | J22: Kıdemli / yönetici | K22: ~€70k+/yıl (ilan: 5.000 € – 6.000 € monatlich) | L22: 2026-09-25 | M22: karriere.at | N22: https://www.karriere.at/jobs/7829969 | O22: 27.09.2026 14:13 · HTTP 200 · AÇIK | Q22: wie ISO 2700x und NIS2 ; Zertifizierungen von Vorteil Ausgeprägte Kommunikationsstärke und die Fähigkeit, komplexe Sachverhalte verständlich in Deutsch & Englisch zu vermitteln Sicheres Auftreten im Kundenkontakt sowie Freude an der Arbeit in einem beratenden Umfeld Worauf man sich freuen kann Eine verantwortungsvolle Position mit großem Gestaltungsspielraum in einem wachsenden Marktsegment Flexible Arbeitszeiten sow… | R22: ITIL / ITSM, Ekip liderliği, Denetim / audit | S22: NIS-2 / DORA / TISAX | T22: 4.5 | U22: 5 | V22: 2 | W22: 3.5 | X22: 5 | Y22: 5 | Z22: =ROUND((T22*Özet!$C$14+U22*Özet!$C$15+V22*Özet!$C$16+W22*Özet!$C$17+X22*Özet!$C$18+Y22*Özet!$C$19)/5,4) -> 0.775 | AA22: =RANK(AE22,$AE$5:$AE$126)+COUNTIF($AE$5:AE22,AE22)-1 -> 18 | AB22: =IF(AND(OR(G22="EN",G22="EN (+DE artı)"),Z22>=0.7),"A – Hemen başvur (İngilizce)",IF(Z22>=0.7,"B – Başvur (Almanca gerekli)",IF(AND(OR(G22="EN",G22="EN (+DE artı)"),Z22>=0.6),"B – Başvur (İngilizce)","C – Opsiyonel"))) -> B – Başvur (Almanca gerekli) | AC22: Almanca CV ile başvur; İngilizce yeterliliğini ve Almanca B1/B2'yi açıkça yaz · Personel danışmanı ilanı → danışmanı telefon/e-posta ile ara, diğer açık pozisyonlarını da sor · İletişim: j.wagner@kern-partner.at | AD22: https://www.karriere.at/f/kern-engineering-careers | AE22: =Z22+IF(OR(G22="EN",G22="EN (+DE artı)"),1,0) -> 0.775
A23: 19 | B23: Salzburger Abfallbeseitigung GmbH | C23: Koordinator für Informationssicherheit und Managementsysteme (m/w/d) | D23: Salzburg (Stadt) | E23: ≤30 dk (Salzburg / yakın çevre) | F23: Cyber Security – yönetişim / ISMS | G23: DE | H23: İlan Almanca; seviye belirtilmemiş | I23: — | J23: Kıdemli / yönetici | K23: ~€60k+/yıl (ilan: ab 4.320 € monatlich) | L23: 2026-09-22 | M23: karriere.at | N23: https://www.karriere.at/jobs/10033426 | O23: 27.09.2026 14:14 · HTTP 200 · AÇIK | Q23: Eine abgeschlossene Ausbildung mit IT-Schwerpunkt, etwa HTL, FH, Universität oder IT-Lehre mit entsprechender Berufserfahrung. Praktische Erfahrung mit IT-Systemen, Netzwerken und grundlegenden Sicherheitsmaßnahmen. Idealerweise eine abgeschlossene Zusatzausbildung im Qualitätsmanagement, in der internen Auditierung oder in integrierten Managementsystemen (z. B. TÜV AUSTRIA, TÜV SÜD oder einem vergleichbaren Anbieter… | R23: Backup / DR, Ağ / Firewall / VPN, Tedarikçi yönetimi, Ekip liderliği, Risk yönetimi, Politika / uyum, Denetim / audit, Perakende / çok lokasyon | S23: NIS-2 / DORA / TISAX | T23: 5 | U23: 5 | V23: 1.5 | W23: 4 | X23: 5 | Y23: 4.5 | Z23: =ROUND((T23*Özet!$C$14+U23*Özet!$C$15+V23*Özet!$C$16+W23*Özet!$C$17+X23*Özet!$C$18+Y23*Özet!$C$19)/5,4) -> 0.77 | AA23: =RANK(AE23,$AE$5:$AE$126)+COUNTIF($AE$5:AE23,AE23)-1 -> 19 | AB23: =IF(AND(OR(G23="EN",G23="EN (+DE artı)"),Z23>=0.7),"A – Hemen başvur (İngilizce)",IF(Z23>=0.7,"B – Başvur (Almanca gerekli)",IF(AND(OR(G23="EN",G23="EN (+DE artı)"),Z23>=0.6),"B – Başvur (İngilizce)","C – Opsiyonel"))) -> B – Başvur (Almanca gerekli) | AC23: Almanca CV + Anschreiben ile başvur (Almanca B1/B2 belirt) | AD23: https://www.karriere.at/f/salzburger-abfallbeseitigung | AE23: =Z23+IF(OR(G23="EN",G23="EN (+DE artı)"),1,0) -> 0.77
A24: 20 | B24: Xenium AG | C24: Lead IT Consultant Digitalisierung & Projektleitung (m/w/d) | D24: Salzburg, Austria | E24: ≤30 dk (Salzburg / yakın çevre) | F24: IT proje yönetimi | G24: DE+EN | H24: kommunizierst sicher auf Deutsch und Englisch und bist etwa 1–2 Tage pro Woche beim Kunden vor Ort Dei | I24: — | J24: Kıdemli / yönetici | K24: ~€83k+/yıl (ilan metninden) | L24: 2026-09-07 | M24: LinkedIn | N24: https://www.linkedin.com/jobs/view/4461881030 | O24: 27.09.2026 14:14 · HTTP 200 · AÇIK | Q24: Du hast ein Studium im MINT- oder wirtschaftsnahen Bereich mit IT-Bezug erfolgreich abgeschlossen Du bringst Erfahrung im IT-Consulting sowie in der Führung von Projekten oder Teams mit Du überzeugst durch Empathie, Souveränität und klare Kommunikation Du denkst analytisch, arbeitest konzeptionell und treibst Digitalisierungsthemen mit Begeisterung voran Du denkst analytisch­ und konzeptionell­ und bist klar und präz… | R24: Proje yönetimi, Ekip liderliği | S24: Belirgin teknik eksik yok | T24: 4 | U24: 5 | V24: 2 | W24: 4 | X24: 5 | Y24: 5 | Z24: =ROUND((T24*Özet!$C$14+U24*Özet!$C$15+V24*Özet!$C$16+W24*Özet!$C$17+X24*Özet!$C$18+Y24*Özet!$C$19)/5,4) -> 0.75 | AA24: =RANK(AE24,$AE$5:$AE$126)+COUNTIF($AE$5:AE24,AE24)-1 -> 20 | AB24: =IF(AND(OR(G24="EN",G24="EN (+DE artı)"),Z24>=0.7),"A – Hemen başvur (İngilizce)",IF(Z24>=0.7,"B – Başvur (Almanca gerekli)",IF(AND(OR(G24="EN",G24="EN (+DE artı)"),Z24>=0.6),"B – Başvur (İngilizce)","C – Opsiyonel"))) -> B – Başvur (Almanca gerekli) | AC24: Almanca CV ile başvur; İngilizce yeterliliğini ve Almanca B1/B2'yi açıkça yaz | AD24: https://de.linkedin.com/company/xenium-ag | AE24: =Z24+IF(OR(G24="EN",G24="EN (+DE artı)"),1,0) -> 0.75
A25: 21 | B25: x-tention Informationstechnologie GmbH | C25: Senior Cyber Security Consultant & Project Manager (m/w/d) | D25: Klagenfurt am Wörthersee, Wien, St. Peter in der Au, Graz, Wels, Salzburg (Stadt) | E25: ≤30 dk (Salzburg / yakın çevre) | F25: Cyber Security – yönetişim / ISMS | G25: DE+EN | H25: & private Vergaben) von Vorteil Stark in Präsentation & Moderation (Deutsch und Englisch) Zertifizierungen wie CISSP, CISM, ITIL sowie Projektman | I25: — | J25: Kıdemli / yönetici | K25: ~€65k+/yıl (ilan: 4.610 € – 5.715 € monatlich) | L25: 2026-09-22 | M25: karriere.at | N25: https://www.karriere.at/jobs/10033472 | O25: 27.09.2026 14:13 · HTTP 200 · AÇIK | Q25: Mehrjährige Erfahrung im Cybersecurity-Consulting und/oder Projektmanagement Fundiertes Know-how im SIEM/SOC-Umfeld, Use-Cases, Runbooks & KPI/SLAs Erfahrung in Ausschreibungsbearbeitung (öffentliche & private Vergaben) von Vorteil Stark in Präsentation & Moderation (Deutsch und Englisch) Zertifizierungen wie CISSP, CISM, ITIL sowie Projektmanagement-Standards wie IPMA oder PRINCE2/PMP von Vorteil Strukturierte, lösu… | R25: ITIL / ITSM, Proje yönetimi, Bütçe, Ekip liderliği, Risk yönetimi, Perakende / çok lokasyon | S25: ANA ŞART: SIEM / SOC / EDR, CISSP / CISM / CISA | T25: 4 | U25: 5 | V25: 2 | W25: 4 | X25: 5 | Y25: 4.5 | Z25: =ROUND((T25*Özet!$C$14+U25*Özet!$C$15+V25*Özet!$C$16+W25*Özet!$C$17+X25*Özet!$C$18+Y25*Özet!$C$19)/5,4) -> 0.74 | AA25: =RANK(AE25,$AE$5:$AE$126)+COUNTIF($AE$5:AE25,AE25)-1 -> 21 | AB25: =IF(AND(OR(G25="EN",G25="EN (+DE artı)"),Z25>=0.7),"A – Hemen başvur (İngilizce)",IF(Z25>=0.7,"B – Başvur (Almanca gerekli)",IF(AND(OR(G25="EN",G25="EN (+DE artı)"),Z25>=0.6),"B – Başvur (İngilizce)","C – Opsiyonel"))) -> B – Başvur (Almanca gerekli) | AC25: Almanca CV ile başvur; İngilizce yeterliliğini ve Almanca B1/B2'yi açıkça yaz | AD25: https://www.karriere.at/f/x-tention-informationstechnologie | AE25: =Z25+IF(OR(G25="EN",G25="EN (+DE artı)"),1,0) -> 0.74
A26: 22 | B26: Soulkitchen Group | C26: IT-Manager (m/w/d) | D26: Salzburg, Salzburg, Austria | E26: ≤30 dk (Salzburg / yakın çevre) | F26: IT yönetimi / liderlik | G26: DE C1 | H26: an unseren Standorten in Österreich und Deutschland Sehr gute Deutsch- und Englischkenntnisse Führerschein Klasse B WIR GARANTIEREN DIR Ein | I26: — | J26: Kıdemli / yönetici | K26: ~€56k+/yıl (ilan metninden) | L26: 2026-09-24 | M26: LinkedIn | N26: https://www.linkedin.com/jobs/view/4469750644 | O26: 27.09.2026 14:14 · HTTP 200 · AÇIK | Q26: über die Umsetzung bis hin zum laufenden Betrieb. Bei Neu-, Um- und Ausbauprojekten begleitest du den gesamten IT-Prozess von der Planung bis zur Inbetriebnahme. Du konzipierst Netzwerk, WLAN, Verkabelung und Netzwerkschränke, definierst die benötigte IT- und Store-Ausstattung, koordinierst externe Partner und Gewerke und stellst eine professionelle technische Abnahme sowie eine reibungslose Übergabe in den laufenden… | R26: Ağ / Firewall / VPN, Tedarikçi yönetimi, Ekip liderliği, Microsoft ortamı, Perakende / çok lokasyon | S26: Almanca C1 / çok iyi Almanca | T26: 5 | U26: 5 | V26: 1 | W26: 5 | X26: 5 | Y26: 4 | Z26: =ROUND((T26*Özet!$C$14+U26*Özet!$C$15+V26*Özet!$C$16+W26*Özet!$C$17+X26*Özet!$C$18+Y26*Özet!$C$19)/5,4) -> 0.74 | AA26: =RANK(AE26,$AE$5:$AE$126)+COUNTIF($AE$5:AE26,AE26)-1 -> 22 | AB26: =IF(AND(OR(G26="EN",G26="EN (+DE artı)"),Z26>=0.7),"A – Hemen başvur (İngilizce)",IF(Z26>=0.7,"B – Başvur (Almanca gerekli)",IF(AND(OR(G26="EN",G26="EN (+DE artı)"),Z26>=0.6),"B – Başvur (İngilizce)","C – Opsiyonel"))) -> B – Başvur (Almanca gerekli) | AC26: Almanca C1 isteniyor – yine de başvurmak istersen Almanca CV + dil planı (kurs/sertifika) belirt · İletişim: bewerbung@soulkitchen.world | AD26: https://at.linkedin.com/company/soulkitchen-group | AE26: =Z26+IF(OR(G26="EN",G26="EN (+DE artı)"),1,0) -> 0.74
A27: 23 | B27: HR Consulting Ines Schöffmann GmbH | C27: IT-Sicherheitsarchitekt:in | D27: Zell Am See, Salzburg, Austria | E27: 60–90 dk | F27: Cyber Security – yönetişim / ISMS | G27: DE+EN | H27: Breites Wissen im Bereich IT Security Projektleitungserfahrung Deutsch und Englisch Das Angebot Eine sichere Festanstellung in einem wirtsch | I27: — | J27: Kıdemli / yönetici | K27: ~€65k+/yıl (ilan metninden) | L27: 2026-09-23 | M27: LinkedIn | N27: https://www.linkedin.com/jobs/view/4470695814 | O27: 27.09.2026 14:14 · HTTP 200 · AÇIK | Q27: und triffst Technologientscheidungen planst und leitest Projekte Dazu kommen Dienstleister- und Schnittstellenmanagement, Dokumentation, Projektmitarbeit, etc. Dein Background Fundierter IT Hintergrund (HTL, Studium und/oder einschlägige Erfahrung) Breites Wissen im Bereich IT Security Projektleitungserfahrung Deutsch und Englisch Das Angebot Eine sichere Festanstellung in einem wirtschaftlich gesunden, eigentümergef… | R27: Proje yönetimi, Tedarikçi yönetimi, Risk yönetimi, Politika / uyum, Denetim / audit | S27: Pentest | T27: 5 | U27: 5 | V27: 2 | W27: 3.5 | X27: 2 | Y27: 4.5 | Z27: =ROUND((T27*Özet!$C$14+U27*Özet!$C$15+V27*Özet!$C$16+W27*Özet!$C$17+X27*Özet!$C$18+Y27*Özet!$C$19)/5,4) -> 0.735 | AA27: =RANK(AE27,$AE$5:$AE$126)+COUNTIF($AE$5:AE27,AE27)-1 -> 23 | AB27: =IF(AND(OR(G27="EN",G27="EN (+DE artı)"),Z27>=0.7),"A – Hemen başvur (İngilizce)",IF(Z27>=0.7,"B – Başvur (Almanca gerekli)",IF(AND(OR(G27="EN",G27="EN (+DE artı)"),Z27>=0.6),"B – Başvur (İngilizce)","C – Opsiyonel"))) -> B – Başvur (Almanca gerekli) | AC27: Almanca CV ile başvur; İngilizce yeterliliğini ve Almanca B1/B2'yi açıkça yaz · Personel danışmanı ilanı → danışmanı telefon/e-posta ile ara, diğer açık pozisyonlarını da sor · İletişim: office@hr-schoeffmann.at | AD27: https://www.linkedin.com/company/hr-consulting-ines-sch%C3%B6ffmann-gmbh | AE27: =Z27+IF(OR(G27="EN",G27="EN (+DE artı)"),1,0) -> 0.735
A28: 24 | B28: SPAR ICS – Information & Communication Services | C28: Product Lead IT Network (m/w/d) | D28: Wien, Salzburg (Stadt) | E28: ≤30 dk (Salzburg / yakın çevre) | F28: IT yönetimi / liderlik | G28: DE C1 | H28: Freude an der Zusammenarbeit mit internationalen Teams Fließenden Deutsch- und Englischkenntnissen in Wort und Schrift Darauf kannst du dich fr | I28: — | J28: Kıdemli / yönetici | K28: ~€60k+/yıl (ilan: ab 60.000 € jährlich) | L28: 2026-09-22 | M28: karriere.at | N28: https://www.karriere.at/jobs/7880023 | O28: 27.09.2026 14:13 · HTTP 200 · AÇIK | P28: https://www.linkedin.com/jobs/view/4470455077 | Q28: Mehrjähriger Berufserfahrung im Bereich Netzwerkarchitektur und Netzwerksicherheit Expertenwissen in Design, Implementierung und Administration von WAN-Lösungen Fundierten Kenntnissen moderner WAN- und LAN-Technologien sowie relevanter Protokolle (BGP, MPLS, WDM, QoS, Cisco SD-WAN, 5G WAN) Erfahrung in der Steuerung von Netzwerk-Service-Providern von Vorteil Kommunikationsstärke und der Fähigkeit, komplexe technische… | R28: Ağ / Firewall / VPN, Tedarikçi yönetimi, Perakende / çok lokasyon | S28: Almanca C1 / çok iyi Almanca, Ağ üreticisi sertifikası (Cisco/Fortinet/Palo Alto) | T28: 4.5 | U28: 5 | V28: 1 | W28: 5 | X28: 5 | Y28: 4.5 | Z28: =ROUND((T28*Özet!$C$14+U28*Özet!$C$15+V28*Özet!$C$16+W28*Özet!$C$17+X28*Özet!$C$18+Y28*Özet!$C$19)/5,4) -> 0.72 | AA28: =RANK(AE28,$AE$5:$AE$126)+COUNTIF($AE$5:AE28,AE28)-1 -> 24 | AB28: =IF(AND(OR(G28="EN",G28="EN (+DE artı)"),Z28>=0.7),"A – Hemen başvur (İngilizce)",IF(Z28>=0.7,"B – Başvur (Almanca gerekli)",IF(AND(OR(G28="EN",G28="EN (+DE artı)"),Z28>=0.6),"B – Başvur (İngilizce)","C – Opsiyonel"))) -> B – Başvur (Almanca gerekli) | AC28: Almanca C1 isteniyor – yine de başvurmak istersen Almanca CV + dil planı (kurs/sertifika) belirt | AD28: https://www.karriere.at/f/spar-ics-information-communication-services | AE28: =Z28+IF(OR(G28="EN",G28="EN (+DE artı)"),1,0) -> 0.72
A29: 25 | B29: Deloitte | C29: (Senior) Manager ServiceNow Architekt (all genders) | D29: Salzburg, Salzburg, Austria | E29: ≤30 dk (Salzburg / yakın çevre) | F29: IT servis yönetimi (ITIL) | G29: DE+EN | H29: besitzt exzellente kommunikative Fähigkeiten in Deutsch und Englisch Erfüllst du nicht alle genannten Kriterien? Kein Problem | I29: — | J29: Kıdemli / yönetici | K29: ~€67k+/yıl (ilan metninden) | L29: 2026-09-23 | M29: LinkedIn | N29: https://www.linkedin.com/jobs/view/4292781889 | O29: 27.09.2026 14:14 · HTTP 200 · AÇIK | Q29: Du hast ein abgeschlossenes Studium der Informatik oder verwandter Fachbereiche, bevorzugt mit Spezialisierung auf IT-Infrastruktur, Softwareentwicklung oder Data Science. Du bringst mindestens 5 Jahre Erfahrung in ITSM und/oder der Implementierung von ServiceNow mit, einschließlich Erfahrung in leitenden Positionen. Du verfügst über vertiefte Kenntnisse in der Architektur von IT-Lösungen und im Projektmanagement. Du… | R29: ITIL / ITSM, SQL Server / DB, Proje yönetimi, Ekip liderliği, Perakende / çok lokasyon | S29: Scripting / otomasyon (PowerShell vb.), Programlama, ANA ŞART: İş uygulaması alanı (CRM/ERP/Legal/ServiceNow…) | T29: 3.5 | U29: 5 | V29: 2 | W29: 4 | X29: 5 | Y29: 4.5 | Z29: =ROUND((T29*Özet!$C$14+U29*Özet!$C$15+V29*Özet!$C$16+W29*Özet!$C$17+X29*Özet!$C$18+Y29*Özet!$C$19)/5,4) -> 0.71 | AA29: =RANK(AE29,$AE$5:$AE$126)+COUNTIF($AE$5:AE29,AE29)-1 -> 25 | AB29: =IF(AND(OR(G29="EN",G29="EN (+DE artı)"),Z29>=0.7),"A – Hemen başvur (İngilizce)",IF(Z29>=0.7,"B – Başvur (Almanca gerekli)",IF(AND(OR(G29="EN",G29="EN (+DE artı)"),Z29>=0.6),"B – Başvur (İngilizce)","C – Opsiyonel"))) -> B – Başvur (Almanca gerekli) | AC29: Almanca CV ile başvur; İngilizce yeterliliğini ve Almanca B1/B2'yi açıkça yaz · İletişim: barrierefreiheit@deloitte.at. | AD29: https://www.linkedin.com/company/deloitte | AE29: =Z29+IF(OR(G29="EN",G29="EN (+DE artı)"),1,0) -> 0.71
A30: 26 | B30: ReqPOOL GmbH | C30: Projektmanager Beratung mit PO-Erfahrung für Software & Digitalisierung (m/w/d) im Bereich Energy | D30: Linz, Wien, Salzburg (Stadt) | E30: ≤30 dk (Salzburg / yakın çevre) | F30: IT proje yönetimi | G30: DE C1 | H30: mit PO-Zertifizierung (CSPO, PSPO) Du bist reisebereit im deutschsprachigen Raum, ergänzend zur Büro- und Home-Office-Arbeit Du sprichs | I30: — | J30: Kıdemli / yönetici | K30: ~€66k+/yıl (ilan: 66.000 € – 76.000 € jährlich) | L30: 2026-09-20 | M30: karriere.at | N30: https://www.karriere.at/jobs/7859100 | O30: 27.09.2026 14:14 · HTTP 200 · AÇIK | Q30: kritisch, übersetzt sie in umsetzbare Spezifikationen und managst Erwartungen zu Scope, Zeit und Budget Du erstellst Fachkonzepte (Screens, Navigations-, Rollen- und Rechtekonzepte), Business Cases, Prozessmodelle sowie Markt- und Datenanalysen, Ausschreibungsunterlagen und Benchmarkings - inklusive fachlichem Verständnis für Systemanbindungen und API-Design Du definierst fachliche Testfälle, nimmst Features ab, stim… | R30: Ağ / Firewall / VPN, Proje yönetimi, Bütçe, Ekip liderliği, Risk yönetimi | S30: Almanca C1 / çok iyi Almanca | T30: 4.5 | U30: 5 | V30: 1 | W30: 4 | X30: 5 | Y30: 4.5 | Z30: =ROUND((T30*Özet!$C$14+U30*Özet!$C$15+V30*Özet!$C$16+W30*Özet!$C$17+X30*Özet!$C$18+Y30*Özet!$C$19)/5,4) -> 0.71 | AA30: =RANK(AE30,$AE$5:$AE$126)+COUNTIF($AE$5:AE30,AE30)-1 -> 26 | AB30: =IF(AND(OR(G30="EN",G30="EN (+DE artı)"),Z30>=0.7),"A – Hemen başvur (İngilizce)",IF(Z30>=0.7,"B – Başvur (Almanca gerekli)",IF(AND(OR(G30="EN",G30="EN (+DE artı)"),Z30>=0.6),"B – Başvur (İngilizce)","C – Opsiyonel"))) -> B – Başvur (Almanca gerekli) | AC30: Almanca C1 isteniyor – yine de başvurmak istersen Almanca CV + dil planı (kurs/sertifika) belirt | AD30: https://www.karriere.at/f/reqpool | AE30: =Z30+IF(OR(G30="EN",G30="EN (+DE artı)"),1,0) -> 0.71
A31: 27 | B31: KTM AG | C31: Head of IT Infrastructure & Operations* | D31: Mattighofen | E31: 45–60 dk | F31: IT yönetimi / liderlik | G31: DE | H31: İlan Almanca; seviye belirtilmemiş | I31: — | J31: Kıdemli / yönetici | K31: ~€82k+/yıl (ilan: ab 81.500 € jährlich) | L31: 2026-09-26 | M31: karriere.at | N31: https://www.karriere.at/jobs/7852769 | O31: 27.09.2026 14:14 · HTTP 200 · AÇIK | Q31: Mehrjährige Berufs‑ und Führungserfahrung im IT‑Infrastructure‑ und/oder Operations‑Umfeld Fundierte Erfahrung in der Steuerung von operativen IT‑Einheiten, Dienstleistern und komplexen IT‑Betriebsstrukturen Erfahrung mit KPI‑, SLA‑ und Provider‑Management sowie Budget‑ und Vertragsverantwortung Fähigkeit, auch in komplexen oder unsicheren Situationen klare Entscheidungen zu treffen und konsequent umzusetzen Ausgeprä… | R31: Tedarikçi yönetimi, Bütçe, Ekip liderliği | S31: Linux | T31: 4.5 | U31: 5 | V31: 1.5 | W31: 4 | X31: 3 | Y31: 5 | Z31: =ROUND((T31*Özet!$C$14+U31*Özet!$C$15+V31*Özet!$C$16+W31*Özet!$C$17+X31*Özet!$C$18+Y31*Özet!$C$19)/5,4) -> 0.71 | AA31: =RANK(AE31,$AE$5:$AE$126)+COUNTIF($AE$5:AE31,AE31)-1 -> 27 | AB31: =IF(AND(OR(G31="EN",G31="EN (+DE artı)"),Z31>=0.7),"A – Hemen başvur (İngilizce)",IF(Z31>=0.7,"B – Başvur (Almanca gerekli)",IF(AND(OR(G31="EN",G31="EN (+DE artı)"),Z31>=0.6),"B – Başvur (İngilizce)","C – Opsiyonel"))) -> B – Başvur (Almanca gerekli) | AC31: Almanca CV + Anschreiben ile başvur (Almanca B1/B2 belirt) | AD31: https://www.karriere.at/f/ktm | AE31: =Z31+IF(OR(G31="EN",G31="EN (+DE artı)"),1,0) -> 0.71
A32: 28 | B32: ACP Gruppe | C32: Senior Operations Engineer m, w, d | D32: Salzburg | E32: ≤30 dk (Salzburg / yakın çevre) | F32: Sistem / altyapı | G32: DE | H32: İlan Almanca; seviye belirtilmemiş | I32: — | J32: Kıdemli / yönetici | K32: ~€60k+/yıl (ilan: ab 60.000 € jährlich) | L32: 2026-09-24 | M32: karriere.at | N32: https://www.karriere.at/jobs/7818680 | O32: 27.09.2026 14:13 · HTTP 200 · AÇIK | P32: https://bewerbung.acp-gruppe.com/at/rx/1119 | Q32: Analytisches Denken und strukturierte Problemlösung. Verantwortungsbewusstsein und Zuverlässigkeit. Kommunikations‑ und Teamfähigkeit. Sehr gute Kenntnisse im Bereich Hypervisor (VMware und Hyper-V). Sehr gute Kenntnisse im Microsoft Windows Bereich inkl. Rollen & Features. Sehr gute Kenntnisse bei Backup & Restore Systemen (Veeam und CommVault). Gute Netzwerkkenntnisse im Bereich Firewalls (Fortinet und Juniper), Sw… | R32: Windows Server, Sanallaştırma (Hyper-V/Proxmox), Backup / DR, Ağ / Firewall / VPN, Tedarikçi yönetimi, Bütçe, Microsoft ortamı, Perakende / çok lokasyon | S32: VMware, Ağ üreticisi sertifikası (Cisco/Fortinet/Palo Alto) | T32: 4 | U32: 4.5 | V32: 1.5 | W32: 4 | X32: 5 | Y32: 4.5 | Z32: =ROUND((T32*Özet!$C$14+U32*Özet!$C$15+V32*Özet!$C$16+W32*Özet!$C$17+X32*Özet!$C$18+Y32*Özet!$C$19)/5,4) -> 0.695 | AA32: =RANK(AE32,$AE$5:$AE$126)+COUNTIF($AE$5:AE32,AE32)-1 -> 28 | AB32: =IF(AND(OR(G32="EN",G32="EN (+DE artı)"),Z32>=0.7),"A – Hemen başvur (İngilizce)",IF(Z32>=0.7,"B – Başvur (Almanca gerekli)",IF(AND(OR(G32="EN",G32="EN (+DE artı)"),Z32>=0.6),"B – Başvur (İngilizce)","C – Opsiyonel"))) -> C – Opsiyonel | AC32: Almanca CV + Anschreiben ile başvur (Almanca B1/B2 belirt) | AD32: https://www.karriere.at/f/acp-gruppe | AE32: =Z32+IF(OR(G32="EN",G32="EN (+DE artı)"),1,0) -> 0.695
A33: 29 | B33: Senoplast Klepsch & Co GmbH | C33: IT Operations & Security Manager (m/w/d) | D33: Piesendorf | E33: 60–90 dk | F33: Cyber Security – yönetişim / ISMS | G33: DE | H33: İlan Almanca; seviye belirtilmemiş | I33: — | J33: Kıdemli / yönetici | K33: İlanda belirtilmemiş | L33: 2026-08-27 | M33: karriere.at | N33: https://www.karriere.at/jobs/10024962 | O33: 27.09.2026 14:13 · HTTP 200 · AÇIK | Q33: Mehrjährige Berufserfahrung im IT Operations Management, Security Information Management oder in einer kombinierten Rolle Gutes Verständnis von ITIL-orientierten Prozessen, insbesondere in den Bereichen Incident, Problem, Change und Service Management Verständnis für Security Information Management Strukturierte, eigenverantwortliche und ergebnisorientierte Arbeitsweise in einem modernen IT-Umfeld mit Fokus auf Veran… | R33: ISO 27001 / ISMS, ITIL / ITSM, Tedarikçi yönetimi, Perakende / çok lokasyon | S33: Belirgin teknik eksik yok | T33: 5 | U33: 5 | V33: 1.5 | W33: 4 | X33: 2 | Y33: 3.5 | Z33: =ROUND((T33*Özet!$C$14+U33*Özet!$C$15+V33*Özet!$C$16+W33*Özet!$C$17+X33*Özet!$C$18+Y33*Özet!$C$19)/5,4) -> 0.69 | AA33: =RANK(AE33,$AE$5:$AE$126)+COUNTIF($AE$5:AE33,AE33)-1 -> 29 | AB33: =IF(AND(OR(G33="EN",G33="EN (+DE artı)"),Z33>=0.7),"A – Hemen başvur (İngilizce)",IF(Z33>=0.7,"B – Başvur (Almanca gerekli)",IF(AND(OR(G33="EN",G33="EN (+DE artı)"),Z33>=0.6),"B – Başvur (İngilizce)","C – Opsiyonel"))) -> C – Opsiyonel | AC33: Almanca CV + Anschreiben ile başvur (Almanca B1/B2 belirt) | AD33: https://www.karriere.at/f/senoplast-klepsch | AE33: =Z33+IF(OR(G33="EN",G33="EN (+DE artı)"),1,0) -> 0.69
A34: 30 | B34: Arvai Plastics GmbH & CoKG | C34: IT-Systemadministrator (m/w/d) | D34: Neumarkt am Wallersee | E34: 30–45 dk | F34: Sistem / altyapı | G34: DE+EN | H34: Arbeitsweise Teamfähigkeit und Kommunikationsstärke Gute Deutsch- und Englischkenntnisse WIR BIETEN DIR Wachsendes Familienunternehmen | I34: — | J34: Uzman (mid-senior) | K34: Sadece KV asgarisi: ~€34k/yıl (ilan metni) – gerçek maaş belirtilmemiş, genelde üstünde | L34: 2026-09-22 | M34: karriere.at | N34: https://www.karriere.at/jobs/10030515 | O34: 27.09.2026 14:13 · HTTP 200 · AÇIK | Q34: und Berufserfahrungen; mögliche Überzahlungen werden selbstverständlich berücksichtigt. KV Mindestgehalt 2.427,90 EUR Benefits Aus- und Weiterbildung Gute Anbindung Team-Events Aus- und Weiterbildung Gute Anbindung Team-Events Alle Benefits anzeigen Weniger Benefits anzeigen INTERESSIERT? Wenn du eine neue Herausforderung in einem dynamischen Umfeld suchst, dann freuen wir uns auf deine aussagekräftige Bewerbung. Bei… | R34: Windows Server, Sanallaştırma (Hyper-V/Proxmox), Backup / DR, Ağ / Firewall / VPN, Ekip liderliği, Politika / uyum, Perakende / çok lokasyon | S34: Belirgin teknik eksik yok | T34: 4.5 | U34: 4 | V34: 2 | W34: 4 | X34: 4 | Y34: 3 | Z34: =ROUND((T34*Özet!$C$14+U34*Özet!$C$15+V34*Özet!$C$16+W34*Özet!$C$17+X34*Özet!$C$18+Y34*Özet!$C$19)/5,4) -> 0.69 | AA34: =RANK(AE34,$AE$5:$AE$126)+COUNTIF($AE$5:AE34,AE34)-1 -> 30 | AB34: =IF(AND(OR(G34="EN",G34="EN (+DE artı)"),Z34>=0.7),"A – Hemen başvur (İngilizce)",IF(Z34>=0.7,"B – Başvur (Almanca gerekli)",IF(AND(OR(G34="EN",G34="EN (+DE artı)"),Z34>=0.6),"B – Başvur (İngilizce)","C – Opsiyonel"))) -> C – Opsiyonel | AC34: Almanca CV ile başvur; İngilizce yeterliliğini ve Almanca B1/B2'yi açıkça yaz · İletişim: jobs@arvai-plastics.at. | AD34: https://www.karriere.at/f/arvai-plastics | AE34: =Z34+IF(OR(G34="EN",G34="EN (+DE artı)"),1,0) -> 0.69
A35: 31 | B35: SPAR ICS – Information & Communication Services | C35: Security Consultant - Vulnerability- und Exposure-Management (m/w/d) | D35: Salzburg (Stadt), Wien, Wernberg | E35: ≤30 dk (Salzburg / yakın çevre) | F35: Cyber Security – teknik | G35: DE+EN | H35: Agieren in der Beratungsrolle als Security Consultant Guten Deutsch- und fließenden Englischkenntnisse Teamgeist und der Fähigkeit, Veran | I35: — | J35: Kıdemli / yönetici | K35: ~€50k+/yıl (ilan: ab 50.000 € jährlich) | L35: 2026-09-22 | M35: karriere.at | N35: https://www.karriere.at/jobs/7868473 | O35: 27.09.2026 14:14 · HTTP 200 · AÇIK | P35: https://www.linkedin.com/jobs/view/4461268801 | Q35: Security Consultant - Vulnerability- und Exposure-Management (m/w/d) Wir sind das "I" und "T" in Retail... Dienstort: Salzburg, Wien, Wernberg Ausmaß: Vollzeit SPAR ICS ist die IT-Gesellschaft der SPAR Österreich-Gruppe und kümmert sich um sämtliche IT-Belange von SPAR, INTERSPAR und SES Spar European Shopping Centers. Wir sind über 700 kluge Köpfe und haben zwei Agenden: Das reibungslose Einkaufserlebnis aller SPAR-… | R35: Ekip liderliği, Perakende / çok lokasyon | S35: Belirgin teknik eksik yok | T35: 3.5 | U35: 4.5 | V35: 2 | W35: 5 | X35: 5 | Y35: 3.5 | Z35: =ROUND((T35*Özet!$C$14+U35*Özet!$C$15+V35*Özet!$C$16+W35*Özet!$C$17+X35*Özet!$C$18+Y35*Özet!$C$19)/5,4) -> 0.685 | AA35: =RANK(AE35,$AE$5:$AE$126)+COUNTIF($AE$5:AE35,AE35)-1 -> 31 | AB35: =IF(AND(OR(G35="EN",G35="EN (+DE artı)"),Z35>=0.7),"A – Hemen başvur (İngilizce)",IF(Z35>=0.7,"B – Başvur (Almanca gerekli)",IF(AND(OR(G35="EN",G35="EN (+DE artı)"),Z35>=0.6),"B – Başvur (İngilizce)","C – Opsiyonel"))) -> C – Opsiyonel | AC35: Almanca CV ile başvur; İngilizce yeterliliğini ve Almanca B1/B2'yi açıkça yaz | AD35: https://www.karriere.at/f/spar-ics-information-communication-services | AE35: =Z35+IF(OR(G35="EN",G35="EN (+DE artı)"),1,0) -> 0.685
A36: 32 | B36: Messezentrum Salzburg | C36: IT-ProjektmanagerIn / IT-SpezialistIn Daten & Anwendungen Service & IT (m/w/d) | D36: Salzburg (Stadt) | E36: ≤30 dk (Salzburg / yakın çevre) | F36: IT proje yönetimi | G36: DE | H36: İlan Almanca; seviye belirtilmemiş | I36: — | J36: Kıdemli / yönetici | K36: İlanda belirtilmemiş | L36: 2026-09-19 | M36: karriere.at | N36: https://www.karriere.at/jobs/10032419 | O36: 27.09.2026 14:13 · HTTP 200 · AÇIK | Q36: Unterstützung bei Deiner Weiterbildung und persönlichen Entwicklung Detaillierte Angaben zur Stelle Vollzeit (Festanstellung) Montag bis Freitag 38,5 Stunden Dienstort Salzburg (Stadt) Erforderliche Kenntnisse IT-Projektmanagement Datenbanken (MS SQL) Access Nice-To-Have Kenntnisse Jira Confluence MS Dynamics Erforderliche Ausbildung Abgeschlossene Ausbildung oder Studium mit IT-Schwerpunkt Detaillierte Angaben zur S… | R36: SQL Server / DB, Proje yönetimi, Ekip liderliği, Microsoft ortamı, Perakende / çok lokasyon | S36: İş uygulaması alanı (CRM/ERP/Legal/ServiceNow…) | T36: 4 | U36: 5 | V36: 1.5 | W36: 3.5 | X36: 5 | Y36: 3.5 | Z36: =ROUND((T36*Özet!$C$14+U36*Özet!$C$15+V36*Özet!$C$16+W36*Özet!$C$17+X36*Özet!$C$18+Y36*Özet!$C$19)/5,4) -> 0.685 | AA36: =RANK(AE36,$AE$5:$AE$126)+COUNTIF($AE$5:AE36,AE36)-1 -> 32 | AB36: =IF(AND(OR(G36="EN",G36="EN (+DE artı)"),Z36>=0.7),"A – Hemen başvur (İngilizce)",IF(Z36>=0.7,"B – Başvur (Almanca gerekli)",IF(AND(OR(G36="EN",G36="EN (+DE artı)"),Z36>=0.6),"B – Başvur (İngilizce)","C – Opsiyonel"))) -> C – Opsiyonel | AC36: Almanca CV + Anschreiben ile başvur (Almanca B1/B2 belirt) | AD36: https://www.karriere.at/f/messezentrum-salzburg | AE36: =Z36+IF(OR(G36="EN",G36="EN (+DE artı)"),1,0) -> 0.685
A37: 33 | B37: Universität Salzburg | C37: IT-Servicemanager*in | D37: Salzburg, Austria | E37: ≤30 dk (Salzburg / yakın çevre) | F37: IT servis yönetimi (ITIL) | G37: DE | H37: İlan Almanca; seviye belirtilmemiş | I37: — | J37: Kıdemli / yönetici | K37: İlanda belirtilmemiş | L37: 2026-09-21 | M37: LinkedIn | N37: https://www.linkedin.com/jobs/view/4458175246 | O37: 27.09.2026 14:14 · HTTP 200 · AÇIK | Q37: Bewerbungsfrist: 07.10.2026 Wochenstunden: 40 h/W Ihre Aufgaben: Analyse von Kund*innenanforderungen und Übersetzung von Geschäftsanforderungen in technische Konzepte Weiterentwicklung des Servicekatalogs Entwicklung und Implementierung von neuen und Weiterentwicklung von bestehenden Serviceprozessen Design und Aufbau übergreifender Prozesse und Systeme zur Integration (SAP, Campusmanagement, ...) Mitwirkung an Daten… | R37: Tedarikçi yönetimi | S37: SAP | T37: 4 | U37: 5 | V37: 1.5 | W37: 3.5 | X37: 5 | Y37: 3.5 | Z37: =ROUND((T37*Özet!$C$14+U37*Özet!$C$15+V37*Özet!$C$16+W37*Özet!$C$17+X37*Özet!$C$18+Y37*Özet!$C$19)/5,4) -> 0.685 | AA37: =RANK(AE37,$AE$5:$AE$126)+COUNTIF($AE$5:AE37,AE37)-1 -> 33 | AB37: =IF(AND(OR(G37="EN",G37="EN (+DE artı)"),Z37>=0.7),"A – Hemen başvur (İngilizce)",IF(Z37>=0.7,"B – Başvur (Almanca gerekli)",IF(AND(OR(G37="EN",G37="EN (+DE artı)"),Z37>=0.6),"B – Başvur (İngilizce)","C – Opsiyonel"))) -> C – Opsiyonel | AC37: Almanca CV + Anschreiben ile başvur (Almanca B1/B2 belirt) | AD37: https://at.linkedin.com/school/universitaet-salzburg/ | AE37: =Z37+IF(OR(G37="EN",G37="EN (+DE artı)"),1,0) -> 0.685
A38: 34 | B38: ip50 Personalberatung (müşteri gizli: ‘Weltmarktführer’, Hallein) | C38: IT-Infrastrukturmanager (w/m/d) | D38: Hallein, Salzburg, Austria | E38: ≤30 dk (Salzburg / yakın çevre) | F38: IT yönetimi / liderlik | G38: DE C1 | H38: Arbeitsweise sowie Freude an Technik und Support ausgezeichnete Deutsch- und sehr gute Englischkenntnisse Benefits Geboten wird eine langfris | I38: — | J38: Kıdemli / yönetici | K38: İlanda belirtilmemiş | L38: 2026-09-25 | M38: LinkedIn | N38: https://www.linkedin.com/jobs/view/4471884648 | O38: 27.09.2026 14:14 · HTTP 200 · AÇIK | Q38: Abgeschlossene Ausbildung (z.B. IT-Lehre, HTL, FH etc.) oder Quereinsteiger mit Berufserfahrung Fundierte Kenntnisse im Bereich Netzwerk und Serverumgebungen Erfahrung mit Microsoft 365 und Active Directory von Vorteil Strukturierte und lösungsorientierte Arbeitsweise sowie Freude an Technik und Support ausgezeichnete Deutsch- und sehr gute Englischkenntnisse Benefits Geboten wird eine langfristige Perspektive in ein… | R38: Active Directory, Backup / DR, Ağ / Firewall / VPN, Microsoft ortamı | S38: Almanca C1 / çok iyi Almanca, Intune / M365 admin | T38: 4.5 | U38: 5 | V38: 1 | W38: 3.5 | X38: 5 | Y38: 3.5 | Z38: =ROUND((T38*Özet!$C$14+U38*Özet!$C$15+V38*Özet!$C$16+W38*Özet!$C$17+X38*Özet!$C$18+Y38*Özet!$C$19)/5,4) -> 0.685 | AA38: =RANK(AE38,$AE$5:$AE$126)+COUNTIF($AE$5:AE38,AE38)-1 -> 34 | AB38: =IF(AND(OR(G38="EN",G38="EN (+DE artı)"),Z38>=0.7),"A – Hemen başvur (İngilizce)",IF(Z38>=0.7,"B – Başvur (Almanca gerekli)",IF(AND(OR(G38="EN",G38="EN (+DE artı)"),Z38>=0.6),"B – Başvur (İngilizce)","C – Opsiyonel"))) -> C – Opsiyonel | AC38: Almanca C1 isteniyor – yine de başvurmak istersen Almanca CV + dil planı (kurs/sertifika) belirt · Personel danışmanı ilanı → danışmanı telefon/e-posta ile ara, diğer açık pozisyonlarını da sor | AD38: https://www.linkedin.com/company/ip50 | AE38: =Z38+IF(OR(G38="EN",G38="EN (+DE artı)"),1,0) -> 0.685
A39: 35 | B39: SPAR ICS – Information & Communication Services | C39: Teamlead IT Service Desk (m/w/d) | D39: Salzburg (Stadt), Wien, Wernberg | E39: ≤30 dk (Salzburg / yakın çevre) | F39: IT yönetimi / liderlik | G39: DE C1 | H39: daran, Menschen zu begeistern und weiterzuentwickeln Sehr guten Deutsch- sowie Englischkenntnissen in Wort und Schrift Darauf kannst du dich | I39: — | J39: Kıdemli / yönetici | K39: ~€55k+/yıl (ilan: ab 55.000 € jährlich) | L39: 2026-09-27 | M39: karriere.at | N39: https://www.karriere.at/jobs/7863127 | O39: 27.09.2026 14:13 · HTTP 200 · AÇIK | P39: https://www.linkedin.com/jobs/view/4454494899 | Q39: Teamlead IT Service Desk (m/w/d) Wir sind das "I" und "T" in Retail... Dienstort: Salzburg, Wien, Wernberg Ausmaß: Vollzeit SPAR ICS ist die IT-Gesellschaft der SPAR Österreich-Gruppe und kümmert sich um sämtliche IT-Belange von SPAR, INTERSPAR und SES Spar European Shopping Centers. Wir sind über 700 kluge Köpfe und haben zwei Agenden: Das reibungslose Einkaufserlebnis aller SPAR-Kund:innen in 5 Ländern und die digi… | R39: ITIL / ITSM, SQL Server / DB, Ekip liderliği, Perakende / çok lokasyon | S39: Almanca C1 / çok iyi Almanca, Scripting / otomasyon (PowerShell vb.), İş uygulaması alanı (CRM/ERP/Legal/ServiceNow…), AI / ML | T39: 4 | U39: 5 | V39: 1 | W39: 5 | X39: 5 | Y39: 4 | Z39: =ROUND((T39*Özet!$C$14+U39*Özet!$C$15+V39*Özet!$C$16+W39*Özet!$C$17+X39*Özet!$C$18+Y39*Özet!$C$19)/5,4) -> 0.68 | AA39: =RANK(AE39,$AE$5:$AE$126)+COUNTIF($AE$5:AE39,AE39)-1 -> 35 | AB39: =IF(AND(OR(G39="EN",G39="EN (+DE artı)"),Z39>=0.7),"A – Hemen başvur (İngilizce)",IF(Z39>=0.7,"B – Başvur (Almanca gerekli)",IF(AND(OR(G39="EN",G39="EN (+DE artı)"),Z39>=0.6),"B – Başvur (İngilizce)","C – Opsiyonel"))) -> C – Opsiyonel | AC39: Almanca C1 isteniyor – yine de başvurmak istersen Almanca CV + dil planı (kurs/sertifika) belirt | AD39: https://www.karriere.at/f/spar-ics-information-communication-services | AE39: =Z39+IF(OR(G39="EN",G39="EN (+DE artı)"),1,0) -> 0.68
A40: 36 | B40: Sanitas GmbH | C40: IT-Systemspezialist/in für klinische Informationssysteme (m/w/d) | D40: Salzburg | E40: ≤30 dk (Salzburg / yakın çevre) | F40: Sistem / altyapı | G40: DE+EN | H40: Arbeitsweise Kommunikationsstärke, Teamgeist und Lernbereitschaft Deutsch und Englisch in Wort und Schrift Wir legen Wert auf Eigeninitiative, | I40: — | J40: Uzman (mid-senior) | K40: ~€42k+/yıl (ilan: ab 42.000 € jährlich) | L40: 2026-09-23 | M40: karriere.at | N40: https://www.karriere.at/jobs/10033575 | O40: 27.09.2026 14:13 · HTTP 200 · AÇIK | Q40: Abgeschlossene Ausbildung im IT-Bereich (HTL, Fachhochschule, Universität) Gute Kenntnisse von (Windows-)Technologien wie Kommandozeile, Security/Netzwerkfreigaben, Powershell, Datenbanken sowie Standards (z.B. XML) Erfahrungen mit Themen wie Automatisierung, Schnittstellen (HL7, FHIR usw.) von Vorteil Selbstständige, strukturierte und lösungsorientierte Arbeitsweise Kommunikationsstärke, Teamgeist und Lernbereitsch… | R40: Windows Server, Ağ / Firewall / VPN, SQL Server / DB, Ekip liderliği, Perakende / çok lokasyon | S40: Scripting / otomasyon (PowerShell vb.), Programlama | T40: 4 | U40: 4 | V40: 2 | W40: 3.5 | X40: 5 | Y40: 3 | Z40: =ROUND((T40*Özet!$C$14+U40*Özet!$C$15+V40*Özet!$C$16+W40*Özet!$C$17+X40*Özet!$C$18+Y40*Özet!$C$19)/5,4) -> 0.675 | AA40: =RANK(AE40,$AE$5:$AE$126)+COUNTIF($AE$5:AE40,AE40)-1 -> 36 | AB40: =IF(AND(OR(G40="EN",G40="EN (+DE artı)"),Z40>=0.7),"A – Hemen başvur (İngilizce)",IF(Z40>=0.7,"B – Başvur (Almanca gerekli)",IF(AND(OR(G40="EN",G40="EN (+DE artı)"),Z40>=0.6),"B – Başvur (İngilizce)","C – Opsiyonel"))) -> C – Opsiyonel | AC40: Almanca CV ile başvur; İngilizce yeterliliğini ve Almanca B1/B2'yi açıkça yaz | AD40: https://www.karriere.at/f/sanitas | AE40: =Z40+IF(OR(G40="EN",G40="EN (+DE artı)"),1,0) -> 0.675
A41: 37 | B41: DBConcepts GmbH | C41: Senior Oracle Database Administrator (m/w/x) | D41: Steiermark, Wien, Voralberg, Kärnten, Niederösterreich, Burgenland, Tirol, Salzburg, Österreich, Oberösterreich | E41: ≤30 dk (Salzburg / yakın çevre) | F41: Sistem / altyapı | G41: DE+EN | H41: İlan Almanca; seviye belirtilmemiş | I41: — | J41: Kıdemli / yönetici | K41: ~€80k+/yıl (ilan: ab 80.000 € jährlich) | L41: 2026-09-23 | M41: karriere.at | N41: https://www.karriere.at/jobs/10033619 | O41: 27.09.2026 14:13 · HTTP 200 · AÇIK | Q41: , Erfahrung und Vordienstzeiten. Für unser Unternehmen gilt der Kollektivvertrag IT. 80.000 EUR Benefits Aus- und Weiterbildung Berufliche und persönliche Weiterentwicklung Berufliche und persönliche Weiterentwicklung Team-Events Freundschaftliche Arbeitsatmosphäre & viele Teamaktivitäten Freundschaftliche Arbeitsatmosphäre & viele Teamaktivitäten Zusatzversicherungen Betriebliche Altersvorsorge Gesundheitsmaßnahmen… | R41: Windows Server, Sanallaştırma (Hyper-V/Proxmox), SQL Server / DB, Tedarikçi yönetimi, Perakende / çok lokasyon | S41: ANA ŞART: Linux, ANA ŞART: Oracle | T41: 3 | U41: 4.5 | V41: 2 | W41: 4 | X41: 5 | Y41: 5 | Z41: =ROUND((T41*Özet!$C$14+U41*Özet!$C$15+V41*Özet!$C$16+W41*Özet!$C$17+X41*Özet!$C$18+Y41*Özet!$C$19)/5,4) -> 0.675 | AA41: =RANK(AE41,$AE$5:$AE$126)+COUNTIF($AE$5:AE41,AE41)-1 -> 37 | AB41: =IF(AND(OR(G41="EN",G41="EN (+DE artı)"),Z41>=0.7),"A – Hemen başvur (İngilizce)",IF(Z41>=0.7,"B – Başvur (Almanca gerekli)",IF(AND(OR(G41="EN",G41="EN (+DE artı)"),Z41>=0.6),"B – Başvur (İngilizce)","C – Opsiyonel"))) -> C – Opsiyonel | AC41: Almanca CV ile başvur; İngilizce yeterliliğini ve Almanca B1/B2'yi açıkça yaz | AD41: https://www.karriere.at/f/dbconcepts | AE41: =Z41+IF(OR(G41="EN",G41="EN (+DE artı)"),1,0) -> 0.675
A42: 38 | B42: Österreichische Gesundheitskasse | C42: Projektleitung Datenmanagement & Data Governance | D42: Steiermark, Wien, Voralberg, Kärnten, Niederösterreich, Burgenland, Tirol, Salzburg, Österreich, Oberösterreich | E42: ≤30 dk (Salzburg / yakın çevre) | F42: IT proje yönetimi | G42: DE | H42: İlan Almanca; seviye belirtilmemiş | I42: — | J42: Kıdemli / yönetici | K42: ~€61k+/yıl (ilan: ab 4.327,50 € monatlich) | L42: 2026-09-26 | M42: karriere.at | N42: https://www.karriere.at/jobs/10032941 | O42: 27.09.2026 14:13 · HTTP 200 · AÇIK | Q42: sowie Übersetzung in umsetzbare Datenlösungen Moderation von Workshops sowie die Abstimmung mit Entscheidungsträgern Sicherstellung der Zielerreichung hinsichtlich Nutzens, Qualität, Zeit und Budget Ihr Profil Abgeschlossenes Studium im Bereich Informatik, Wirtschaftsinformatik, Data Science, Betriebswirtschaft oder eine vergleichbare Qualifikation Managementkompetenzen sowie praktische Erfahrung im Führen dezentrale… | R42: Proje yönetimi, Bütçe, Ekip liderliği, Politika / uyum, Perakende / çok lokasyon | S42: ANA ŞART: İş uygulaması alanı (CRM/ERP/Legal/ServiceNow…) | T42: 3.5 | U42: 5 | V42: 1.5 | W42: 3.5 | X42: 5 | Y42: 4.5 | Z42: =ROUND((T42*Özet!$C$14+U42*Özet!$C$15+V42*Özet!$C$16+W42*Özet!$C$17+X42*Özet!$C$18+Y42*Özet!$C$19)/5,4) -> 0.675 | AA42: =RANK(AE42,$AE$5:$AE$126)+COUNTIF($AE$5:AE42,AE42)-1 -> 38 | AB42: =IF(AND(OR(G42="EN",G42="EN (+DE artı)"),Z42>=0.7),"A – Hemen başvur (İngilizce)",IF(Z42>=0.7,"B – Başvur (Almanca gerekli)",IF(AND(OR(G42="EN",G42="EN (+DE artı)"),Z42>=0.6),"B – Başvur (İngilizce)","C – Opsiyonel"))) -> C – Opsiyonel | AC42: Almanca CV + Anschreiben ile başvur (Almanca B1/B2 belirt) · İletişim: recruiting-team5@oegk.at. | AD42: https://www.karriere.at/f/%C3%B6sterreichische-gesundheitskasse-wien | AE42: =Z42+IF(OR(G42="EN",G42="EN (+DE artı)"),1,0) -> 0.675
A43: 39 | B43: Arineo Group | C43: Senior Projektmanager ERP (all genders) | D43: Salzburg, Salzburg, Austria | E43: ≤30 dk (Salzburg / yakın çevre) | F43: IT proje yönetimi | G43: EN+DE (akıcı DE) | H43: knowledge of project planning software Very good command of German and good command of English Willingness to travel for project-related | I43: — | J43: Kıdemli / yönetici | K43: ~€75k+/yıl (ilan metninden) | L43: 2026-09-09 | M43: LinkedIn | N43: https://www.linkedin.com/jobs/view/4463896589 | O43: 27.09.2026 14:14 · HTTP 200 · AÇIK | Q43: At least 5 years’ experience as a project manager in the implementation of ERP systems or complex software projects – ideally on the service provider side Proven experience in leading projects spanning several years and managing long-term client relationships Knowledge of an agile project methodology A confident and assured manner, as well as strong communication skills A solution- and service-oriented approach to wo… | R43: ITIL / ITSM, Proje yönetimi, Tedarikçi yönetimi, Bütçe, Risk yönetimi, Microsoft ortamı | S43: Azure / Entra ID, Container / IaC / DevOps, ANA ŞART: İş uygulaması alanı (CRM/ERP/Legal/ServiceNow…), AI / ML | T43: 3 | U43: 5 | V43: 1.5 | W43: 4 | X43: 5 | Y43: 5 | Z43: =ROUND((T43*Özet!$C$14+U43*Özet!$C$15+V43*Özet!$C$16+W43*Özet!$C$17+X43*Özet!$C$18+Y43*Özet!$C$19)/5,4) -> 0.66 | AA43: =RANK(AE43,$AE$5:$AE$126)+COUNTIF($AE$5:AE43,AE43)-1 -> 39 | AB43: =IF(AND(OR(G43="EN",G43="EN (+DE artı)"),Z43>=0.7),"A – Hemen başvur (İngilizce)",IF(Z43>=0.7,"B – Başvur (Almanca gerekli)",IF(AND(OR(G43="EN",G43="EN (+DE artı)"),Z43>=0.6),"B – Başvur (İngilizce)","C – Opsiyonel"))) -> C – Opsiyonel | AC43: İngilizce CV + ön yazı ile başvur | AD43: https://de.linkedin.com/company/arineo | AE43: =Z43+IF(OR(G43="EN",G43="EN (+DE artı)"),1,0) -> 0.66
A44: 40 | B44: ACP Gruppe | C44: Netzwerk Systems Engineer / Consultant | D44: Salzburg (Stadt) | E44: ≤30 dk (Salzburg / yakın çevre) | F44: Sistem / altyapı | G44: DE C1 | H44: Ausgeprägter Teamgeist und Freude an Wissensaustausch Sehr gute Deutsch- und Englischkenntnisse in Wort und Schrift Hohe Kundenorientierung F | I44: — | J44: Kıdemli / yönetici | K44: ~€59k+/yıl (ilan: ab 58.800 € jährlich) | L44: 2026-09-23 | M44: karriere.at | N44: https://www.karriere.at/jobs/7860364 | O44: 27.09.2026 14:13 · HTTP 200 · AÇIK | P44: https://bewerbung.acp-gruppe.com/at/rx/887 | Q44: Abgeschlossene Ausbildung im IT-Bereich (HTL, FH, Uni o. Ä.) oder einschlägige Berufserfahrung Sehr gutes technisches Verständnis für IT-Infrastruktur als Gesamtsystem Interesse an kontinuierlicher Weiterbildung und neuen Technologien Selbstständige, strukturierte und kundenorientierte Arbeitsweise Ausgeprägter Teamgeist und Freude an Wissensaustausch Sehr gute Deutsch- und Englischkenntnisse in Wort und Schrift Hohe… | R44: Ağ / Firewall / VPN, Tedarikçi yönetimi | S44: Almanca C1 / çok iyi Almanca, Ağ üreticisi sertifikası (Cisco/Fortinet/Palo Alto) | T44: 4 | U44: 4.5 | V44: 1 | W44: 4 | X44: 5 | Y44: 4 | Z44: =ROUND((T44*Özet!$C$14+U44*Özet!$C$15+V44*Özet!$C$16+W44*Özet!$C$17+X44*Özet!$C$18+Y44*Özet!$C$19)/5,4) -> 0.655 | AA44: =RANK(AE44,$AE$5:$AE$126)+COUNTIF($AE$5:AE44,AE44)-1 -> 40 | AB44: =IF(AND(OR(G44="EN",G44="EN (+DE artı)"),Z44>=0.7),"A – Hemen başvur (İngilizce)",IF(Z44>=0.7,"B – Başvur (Almanca gerekli)",IF(AND(OR(G44="EN",G44="EN (+DE artı)"),Z44>=0.6),"B – Başvur (İngilizce)","C – Opsiyonel"))) -> C – Opsiyonel | AC44: Almanca C1 isteniyor – yine de başvurmak istersen Almanca CV + dil planı (kurs/sertifika) belirt | AD44: https://www.karriere.at/f/acp-gruppe | AE44: =Z44+IF(OR(G44="EN",G44="EN (+DE artı)"),1,0) -> 0.655
A45: 41 | B45: ACP Gruppe | C45: (Senior) Systems Engineer m, w, d | D45: Salzburg | E45: ≤30 dk (Salzburg / yakın çevre) | F45: Sistem / altyapı | G45: DE C1 | H45: Ausgeprägter Teamgeist und Freude an Wissensaustausch Sehr gute Deutsch- und Englischkenntnisse in Wort und Schrift Hohe Kundenorientierung F | I45: — | J45: Kıdemli / yönetici | K45: ~€59k+/yıl (ilan: ab 58.800 € jährlich) | L45: 2026-09-21 | M45: karriere.at | N45: https://www.karriere.at/jobs/7879510 | O45: 27.09.2026 14:13 · HTTP 200 · AÇIK | P45: https://www.linkedin.com/jobs/view/4468764638 https://bewerbung.acp-gruppe.com/at/rx/907 | Q45: Abgeschlossene Ausbildung im IT-Bereich (HTL, FH, Uni o. Ä.) und einschlägige Berufserfahrung Sehr gutes technisches Verständnis für IT-Infrastrukturen als Gesamtsystem Interesse an kontinuierlicher Weiterbildung und neuen Technologien Selbstständige, strukturierte und kundenorientierte Arbeitsweise Ausgeprägter Teamgeist und Freude an Wissensaustausch Sehr gute Deutsch- und Englischkenntnisse in Wort und Schrift Hoh… | R45: Windows Server, Sanallaştırma (Hyper-V/Proxmox), Tedarikçi yönetimi, Ekip liderliği, Microsoft ortamı | S45: Almanca C1 / çok iyi Almanca, Azure / Entra ID, Intune / M365 admin | T45: 4 | U45: 4.5 | V45: 1 | W45: 4 | X45: 5 | Y45: 4 | Z45: =ROUND((T45*Özet!$C$14+U45*Özet!$C$15+V45*Özet!$C$16+W45*Özet!$C$17+X45*Özet!$C$18+Y45*Özet!$C$19)/5,4) -> 0.655 | AA45: =RANK(AE45,$AE$5:$AE$126)+COUNTIF($AE$5:AE45,AE45)-1 -> 41 | AB45: =IF(AND(OR(G45="EN",G45="EN (+DE artı)"),Z45>=0.7),"A – Hemen başvur (İngilizce)",IF(Z45>=0.7,"B – Başvur (Almanca gerekli)",IF(AND(OR(G45="EN",G45="EN (+DE artı)"),Z45>=0.6),"B – Başvur (İngilizce)","C – Opsiyonel"))) -> C – Opsiyonel | AC45: Almanca C1 isteniyor – yine de başvurmak istersen Almanca CV + dil planı (kurs/sertifika) belirt | AD45: https://www.karriere.at/f/acp-gruppe | AE45: =Z45+IF(OR(G45="EN",G45="EN (+DE artı)"),1,0) -> 0.655
A46: 42 | B46: Iventa. The Human Management Group | C46: Senior IT Service Manager (w/m/d) – ITSM & Prozessmanagement | D46: Salzburg, Salzburg, Austria | E46: ≤30 dk (Salzburg / yakın çevre) | F46: IT servis yönetimi (ITIL) | G46: DE C1 | H46: IT Landschaften und serviceorientierte Arbeitsweisen Sehr gute Deutschkenntnisse (C1 Niveau) sowie gute Englischkenntnisse (B2 Niveau) Ausge | I46: — | J46: Kıdemli / yönetici | K46: ~€48k+/yıl (ilan metninden) | L46: 2026-09-09 | M46: LinkedIn | N46: https://www.linkedin.com/jobs/view/4446306750 | O46: 27.09.2026 14:14 · HTTP 200 · AÇIK | Q46: und einschlägiger Berufserfahrung ist eine höhere Einstufung möglich. Gerne besprechen wir die Details persönlich mit Ihnen. Bewerben Sie sich bei uns unter www.iventa.eu/bewerberportal/offene-jobs mit Angabe der Ref.-Nr. 2026-06673. Wir freuen uns darauf, Sie erfolgreich zu vernetzen! Ansprechperson Zsuzsanna Torda +43 (1) 523 49 44-282 Jetzt bewerben… | R46: ITIL / ITSM, Tedarikçi yönetimi | S46: Almanca C1 / çok iyi Almanca, İş uygulaması alanı (CRM/ERP/Legal/ServiceNow…) | T46: 4 | U46: 5 | V46: 1 | W46: 3.5 | X46: 5 | Y46: 3.5 | Z46: =ROUND((T46*Özet!$C$14+U46*Özet!$C$15+V46*Özet!$C$16+W46*Özet!$C$17+X46*Özet!$C$18+Y46*Özet!$C$19)/5,4) -> 0.655 | AA46: =RANK(AE46,$AE$5:$AE$126)+COUNTIF($AE$5:AE46,AE46)-1 -> 42 | AB46: =IF(AND(OR(G46="EN",G46="EN (+DE artı)"),Z46>=0.7),"A – Hemen başvur (İngilizce)",IF(Z46>=0.7,"B – Başvur (Almanca gerekli)",IF(AND(OR(G46="EN",G46="EN (+DE artı)"),Z46>=0.6),"B – Başvur (İngilizce)","C – Opsiyonel"))) -> C – Opsiyonel | AC46: Almanca C1 isteniyor – yine de başvurmak istersen Almanca CV + dil planı (kurs/sertifika) belirt · Personel danışmanı ilanı → danışmanı telefon/e-posta ile ara, diğer açık pozisyonlarını da sor | AD46: https://at.linkedin.com/company/iventagroup | AE46: =Z46+IF(OR(G46="EN",G46="EN (+DE artı)"),1,0) -> 0.655
A47: 43 | B47: ip50 Personalberatung (müşteri gizli: ‘Weltmarktführer’, Hallein) | C47: IT-Systemadministrator (w/m/d) | D47: Hallein, Salzburg, Austria | E47: ≤30 dk (Salzburg / yakın çevre) | F47: Sistem / altyapı | G47: DE C1 | H47: Grundverständnis im Bereich IT-Security ausgezeichnete Deutsch- und sehr gute Englischkenntnisse Benefits Geboten wird eine langfris | I47: — | J47: Uzman (mid-senior) | K47: İlanda belirtilmemiş | L47: 2026-09-25 | M47: LinkedIn | N47: https://www.linkedin.com/jobs/view/4471881682 | O47: 27.09.2026 14:14 · HTTP 200 · AÇIK | Q47: Abgeschlossene Ausbildung (z.B. IT-Lehre, HTL, FH etc.) oder Quereinsteiger mit Berufserfahrung Erfahrung mit MS Windows (Active Directory) Kenntnisse in der Server- und Netzwerkadministration Grundverständnis im Bereich IT-Security ausgezeichnete Deutsch- und sehr gute Englischkenntnisse Benefits Geboten wird eine langfristige Perspektive in einem wirtschaftlich äußerst stabilen Umfeld mit klarer Rückendeckung des M… | R47: Active Directory, Windows Server, Backup / DR, Ağ / Firewall / VPN, Proje yönetimi, Microsoft ortamı | S47: Almanca C1 / çok iyi Almanca | T47: 4.5 | U47: 4 | V47: 1 | W47: 3.5 | X47: 5 | Y47: 3 | Z47: =ROUND((T47*Özet!$C$14+U47*Özet!$C$15+V47*Özet!$C$16+W47*Özet!$C$17+X47*Özet!$C$18+Y47*Özet!$C$19)/5,4) -> 0.645 | AA47: =RANK(AE47,$AE$5:$AE$126)+COUNTIF($AE$5:AE47,AE47)-1 -> 43 | AB47: =IF(AND(OR(G47="EN",G47="EN (+DE artı)"),Z47>=0.7),"A – Hemen başvur (İngilizce)",IF(Z47>=0.7,"B – Başvur (Almanca gerekli)",IF(AND(OR(G47="EN",G47="EN (+DE artı)"),Z47>=0.6),"B – Başvur (İngilizce)","C – Opsiyonel"))) -> C – Opsiyonel | AC47: Almanca C1 isteniyor – yine de başvurmak istersen Almanca CV + dil planı (kurs/sertifika) belirt · Personel danışmanı ilanı → danışmanı telefon/e-posta ile ara, diğer açık pozisyonlarını da sor | AD47: https://www.linkedin.com/company/ip50 | AE47: =Z47+IF(OR(G47="EN",G47="EN (+DE artı)"),1,0) -> 0.645
A48: 44 | B48: Red Bull | C48: IT Project Manager – Finance Applications | D48: Elsbethen | E48: ≤30 dk (Salzburg / yakın çevre) | F48: IT proje yönetimi | G48: DE+EN | H48: Berufserfahrung Gute Deutschkenntnisse sowie fließende Englischkenntnisse Fundierte praktische Erf | I48: — | J48: Kıdemli / yönetici | K48: Sadece KV asgarisi: ~€35k/yıl (ab 2.535 € monatlich) – gerçek maaş belirtilmemiş, genelde üstünde | L48: 2026-09-23 | M48: Red Bull resmi | N48: https://jobs.redbull.com/at-de/elsbethen-it-project-application-manager-sapfi-application--ref31534p | O48: 27.09.2026 14:13 · HTTP 200 · AÇIK | P48: https://www.karriere.at/jobs/7821824 https://www.linkedin.com/jobs/view/4454029704 https://www.linkedin.com/jobs/view/4425603684 | Q48: in funktionale und technische Lösungskonzepte und verantwortest Projekte ganzheitlich - von der Konzeption über die Implementierung bis zum Go-live und zum stabilen Betrieb. Dabei entwickelst du effiziente und skalierbare Finanzprozesse in einer globalen SAP-S/4HANA-Landschaft kontinuierlich weiter. APPLICATION MANAGEMENT Als Application Owner für SAP-FI-Lösungen verantwortest du die Finance-Applikationslandschaft en… | R48: Proje yönetimi, Bütçe, Politika / uyum | S48: ANA ŞART: SAP, ANA ŞART: İş uygulaması alanı (CRM/ERP/Legal/ServiceNow…), AI / ML | T48: 2.5 | U48: 5 | V48: 2 | W48: 5 | X48: 5 | Y48: 3.5 | Z48: =ROUND((T48*Özet!$C$14+U48*Özet!$C$15+V48*Özet!$C$16+W48*Özet!$C$17+X48*Özet!$C$18+Y48*Özet!$C$19)/5,4) -> 0.64 | AA48: =RANK(AE48,$AE$5:$AE$126)+COUNTIF($AE$5:AE48,AE48)-1 -> 44 | AB48: =IF(AND(OR(G48="EN",G48="EN (+DE artı)"),Z48>=0.7),"A – Hemen başvur (İngilizce)",IF(Z48>=0.7,"B – Başvur (Almanca gerekli)",IF(AND(OR(G48="EN",G48="EN (+DE artı)"),Z48>=0.6),"B – Başvur (İngilizce)","C – Opsiyonel"))) -> C – Opsiyonel | AC48: Almanca CV ile başvur; İngilizce yeterliliğini ve Almanca B1/B2'yi açıkça yaz | AD48: https://www.karriere.at/f/red-bull | AE48: =Z48+IF(OR(G48="EN",G48="EN (+DE artı)"),1,0) -> 0.64
A49: 45 | B49: KPMG Österreich | C49: Senior ISO 270XX-Auditor:in bzw. Implementierungsspezialist:in | D49: Wien, Graz, Klagenfurt, Linz, Salzburg | E49: ≤30 dk (Salzburg / yakın çevre) | F49: Cyber Security – yönetişim / ISMS | G49: DE C1 | H49: Zukunftsthemen der Digitalisierung von Vorteil Ausgezeichnete Deutsch- und Englischkenntnisse in Wort und Schrift Wenn du nicht alle Kompet | I49: — | J49: Kıdemli / yönetici | K49: ~€58k+/yıl (ilan: ab 58.000 € jährlich) | L49: 2026-09-20 | M49: karriere.at | N49: https://www.karriere.at/jobs/7868488 | O49: 27.09.2026 14:14 · HTTP 200 · AÇIK | Q49: unserer Kund:innen. Entsprechend deiner Erfahrung werden deine Aufgaben nicht nur in der Projektmitarbeit, sondern auch in der Projektleitung liegen. Im Auge des Security-Orkans: Digitale Transformation, Hacker Angriff, neue Entwicklungsmodelle, Technical Debt und Cloud Technologie - hilf mit, Österreich sicherer zu machen! Perspektiven Rasche Übernahme von Projekt- & und ggf. Führungsverantwortung um die kniffeligst… | R49: ISO 27001 / ISMS, ITIL / ITSM, Ağ / Firewall / VPN, Proje yönetimi, Bütçe, Ekip liderliği, Risk yönetimi, Politika / uyum, Denetim / audit, Perakende / çok lokasyon | S49: Almanca C1 / çok iyi Almanca, Container / IaC / DevOps, Programlama, NIS-2 / DORA / TISAX, CISSP / CISM / CISA, ANA ŞART: AI / ML | T49: 3.5 | U49: 5 | V49: 1 | W49: 4 | X49: 5 | Y49: 4 | Z49: =ROUND((T49*Özet!$C$14+U49*Özet!$C$15+V49*Özet!$C$16+W49*Özet!$C$17+X49*Özet!$C$18+Y49*Özet!$C$19)/5,4) -> 0.64 | AA49: =RANK(AE49,$AE$5:$AE$126)+COUNTIF($AE$5:AE49,AE49)-1 -> 45 | AB49: =IF(AND(OR(G49="EN",G49="EN (+DE artı)"),Z49>=0.7),"A – Hemen başvur (İngilizce)",IF(Z49>=0.7,"B – Başvur (Almanca gerekli)",IF(AND(OR(G49="EN",G49="EN (+DE artı)"),Z49>=0.6),"B – Başvur (İngilizce)","C – Opsiyonel"))) -> C – Opsiyonel | AC49: Almanca C1 isteniyor – yine de başvurmak istersen Almanca CV + dil planı (kurs/sertifika) belirt | AD49: https://www.karriere.at/f/kpmg-%C3%B6sterreich | AE49: =Z49+IF(OR(G49="EN",G49="EN (+DE artı)"),1,0) -> 0.64
A50: 46 | B50: teampool Personalberatung | C50: IT Support Engineer (m/w/d) | D50: Salzburg | E50: ≤30 dk (Salzburg / yakın çevre) | F50: IT destek / service desk | G50: DE+EN | H50: & MS Office) und Apple -Umfeld (macOS & iOS) Gute Englisch- und Deutschkenntnisse in Wort und Schrift für die Kommunikation mit den Usern Tea | I50: — | J50: Orta / giriş – aday overqualified | K50: ~€35k+/yıl (ilan: ab 2.500 € monatlich) | L50: 2026-09-10 | M50: karriere.at | N50: https://www.karriere.at/jobs/7874311 | O50: 27.09.2026 14:13 · HTTP 200 · AÇIK | Q50: Abgeschlossene IT- Ausbildung oder Berufserfahrung im IT Bereich Erfahrung im Microsoft- (Windows & MS Office) und Apple -Umfeld (macOS & iOS) Gute Englisch- und Deutschkenntnisse in Wort und Schrift für die Kommunikation mit den Usern Teamfähigkeit und gute Kommunikationsfähigkeiten, um erfolgreich mit verschiedenen internen und externen Partnern zusammenzuarbeiten Zusätzliche Sprachkenntnisse von Vorteil Unser Kund… | R50: Windows Server, Microsoft ortamı | S50: Belirgin teknik eksik yok | T50: 4 | U50: 3 | V50: 2 | W50: 3.5 | X50: 5 | Y50: 2.5 | Z50: =ROUND((T50*Özet!$C$14+U50*Özet!$C$15+V50*Özet!$C$16+W50*Özet!$C$17+X50*Özet!$C$18+Y50*Özet!$C$19)/5,4) -> 0.635 | AA50: =RANK(AE50,$AE$5:$AE$126)+COUNTIF($AE$5:AE50,AE50)-1 -> 46 | AB50: =IF(AND(OR(G50="EN",G50="EN (+DE artı)"),Z50>=0.7),"A – Hemen başvur (İngilizce)",IF(Z50>=0.7,"B – Başvur (Almanca gerekli)",IF(AND(OR(G50="EN",G50="EN (+DE artı)"),Z50>=0.6),"B – Başvur (İngilizce)","C – Opsiyonel"))) -> C – Opsiyonel | AC50: Almanca CV ile başvur; İngilizce yeterliliğini ve Almanca B1/B2'yi açıkça yaz · Personel danışmanı ilanı → danışmanı telefon/e-posta ile ara, diğer açık pozisyonlarını da sor · İletişim: bewerbung.seekirchen@teampool.com | AD50: https://www.karriere.at/f/teampool-personalberatung | AE50: =Z50+IF(OR(G50="EN",G50="EN (+DE artı)"),1,0) -> 0.635
A51: 47 | B51: x-tention Informationstechnologie GmbH | C51: Senior Enterprise Network Engineer (m/w/d) | D51: Wien, Wels, Salzburg (Stadt) | E51: ≤30 dk (Salzburg / yakın çevre) | F51: Sistem / altyapı | G51: DE | H51: İlan Almanca; seviye belirtilmemiş | I51: — | J51: Kıdemli / yönetici | K51: ~€65k+/yıl (ilan: 4.620 € – 5.620 € monatlich) | L51: 2026-09-22 | M51: karriere.at | N51: https://www.karriere.at/jobs/10031631 | O51: 27.09.2026 14:13 · HTTP 200 · AÇIK | Q51: und Berufserfahrung vorgesehen. KV Min. KV Mindestgehalt 4.620 EUR 5.620 EUR Benefits Aus- und Weiterbildung Die Zukunft der Healthcare-IT kann man nur gestalten, wenn man immer up-to-date bleibt. Darum ermöglichen wir dir gerne individuelle Aus- und Weiterbildungen, Seminare und Schulungen. Die Zukunft der Healthcare-IT kann man nur gestalten, wenn man immer up-to-date bleibt. Darum ermöglichen wir dir gerne individ… | R51: Ağ / Firewall / VPN, Tedarikçi yönetimi, Perakende / çok lokasyon | S51: Scripting / otomasyon (PowerShell vb.), ANA ŞART: Ağ üreticisi sertifikası (Cisco/Fortinet/Palo Alto) | T51: 3 | U51: 4.5 | V51: 1.5 | W51: 4 | X51: 5 | Y51: 4.5 | Z51: =ROUND((T51*Özet!$C$14+U51*Özet!$C$15+V51*Özet!$C$16+W51*Özet!$C$17+X51*Özet!$C$18+Y51*Özet!$C$19)/5,4) -> 0.635 | AA51: =RANK(AE51,$AE$5:$AE$126)+COUNTIF($AE$5:AE51,AE51)-1 -> 47 | AB51: =IF(AND(OR(G51="EN",G51="EN (+DE artı)"),Z51>=0.7),"A – Hemen başvur (İngilizce)",IF(Z51>=0.7,"B – Başvur (Almanca gerekli)",IF(AND(OR(G51="EN",G51="EN (+DE artı)"),Z51>=0.6),"B – Başvur (İngilizce)","C – Opsiyonel"))) -> C – Opsiyonel | AC51: Almanca CV + Anschreiben ile başvur (Almanca B1/B2 belirt) | AD51: https://www.karriere.at/f/x-tention-informationstechnologie | AE51: =Z51+IF(OR(G51="EN",G51="EN (+DE artı)"),1,0) -> 0.635
A52: 48 | B52: x-tention Informationstechnologie GmbH | C52: Datacenter Systems Engineer (m/w/d) | D52: Klagenfurt am Wörthersee, Wien, St. Peter in der Au, Graz, Wels, Salzburg (Stadt) | E52: ≤30 dk (Salzburg / yakın çevre) | F52: Sistem / altyapı | G52: DE | H52: İlan Almanca; seviye belirtilmemiş | I52: — | J52: Uzman (mid-senior) | K52: ~€50k+/yıl (ilan: 3.600 € – 4.600 € monatlich) | L52: 2026-09-21 | M52: karriere.at | N52: https://www.karriere.at/jobs/10031629 | O52: 27.09.2026 14:13 · HTTP 200 · AÇIK | Q52: des Fachbereiches sowie der Einbringung eigener Ideen Sicherstellen der Serviceverfügbarkeit (Monitoring) Patch- und Firmware-Management bei der eingesetzten Hard- und Software Diese Skills solltest du mitbringen. Abgeschlossene IT-Ausbildung (Lehre/FH/Uni) Fundierte Kenntnisse in Hypervisor-Technologien (VMWare ESXi, MS Hyper-V, etc.) von Vorteil Erfahrung in der Verwaltung und Wartung von Virtualisierungsplattforme… | R52: Sanallaştırma (Hyper-V/Proxmox), Ekip liderliği, Politika / uyum, Microsoft ortamı, Perakende / çok lokasyon | S52: ANA ŞART: VMware | T52: 3.5 | U52: 4 | V52: 1.5 | W52: 4 | X52: 5 | Y52: 3.5 | Z52: =ROUND((T52*Özet!$C$14+U52*Özet!$C$15+V52*Özet!$C$16+W52*Özet!$C$17+X52*Özet!$C$18+Y52*Özet!$C$19)/5,4) -> 0.63 | AA52: =RANK(AE52,$AE$5:$AE$126)+COUNTIF($AE$5:AE52,AE52)-1 -> 48 | AB52: =IF(AND(OR(G52="EN",G52="EN (+DE artı)"),Z52>=0.7),"A – Hemen başvur (İngilizce)",IF(Z52>=0.7,"B – Başvur (Almanca gerekli)",IF(AND(OR(G52="EN",G52="EN (+DE artı)"),Z52>=0.6),"B – Başvur (İngilizce)","C – Opsiyonel"))) -> C – Opsiyonel | AC52: Almanca CV + Anschreiben ile başvur (Almanca B1/B2 belirt) | AD52: https://www.karriere.at/f/x-tention-informationstechnologie | AE52: =Z52+IF(OR(G52="EN",G52="EN (+DE artı)"),1,0) -> 0.63
A53: 49 | B53: SIGMATEK GmbH & Co KG | C53: Senior IT Systems Engineer | D53: Lamprechtshausen | E53: 30–45 dk | F53: Sistem / altyapı | G53: DE+EN | H53: Selbstständige, methodische und strukturierte Arbeitsweise Gute Deutsch- und Englischkenntnisse in Wort und Schrift Wir bieten Onboarding Pro | I53: — | J53: Kıdemli / yönetici | K53: İlanda belirtilmemiş | L53: 2026-09-26 | M53: karriere.at | N53: https://www.karriere.at/jobs/7872163 | O53: 27.09.2026 14:13 · HTTP 200 · AÇIK | Q53: und Erfahrung. Bewerbung absenden We MaxUp Your Automation… | R53: Active Directory, Windows Server, Sanallaştırma (Hyper-V/Proxmox), Backup / DR, Ağ / Firewall / VPN, Microsoft ortamı | S53: Intune / M365 admin, Scripting / otomasyon (PowerShell vb.), Linux, VMware, Ağ üreticisi sertifikası (Cisco/Fortinet/Palo Alto) | T53: 3 | U53: 4.5 | V53: 2 | W53: 4 | X53: 4 | Y53: 3.5 | Z53: =ROUND((T53*Özet!$C$14+U53*Özet!$C$15+V53*Özet!$C$16+W53*Özet!$C$17+X53*Özet!$C$18+Y53*Özet!$C$19)/5,4) -> 0.625 | AA53: =RANK(AE53,$AE$5:$AE$126)+COUNTIF($AE$5:AE53,AE53)-1 -> 49 | AB53: =IF(AND(OR(G53="EN",G53="EN (+DE artı)"),Z53>=0.7),"A – Hemen başvur (İngilizce)",IF(Z53>=0.7,"B – Başvur (Almanca gerekli)",IF(AND(OR(G53="EN",G53="EN (+DE artı)"),Z53>=0.6),"B – Başvur (İngilizce)","C – Opsiyonel"))) -> C – Opsiyonel | AC53: Almanca CV ile başvur; İngilizce yeterliliğini ve Almanca B1/B2'yi açıkça yaz | AD53: https://www.karriere.at/f/sigmatek | AE53: =Z53+IF(OR(G53="EN",G53="EN (+DE artı)"),1,0) -> 0.625
A54: 50 | B54: Universität Salzburg | C54: IT-AV-Engineer | D54: Salzburg | E54: ≤30 dk (Salzburg / yakın çevre) | F54: Sistem / altyapı | G54: DE C1 | H54: und Programmierkenntnisse mit Schwerpunkt auf AV-Systeme Sehr gute Deutschkenntnisse (C1) und gute Englischkenntnisse (B2) Führerschein B Strukt | I54: — | J54: Uzman (mid-senior) | K54: ~€48k+/yıl (ilan: ab 48.304,20 € jährlich) | L54: 2026-09-27 | M54: karriere.at | N54: https://www.karriere.at/jobs/7862965 | O54: 27.09.2026 14:13 · HTTP 200 · AÇIK | P54: https://www.linkedin.com/jobs/view/4458164478 | Q54: Fachliche Anforderungen Mehrjährige einschlägige Berufserfahrung in den genannten Aufgabenbereichen sowie der Live-Kongresstechnik und Live-Streaming Erfahrung im professionellen Audio-und Videobereich Gute Kenntnisse im Bereich Kommunikationstechnik und Netzwerktechnologie Gute IT- und Programmierkenntnisse mit Schwerpunkt auf AV-Systeme Sehr gute Deutschkenntnisse (C1) und gute Englischkenntnisse (B2) Führerschein… | R54: Ağ / Firewall / VPN, Ekip liderliği | S54: Almanca C1 / çok iyi Almanca, Programlama | T54: 4 | U54: 4 | V54: 1 | W54: 3.5 | X54: 5 | Y54: 3.5 | Z54: =ROUND((T54*Özet!$C$14+U54*Özet!$C$15+V54*Özet!$C$16+W54*Özet!$C$17+X54*Özet!$C$18+Y54*Özet!$C$19)/5,4) -> 0.625 | AA54: =RANK(AE54,$AE$5:$AE$126)+COUNTIF($AE$5:AE54,AE54)-1 -> 50 | AB54: =IF(AND(OR(G54="EN",G54="EN (+DE artı)"),Z54>=0.7),"A – Hemen başvur (İngilizce)",IF(Z54>=0.7,"B – Başvur (Almanca gerekli)",IF(AND(OR(G54="EN",G54="EN (+DE artı)"),Z54>=0.6),"B – Başvur (İngilizce)","C – Opsiyonel"))) -> C – Opsiyonel | AC54: Almanca C1 isteniyor – yine de başvurmak istersen Almanca CV + dil planı (kurs/sertifika) belirt · İletişim: disability@plus.ac.at. | AD54: https://www.karriere.at/f/universit%C3%A4t-salzburg-personalabteilung | AE54: =Z54+IF(OR(G54="EN",G54="EN (+DE artı)"),1,0) -> 0.625
A55: 51 | B55: Heimat Österreich gemeinnützige Wohnungs- und Siedlungsgesellschaft m.b.H. | C55: IT Systemadministrator (m/w/d) | D55: Salzburg (Stadt) | E55: ≤30 dk (Salzburg / yakın çevre) | F55: Sistem / altyapı | G55: DE | H55: İlan Almanca; seviye belirtilmemiş | I55: — | J55: Uzman (mid-senior) | K55: ~€50k+/yıl (ilan: ab 3.590,30 € monatlich) | L55: 2026-09-20 | M55: karriere.at | N55: https://www.karriere.at/jobs/7852229 | O55: 27.09.2026 14:13 · HTTP 200 · AÇIK | Q55: Abgeschlossene Ausbildung im Bereich Informatik oder eine vergleichbare Qualifikation Mehrjährige Berufserfahrung in der Systemadministrationn sowie im User Support Fundiertes Wissen im Software- und Hardware sowie Erfahrung mit Windows Serverbetriebssystemen (2016-2025), Virtualisierung (VMware) und Netzwerktechnik Erfahrung im Bereich Microsoft Azure, Microsoft Entra, DNS Verwaltung, Email Workflows und Anti Spam I… | R55: Windows Server, Sanallaştırma (Hyper-V/Proxmox), Backup / DR, Ağ / Firewall / VPN, Microsoft ortamı | S55: Azure / Entra ID, Linux, VMware | T55: 3.5 | U55: 4 | V55: 1.5 | W55: 3.5 | X55: 5 | Y55: 3.5 | Z55: =ROUND((T55*Özet!$C$14+U55*Özet!$C$15+V55*Özet!$C$16+W55*Özet!$C$17+X55*Özet!$C$18+Y55*Özet!$C$19)/5,4) -> 0.625 | AA55: =RANK(AE55,$AE$5:$AE$126)+COUNTIF($AE$5:AE55,AE55)-1 -> 51 | AB55: =IF(AND(OR(G55="EN",G55="EN (+DE artı)"),Z55>=0.7),"A – Hemen başvur (İngilizce)",IF(Z55>=0.7,"B – Başvur (Almanca gerekli)",IF(AND(OR(G55="EN",G55="EN (+DE artı)"),Z55>=0.6),"B – Başvur (İngilizce)","C – Opsiyonel"))) -> C – Opsiyonel | AC55: Almanca CV + Anschreiben ile başvur (Almanca B1/B2 belirt) | AD55: https://www.karriere.at/f/heimat-%C3%B6sterreich-gemeinn%C3%BCtzige-wohnungs-und-siedlungsgesellschaft | AE55: =Z55+IF(OR(G55="EN",G55="EN (+DE artı)"),1,0) -> 0.625
A56: 52 | B56: iTaurus IT Dienstleistungs GmbH | C56: Systems Engineer (all genders) | D56: Bergheim | E56: ≤30 dk (Salzburg / yakın çevre) | F56: Sistem / altyapı | G56: DE C1 | H56: sprichst fließend IT - und das nicht nur auf Deutsch, sondern auch auf Englisch | I56: — | J56: Uzman (mid-senior) | K56: ~€63k+/yıl (ilan: 4.500 € – 6.500 € monatlich) | L56: 2026-09-23 | M56: karriere.at | N56: https://www.karriere.at/jobs/10030831 | O56: 27.09.2026 14:13 · HTTP 200 · AÇIK | Q56: & Erfahrung zwischen 4.500 EUR und 6.500 EUR brutto pro Monat (auf 38,5 Stunden Basis). Das Gehalt wird 14-mal jährlich ausbezahlt. Es gilt der Kollektivvertrag Informationstechnologie, Datenverarbeitung (IT). 4.500 EUR 6.500 EUR Überstunden Anfallende Überstunden werden teilweise in Form von Zeitausgleich abgegolten und teilweise ausbezahlt. Benefits Aus- und Weiterbildung Essenszulage Firmenhandy Firmennotebook Fle… | R56: Windows Server, Backup / DR, Ağ / Firewall / VPN, Microsoft ortamı, Perakende / çok lokasyon | S56: Almanca C1 / çok iyi Almanca, ANA ŞART: Intune / M365 admin | T56: 3.5 | U56: 4 | V56: 1 | W56: 4 | X56: 5 | Y56: 4.5 | Z56: =ROUND((T56*Özet!$C$14+U56*Özet!$C$15+V56*Özet!$C$16+W56*Özet!$C$17+X56*Özet!$C$18+Y56*Özet!$C$19)/5,4) -> 0.62 | AA56: =RANK(AE56,$AE$5:$AE$126)+COUNTIF($AE$5:AE56,AE56)-1 -> 52 | AB56: =IF(AND(OR(G56="EN",G56="EN (+DE artı)"),Z56>=0.7),"A – Hemen başvur (İngilizce)",IF(Z56>=0.7,"B – Başvur (Almanca gerekli)",IF(AND(OR(G56="EN",G56="EN (+DE artı)"),Z56>=0.6),"B – Başvur (İngilizce)","C – Opsiyonel"))) -> C – Opsiyonel | AC56: Almanca C1 isteniyor – yine de başvurmak istersen Almanca CV + dil planı (kurs/sertifika) belirt | AD56: https://www.karriere.at/f/itaurus-it-dienstleistungs-gmbh | AE56: =Z56+IF(OR(G56="EN",G56="EN (+DE artı)"),1,0) -> 0.62
A57: 53 | B57: ACP Gruppe | C57: IT Operations Engineer | D57: Salzburg | E57: ≤30 dk (Salzburg / yakın çevre) | F57: Sistem / altyapı | G57: DE | H57: İlan Almanca; seviye belirtilmemiş | I57: — | J57: Uzman (mid-senior) | K57: ~€45k+/yıl (ilan: > € 45000 jährlich) | L57: 2025-12-29 | M57: ACP portalı | N57: https://bewerbung.acp-gruppe.com/at/rx/906 | O57: 27.09.2026 14:14 · HTTP 200 · AÇIK | Q57: Sie begeistern sich für aktuelle IT‑Infrastrukturen, arbeiten proaktiv und bringen hohe Lernbereitschaft mit. Sie erkennen technische Probleme schnell, analysieren diese strukturiert und lösen sie kundenorientiert. Sie verfügen über eine abgeschlossene IT‑Ausbildung (Lehre, Fachschule, HTL) und erste praktische Erfahrung im IT‑Support oder technischen Kundendienst. Sie besitzen fundierte Kenntnisse im Umgang mit Micr… | R57: Windows Server, Sanallaştırma (Hyper-V/Proxmox), Backup / DR, Ağ / Firewall / VPN, Tedarikçi yönetimi, Microsoft ortamı | S57: Intune / M365 admin, Scripting / otomasyon (PowerShell vb.), VMware, Programlama | T57: 3.5 | U57: 4 | V57: 1.5 | W57: 4 | X57: 5 | Y57: 3 | Z57: =ROUND((T57*Özet!$C$14+U57*Özet!$C$15+V57*Özet!$C$16+W57*Özet!$C$17+X57*Özet!$C$18+Y57*Özet!$C$19)/5,4) -> 0.62 | AA57: =RANK(AE57,$AE$5:$AE$126)+COUNTIF($AE$5:AE57,AE57)-1 -> 53 | AB57: =IF(AND(OR(G57="EN",G57="EN (+DE artı)"),Z57>=0.7),"A – Hemen başvur (İngilizce)",IF(Z57>=0.7,"B – Başvur (Almanca gerekli)",IF(AND(OR(G57="EN",G57="EN (+DE artı)"),Z57>=0.6),"B – Başvur (İngilizce)","C – Opsiyonel"))) -> C – Opsiyonel | AC57: Almanca CV + Anschreiben ile başvur (Almanca B1/B2 belirt) | AD57: https://bewerbung.acp-gruppe.com/at | AE57: =Z57+IF(OR(G57="EN",G57="EN (+DE artı)"),1,0) -> 0.62
A58: 54 | B58: TNT Personalberatung GmbH | C58: IT-Spezialist (w/m/d) | D58: Salzburg | E58: ≤30 dk (Salzburg / yakın çevre) | F58: IT destek / service desk | G58: DE C1 | H58: gute Deutschkenntnisse in Wort und Schrift | I58: — | J58: Orta / giriş – aday overqualified | K58: ~€60k+/yıl (ilan: ab 60.000 € jährlich) | L58: 2026-09-21 | M58: karriere.at | N58: https://www.karriere.at/jobs/7869670 | O58: 27.09.2026 14:13 · HTTP 200 · AÇIK | Q58: Eine abgeschlossene IT-Ausbildung (z. B. HTL, Lehre, Fachschule oder vergleichbar). Mehrjährige Berufserfahrung in der Systemadministration. Gute Kenntnisse in den Bereichen Client, Server und Netzwerk. Interesse an IT-Security und modernen Infrastruktur-Lösungen. Eine selbstständige, lösungsorientierte und zuverlässige Arbeitsweise. Sehr gute Deutschkenntnisse in Wort und Schrift. Das erwartet Sie: Flexible Arbeits… | R58: Ağ / Firewall / VPN | S58: Almanca C1 / çok iyi Almanca | T58: 4 | U58: 3 | V58: 1 | W58: 3.5 | X58: 5 | Y58: 4.5 | Z58: =ROUND((T58*Özet!$C$14+U58*Özet!$C$15+V58*Özet!$C$16+W58*Özet!$C$17+X58*Özet!$C$18+Y58*Özet!$C$19)/5,4) -> 0.615 | AA58: =RANK(AE58,$AE$5:$AE$126)+COUNTIF($AE$5:AE58,AE58)-1 -> 54 | AB58: =IF(AND(OR(G58="EN",G58="EN (+DE artı)"),Z58>=0.7),"A – Hemen başvur (İngilizce)",IF(Z58>=0.7,"B – Başvur (Almanca gerekli)",IF(AND(OR(G58="EN",G58="EN (+DE artı)"),Z58>=0.6),"B – Başvur (İngilizce)","C – Opsiyonel"))) -> C – Opsiyonel | AC58: Almanca C1 isteniyor – yine de başvurmak istersen Almanca CV + dil planı (kurs/sertifika) belirt · Personel danışmanı ilanı → danışmanı telefon/e-posta ile ara, diğer açık pozisyonlarını da sor · İletişim: miguel.tejeda@tntpersonal.at | AD58: https://www.karriere.at/f/tnt-personalberatung | AE58: =Z58+IF(OR(G58="EN",G58="EN (+DE artı)"),1,0) -> 0.615
A59: 55 | B59: NTS | C59: Senior Systems Engineer Network & Security (m/w/d) | D59: Salzburg, Wien, Graz, Linz | E59: ≤30 dk (Salzburg / yakın çevre) | F59: Cyber Security – teknik | G59: DE C1 | H59: Prioritäten im Incident-, Problem- und Change-Management Sehr gute Deutsch- und Englischkenntnisse in Wort und Schrift Hervorragende Kommunikati | I59: — | J59: Kıdemli / yönetici | K59: ~€70k+/yıl (ilan: ab 70.000 € jährlich) | L59: 2026-09-21 | M59: karriere.at | N59: https://www.karriere.at/jobs/7863661 | O59: 27.09.2026 14:13 · HTTP 200 · AÇIK | P59: https://www.linkedin.com/jobs/view/4454189709 | Q59: Mehrjährige praktische Erfahrung im Betrieb, Support und der Weiterentwicklung von Netzwerk-Infrastrukturen Fundierte Kenntnisse in Netzwerktechnologien, Routing, Switching, WLAN und TCP/IP (Cisco CCNA oder vergleichbare Kenntnisse) Erfahrung im Betrieb und in der Administration von Firewall-, VPN- und Security-Lösungen, vorzugsweise Palo Alto Kenntnisse im Bereich Network Security, Netzwerksegmentierung und Zugriffs… | R59: ITIL / ITSM, Ağ / Firewall / VPN, Tedarikçi yönetimi, Ekip liderliği | S59: Almanca C1 / çok iyi Almanca, ANA ŞART: Ağ üreticisi sertifikası (Cisco/Fortinet/Palo Alto) | T59: 3 | U59: 4.5 | V59: 1 | W59: 4 | X59: 5 | Y59: 5 | Z59: =ROUND((T59*Özet!$C$14+U59*Özet!$C$15+V59*Özet!$C$16+W59*Özet!$C$17+X59*Özet!$C$18+Y59*Özet!$C$19)/5,4) -> 0.615 | AA59: =RANK(AE59,$AE$5:$AE$126)+COUNTIF($AE$5:AE59,AE59)-1 -> 55 | AB59: =IF(AND(OR(G59="EN",G59="EN (+DE artı)"),Z59>=0.7),"A – Hemen başvur (İngilizce)",IF(Z59>=0.7,"B – Başvur (Almanca gerekli)",IF(AND(OR(G59="EN",G59="EN (+DE artı)"),Z59>=0.6),"B – Başvur (İngilizce)","C – Opsiyonel"))) -> C – Opsiyonel | AC59: Almanca C1 isteniyor – yine de başvurmak istersen Almanca CV + dil planı (kurs/sertifika) belirt | AD59: https://www.karriere.at/f/nts | AE59: =Z59+IF(OR(G59="EN",G59="EN (+DE artı)"),1,0) -> 0.615
A60: 56 | B60: CANCOM Austria AG | C60: Senior System Engineer Endpoint Management (w/m/*) | D60: Dornbirn, Innsbruck, Klagenfurt, Linz, Raaba-Grambach, Salzburg (Stadt), Wien | E60: ≤30 dk (Salzburg / yakın çevre) | F60: Sistem / altyapı | G60: DE C1 | H60: und komplexe Zusammenhänge verständlich zu kommunizieren Sehr gute Deutsch- und Englischkenntnisse in Wort und Schrift, ausgeprägte Kund:innen- | I60: — | J60: Kıdemli / yönetici | K60: ~€70k+/yıl (ilan: ab 70.000 € jährlich) | L60: 2026-09-21 | M60: karriere.at | N60: https://www.karriere.at/jobs/7839929 | O60: 27.09.2026 14:13 · HTTP 200 · AÇIK | Q60: und Erfahrung definieren wir dein individuelles Package Deine Aufgaben Beratung im Bereich Endpoint Management, von der Anforderungsanalyse über die Konzeption bis hin zur technischen Umsetzung moderner Client-Management- und Modern-Workplace-Lösungen Bearbeitung von Incidents, Service Requests und Changes im Microsoft Endpoint Management Umfeld sowie Analyse und Behebung komplexer Störungen in Microsoft Intune-, Con… | R60: ITIL / ITSM, Windows Server, Ağ / Firewall / VPN, Tedarikçi yönetimi, Ekip liderliği, Politika / uyum, Microsoft ortamı | S60: Almanca C1 / çok iyi Almanca, Azure / Entra ID, ANA ŞART: Intune / M365 admin, Scripting / otomasyon (PowerShell vb.), AI / ML | T60: 3 | U60: 4.5 | V60: 1 | W60: 4 | X60: 5 | Y60: 5 | Z60: =ROUND((T60*Özet!$C$14+U60*Özet!$C$15+V60*Özet!$C$16+W60*Özet!$C$17+X60*Özet!$C$18+Y60*Özet!$C$19)/5,4) -> 0.615 | AA60: =RANK(AE60,$AE$5:$AE$126)+COUNTIF($AE$5:AE60,AE60)-1 -> 56 | AB60: =IF(AND(OR(G60="EN",G60="EN (+DE artı)"),Z60>=0.7),"A – Hemen başvur (İngilizce)",IF(Z60>=0.7,"B – Başvur (Almanca gerekli)",IF(AND(OR(G60="EN",G60="EN (+DE artı)"),Z60>=0.6),"B – Başvur (İngilizce)","C – Opsiyonel"))) -> C – Opsiyonel | AC60: Almanca C1 isteniyor – yine de başvurmak istersen Almanca CV + dil planı (kurs/sertifika) belirt | AD60: https://www.karriere.at/f/cancomaustria | AE60: =Z60+IF(OR(G60="EN",G60="EN (+DE artı)"),1,0) -> 0.615
A61: 57 | B61: CANCOM Austria AG | C61: Presales Consultant Security (w/m/*) | D61: Leonding, Salzburg (Stadt) | E61: ≤30 dk (Salzburg / yakın çevre) | F61: Cyber Security – teknik | G61: DE C1 | H61: eine selbstständige und teamorientierte Arbeitsweise Sehr gute Deutsch- und Englischkenntnisse sowie großes Interesse an technischen Sicherh | I61: — | J61: Kıdemli / yönetici | K61: ~€70k+/yıl (ilan: ab 70.000 € jährlich) | L61: 2026-09-27 | M61: karriere.at | N61: https://www.karriere.at/jobs/7873291 | O61: 27.09.2026 14:14 · HTTP 200 · AÇIK | Q61: und Erfahrung definieren wir dein individuelles Package Deine Aufgaben Verantwortung für das Design von IT-Sicherheitslösungen sowie deren professionelle Präsentation bei Kund:innen Schnittstelle zwischen Vertrieb und Technik, Analyse der Kundenanforderungen, Beratung zu IT-Sicherheitslösungen und Erstellung maßgeschneiderter Sicherheitskonzepte Enge Abstimmung mit internen Teams zur Entwicklung und Umsetzung von Sic… | R61: Ağ / Firewall / VPN, Tedarikçi yönetimi, Ekip liderliği | S61: Almanca C1 / çok iyi Almanca, Ağ üreticisi sertifikası (Cisco/Fortinet/Palo Alto), AI / ML | T61: 3 | U61: 4.5 | V61: 1 | W61: 4 | X61: 5 | Y61: 5 | Z61: =ROUND((T61*Özet!$C$14+U61*Özet!$C$15+V61*Özet!$C$16+W61*Özet!$C$17+X61*Özet!$C$18+Y61*Özet!$C$19)/5,4) -> 0.615 | AA61: =RANK(AE61,$AE$5:$AE$126)+COUNTIF($AE$5:AE61,AE61)-1 -> 57 | AB61: =IF(AND(OR(G61="EN",G61="EN (+DE artı)"),Z61>=0.7),"A – Hemen başvur (İngilizce)",IF(Z61>=0.7,"B – Başvur (Almanca gerekli)",IF(AND(OR(G61="EN",G61="EN (+DE artı)"),Z61>=0.6),"B – Başvur (İngilizce)","C – Opsiyonel"))) -> C – Opsiyonel | AC61: Almanca C1 isteniyor – yine de başvurmak istersen Almanca CV + dil planı (kurs/sertifika) belirt | AD61: https://www.karriere.at/f/cancomaustria | AE61: =Z61+IF(OR(G61="EN",G61="EN (+DE artı)"),1,0) -> 0.615
A62: 58 | B62: TNT Personal | C62: IT-Spezialist:in | D62: Salzburg, Austria | E62: ≤30 dk (Salzburg / yakın çevre) | F62: IT destek / service desk | G62: DE C1 | H62: gute Deutschkenntnisse in Wort und Schrift | I62: — | J62: Orta / giriş – aday overqualified | K62: ~€60k+/yıl (ilan metninden) | L62: 2026-09-03 | M62: LinkedIn | N62: https://www.linkedin.com/jobs/view/4460493025 | O62: 27.09.2026 14:14 · HTTP 200 · AÇIK | Q62: Eine abgeschlossene IT-Ausbildung (z. B. HTL, Lehre, Fachschule oder vergleichbar). Mehrjährige Berufserfahrung in der Systemadministration. Gute Kenntnisse in den Bereichen Client, Server und Netzwerk. Interesse an IT-Security und modernen Infrastruktur-Lösungen. Eine selbstständige, lösungsorientierte und zuverlässige Arbeitsweise. Sehr gute Deutschkenntnisse in Wort und Schrift. Das erwartet Sie: Flexible Arbeits… | R62: Ağ / Firewall / VPN | S62: Almanca C1 / çok iyi Almanca | T62: 4 | U62: 3 | V62: 1 | W62: 3.5 | X62: 5 | Y62: 4.5 | Z62: =ROUND((T62*Özet!$C$14+U62*Özet!$C$15+V62*Özet!$C$16+W62*Özet!$C$17+X62*Özet!$C$18+Y62*Özet!$C$19)/5,4) -> 0.615 | AA62: =RANK(AE62,$AE$5:$AE$126)+COUNTIF($AE$5:AE62,AE62)-1 -> 58 | AB62: =IF(AND(OR(G62="EN",G62="EN (+DE artı)"),Z62>=0.7),"A – Hemen başvur (İngilizce)",IF(Z62>=0.7,"B – Başvur (Almanca gerekli)",IF(AND(OR(G62="EN",G62="EN (+DE artı)"),Z62>=0.6),"B – Başvur (İngilizce)","C – Opsiyonel"))) -> C – Opsiyonel | AC62: Almanca C1 isteniyor – yine de başvurmak istersen Almanca CV + dil planı (kurs/sertifika) belirt · Personel danışmanı ilanı → danışmanı telefon/e-posta ile ara, diğer açık pozisyonlarını da sor · İletişim: miguel.tejeda@tntpersonal.at | AD62: https://at.linkedin.com/company/tnt-personal | AE62: =Z62+IF(OR(G62="EN",G62="EN (+DE artı)"),1,0) -> 0.615
A63: 59 | B63: KPMG Österreich | C63: Expert:in Information Security Strategy & Transformation | D63: Wien, Graz, Klagenfurt, Linz, Salzburg | E63: ≤30 dk (Salzburg / yakın çevre) | F63: Cyber Security – yönetişim / ISMS | G63: DE C1 | H63: Zukunftsthemen der Digitalisierung von Vorteil Ausgezeichnete Deutsch- und Englischkenntnisse in Wort und Schrift Wenn du nicht alle Kompet | I63: — | J63: Kıdemli / yönetici | K63: ~€58k+/yıl (ilan: ab 58.000 € jährlich) | L63: 2026-09-20 | M63: karriere.at | N63: https://www.karriere.at/jobs/7868491 | O63: 27.09.2026 14:14 · HTTP 200 · AÇIK | Q63: unserer Kund:innen. Entsprechend deiner Erfahrung werden deine Aufgaben nicht nur in der Projektmitarbeit, sondern auch in der Projektleitung liegen. Perpektiven Rasche Übernahme von Projekt-& Führungsverantwortung um die kniffeligsten Herausforderungen unserer Kund:innen im Bereich Information Security Strategy & Transformation zu lösen Aktive Mitgestaltung in der Weiterentwicklung unseres Bereichs Information Secur… | R63: ITIL / ITSM, Active Directory, Backup / DR, Ağ / Firewall / VPN, Proje yönetimi, Bütçe, Ekip liderliği, Perakende / çok lokasyon | S63: Almanca C1 / çok iyi Almanca, Azure / Entra ID, Scripting / otomasyon (PowerShell vb.), Container / IaC / DevOps, Programlama, CISSP / CISM / CISA, AWS / GCP, ANA ŞART: AI / ML | T63: 3 | U63: 5 | V63: 1 | W63: 4 | X63: 5 | Y63: 4 | Z63: =ROUND((T63*Özet!$C$14+U63*Özet!$C$15+V63*Özet!$C$16+W63*Özet!$C$17+X63*Özet!$C$18+Y63*Özet!$C$19)/5,4) -> 0.61 | AA63: =RANK(AE63,$AE$5:$AE$126)+COUNTIF($AE$5:AE63,AE63)-1 -> 59 | AB63: =IF(AND(OR(G63="EN",G63="EN (+DE artı)"),Z63>=0.7),"A – Hemen başvur (İngilizce)",IF(Z63>=0.7,"B – Başvur (Almanca gerekli)",IF(AND(OR(G63="EN",G63="EN (+DE artı)"),Z63>=0.6),"B – Başvur (İngilizce)","C – Opsiyonel"))) -> C – Opsiyonel | AC63: Almanca C1 isteniyor – yine de başvurmak istersen Almanca CV + dil planı (kurs/sertifika) belirt · İletişim: bewerbung@kpmg.at. | AD63: https://www.karriere.at/f/kpmg-%C3%B6sterreich | AE63: =Z63+IF(OR(G63="EN",G63="EN (+DE artı)"),1,0) -> 0.61
A64: 60 | B64: Ginzinger electronic systems GmbH | C64: IT 1st & 2nd Level Support | D64: Weng im Innkreis | E64: 45–60 dk | F64: IT destek / service desk | G64: DE+EN | H64: Teamfähigkeit, Kommunikationsstärke und Lernbereitschaft Gute Deutschkenntnisse, Englischkenntnisse von Vorteil Wir bieten dir: Wir bieten | I64: — | J64: Orta / giriş – aday overqualified | K64: İlanda belirtilmemiş | L64: 2026-09-26 | M64: karriere.at | N64: https://www.karriere.at/jobs/10024863 | O64: 27.09.2026 14:14 · HTTP 200 · AÇIK | Q64: Abgeschlossene Ausbildung im Bereich IT (z.B. Lehre, HTL oder vergleichbare Qualifikation) Erste Berufserfahrung im IT-Support von Vorteil Gute Kenntnisse in den Bereichen Windows, Microsoft 365, Netzwerke und Hardware Kenntnisse in Linux und im Bereich Visualisierung von Vorteil Strukturierte, selbstständige und serviceorientierte Arbeitsweise Freude am direkten Kontakt mit AnwenderInnen und an der Lösung technisch… | R64: Windows Server, Ağ / Firewall / VPN, Proje yönetimi, Tedarikçi yönetimi, Microsoft ortamı, Perakende / çok lokasyon | S64: Intune / M365 admin, Linux | T64: 4 | U64: 3 | V64: 2 | W64: 4 | X64: 3 | Y64: 3 | Z64: =ROUND((T64*Özet!$C$14+U64*Özet!$C$15+V64*Özet!$C$16+W64*Özet!$C$17+X64*Özet!$C$18+Y64*Özet!$C$19)/5,4) -> 0.61 | AA64: =RANK(AE64,$AE$5:$AE$126)+COUNTIF($AE$5:AE64,AE64)-1 -> 60 | AB64: =IF(AND(OR(G64="EN",G64="EN (+DE artı)"),Z64>=0.7),"A – Hemen başvur (İngilizce)",IF(Z64>=0.7,"B – Başvur (Almanca gerekli)",IF(AND(OR(G64="EN",G64="EN (+DE artı)"),Z64>=0.6),"B – Başvur (İngilizce)","C – Opsiyonel"))) -> C – Opsiyonel | AC64: Almanca CV ile başvur; İngilizce yeterliliğini ve Almanca B1/B2'yi açıkça yaz | AD64: https://www.karriere.at/f/ginzinger-electronic-systems | AE64: =Z64+IF(OR(G64="EN",G64="EN (+DE artı)"),1,0) -> 0.61
A65: 61 | B65: EVER Pharma | C65: Team Lead Business Solutions, AI & Collaboration (m/w/d) | D65: Unterach am Attersee | E65: 45–60 dk | F65: IT yönetimi / liderlik | G65: DE | H65: İlan Almanca; seviye belirtilmemiş | I65: — | J65: Kıdemli / yönetici | K65: ~€61k+/yıl (ilan: ab 60.977,70 € jährlich) | L65: 2026-09-20 | M65: karriere.at | N65: https://www.karriere.at/jobs/10029632 | O65: 27.09.2026 14:14 · HTTP 200 · AÇIK | Q65: Mehrjährige praktische Berufserfahrung in den IT und Digitalisierungsbereichen Studium Informatik, Wirtschaftsinformatik oder vergleichbarer Ausbildung Sehr gutes Verständnis für Geschäftsprozesse und deren digitale Unterstützung Erste Führungserfahrung oder den klaren Wunsch, ein Team zu führen Sie packen Projekte pragmatisch und lösungsorientiert an Das bieten wir Wir bieten Ihnen ein spannendes, anspruchsvolles un… | R65: Ekip liderliği, Microsoft ortamı, Perakende / çok lokasyon | S65: Intune / M365 admin, Scripting / otomasyon (PowerShell vb.), İş uygulaması alanı (CRM/ERP/Legal/ServiceNow…), ANA ŞART: AI / ML | T65: 3 | U65: 5 | V65: 1.5 | W65: 4 | X65: 3 | Y65: 4.5 | Z65: =ROUND((T65*Özet!$C$14+U65*Özet!$C$15+V65*Özet!$C$16+W65*Özet!$C$17+X65*Özet!$C$18+Y65*Özet!$C$19)/5,4) -> 0.61 | AA65: =RANK(AE65,$AE$5:$AE$126)+COUNTIF($AE$5:AE65,AE65)-1 -> 61 | AB65: =IF(AND(OR(G65="EN",G65="EN (+DE artı)"),Z65>=0.7),"A – Hemen başvur (İngilizce)",IF(Z65>=0.7,"B – Başvur (Almanca gerekli)",IF(AND(OR(G65="EN",G65="EN (+DE artı)"),Z65>=0.6),"B – Başvur (İngilizce)","C – Opsiyonel"))) -> C – Opsiyonel | AC65: Almanca CV + Anschreiben ile başvur (Almanca B1/B2 belirt) | AD65: https://www.karriere.at/f/ever-pharma | AE65: =Z65+IF(OR(G65="EN",G65="EN (+DE artı)"),1,0) -> 0.61
A66: 62 | B66: Windhager Home & Garden | C66: IT SYSTEM ENGINEER (m/w/d) | D66: Thalgau, Salzburg, Austria | E66: 30–45 dk | F66: Sistem / altyapı | G66: DE C1 | H66: Arbeitsweise zeichnen Sie aus Sie verfügen über ausgezeichnete Deutsch- und sehr gute Englischkenntnisse Vor allem aber ist es Ihnen ein Anl | I66: — | J66: Uzman (mid-senior) | K66: ~€45k+/yıl (ilan metninden) | L66: 2026-09-02 | M66: LinkedIn | N66: https://www.linkedin.com/jobs/view/4459936185 | O66: 27.09.2026 14:14 · HTTP 200 · AÇIK | Q66: und Erfahrung im persönlichen Gespräch festgelegt.… | R66: Ağ / Firewall / VPN, Microsoft ortamı, Perakende / çok lokasyon | S66: Almanca C1 / çok iyi Almanca, VMware | T66: 4 | U66: 4 | V66: 1 | W66: 5 | X66: 4 | Y66: 3 | Z66: =ROUND((T66*Özet!$C$14+U66*Özet!$C$15+V66*Özet!$C$16+W66*Özet!$C$17+X66*Özet!$C$18+Y66*Özet!$C$19)/5,4) -> 0.61 | AA66: =RANK(AE66,$AE$5:$AE$126)+COUNTIF($AE$5:AE66,AE66)-1 -> 62 | AB66: =IF(AND(OR(G66="EN",G66="EN (+DE artı)"),Z66>=0.7),"A – Hemen başvur (İngilizce)",IF(Z66>=0.7,"B – Başvur (Almanca gerekli)",IF(AND(OR(G66="EN",G66="EN (+DE artı)"),Z66>=0.6),"B – Başvur (İngilizce)","C – Opsiyonel"))) -> C – Opsiyonel | AC66: Almanca C1 isteniyor – yine de başvurmak istersen Almanca CV + dil planı (kurs/sertifika) belirt | AD66: https://at.linkedin.com/company/windhagerhandelsgesmbh | AE66: =Z66+IF(OR(G66="EN",G66="EN (+DE artı)"),1,0) -> 0.61
A67: 63 | B67: Wirtschaftskammer Salzburg | C67: IT Application Manager (m/w/d) | D67: Salzburg (Stadt) | E67: ≤30 dk (Salzburg / yakın çevre) | F67: Uygulama / iş uygulamaları | G67: DE | H67: für das selbstständige und eigenverantwortliche Arbeiten Gesicherte Deutsch- und Rechtschreibkenntnisse Freude an der Zusammenarbeit im Team sowi | I67: — | J67: Kıdemli / yönetici | K67: ~€50k+/yıl (ilan: ab 50.000 € jährlich) | L67: 2026-09-21 | M67: karriere.at | N67: https://www.karriere.at/jobs/7850054 | O67: 27.09.2026 14:13 · HTTP 200 · AÇIK | Q67: und Erfahrung.… | R67: SQL Server / DB, Proje yönetimi, Tedarikçi yönetimi, Ekip liderliği, Microsoft ortamı | S67: Programlama, İş uygulaması alanı (CRM/ERP/Legal/ServiceNow…) | T67: 3 | U67: 4.5 | V67: 1.5 | W67: 3.5 | X67: 5 | Y67: 3.5 | Z67: =ROUND((T67*Özet!$C$14+U67*Özet!$C$15+V67*Özet!$C$16+W67*Özet!$C$17+X67*Özet!$C$18+Y67*Özet!$C$19)/5,4) -> 0.61 | AA67: =RANK(AE67,$AE$5:$AE$126)+COUNTIF($AE$5:AE67,AE67)-1 -> 63 | AB67: =IF(AND(OR(G67="EN",G67="EN (+DE artı)"),Z67>=0.7),"A – Hemen başvur (İngilizce)",IF(Z67>=0.7,"B – Başvur (Almanca gerekli)",IF(AND(OR(G67="EN",G67="EN (+DE artı)"),Z67>=0.6),"B – Başvur (İngilizce)","C – Opsiyonel"))) -> C – Opsiyonel | AC67: Almanca CV + Anschreiben ile başvur (Almanca B1/B2 belirt) | AD67: https://www.karriere.at/f/wirtschaftskammer-salzburg | AE67: =Z67+IF(OR(G67="EN",G67="EN (+DE artı)"),1,0) -> 0.61
A68: 64 | B68: Salzburg AG für Energie, Verkehr und Telekommunikation | C68: IT Infrastructure Systems Engineer (all genders) | D68: Salzburg | E68: ≤30 dk (Salzburg / yakın çevre) | F68: Sistem / altyapı | G68: DE C1 | H68: sowie Eigeninitiative und Entscheidungskompetenz Sehr gute Deutsch‑ und Englischkenntnisse Wir bieten Vielfältiges und abwechslungsreich | I68: — | J68: Uzman (mid-senior) | K68: ~€55k+/yıl (ilan: ab 3.927,14 € monatlich) | L68: 2026-09-27 | M68: karriere.at | N68: https://www.karriere.at/jobs/7847861 | O68: 27.09.2026 14:13 · HTTP 200 · AÇIK | Q68: von heute und morgen. Aufgabenbereich Betrieb, Ausbau und kontinuierliche Weiterentwicklung unserer hochverfügbaren IT‑Infrastruktur End‑to‑End‑Verantwortung (Service Ownership) für zentrale IT-Infrastruktur‑Services, insbesondere: Windows Server Services (On‑Premises & Microsoft Azure) Active Directory / EntraID Virtuelle Desktop‑Infrastruktur & Remote‑Access‑Lösungen Zentrale Virtualisierungsplattformen (VMware vSp… | R68: ITIL / ITSM, Active Directory, Windows Server, Sanallaştırma (Hyper-V/Proxmox), Ekip liderliği, Microsoft ortamı | S68: Almanca C1 / çok iyi Almanca, ANA ŞART: Azure / Entra ID, VMware | T68: 3.5 | U68: 4 | V68: 1 | W68: 3.5 | X68: 5 | Y68: 4 | Z68: =ROUND((T68*Özet!$C$14+U68*Özet!$C$15+V68*Özet!$C$16+W68*Özet!$C$17+X68*Özet!$C$18+Y68*Özet!$C$19)/5,4) -> 0.605 | AA68: =RANK(AE68,$AE$5:$AE$126)+COUNTIF($AE$5:AE68,AE68)-1 -> 64 | AB68: =IF(AND(OR(G68="EN",G68="EN (+DE artı)"),Z68>=0.7),"A – Hemen başvur (İngilizce)",IF(Z68>=0.7,"B – Başvur (Almanca gerekli)",IF(AND(OR(G68="EN",G68="EN (+DE artı)"),Z68>=0.6),"B – Başvur (İngilizce)","C – Opsiyonel"))) -> C – Opsiyonel | AC68: Almanca C1 isteniyor – yine de başvurmak istersen Almanca CV + dil planı (kurs/sertifika) belirt | AD68: https://www.karriere.at/f/salzburg-f%C3%BCr-energie-verkehr-und-telekommunikation | AE68: =Z68+IF(OR(G68="EN",G68="EN (+DE artı)"),1,0) -> 0.605
A69: 65 | B69: KERN engineering careers GmbH | C69: Devops Engineer mit Security-Schwerpunkt (w/m/d) | D69: Linz, Steyr, Salzburg, Wels, Wien | E69: ≤30 dk (Salzburg / yakın çevre) | F69: Cyber Security – teknik | G69: DE+EN | H69: hast du schon selbst konfiguriert oder debuggt Du kannst dich auf Deutsch und Englisch problemlos mit Kolleg:innen im Ausland und externen Part | I69: — | J69: Uzman (mid-senior) | K69: ~€55k+/yıl (ilan: 3.900 € – 4.900 € monatlich) | L69: 2026-09-24 | M69: karriere.at | N69: https://www.karriere.at/jobs/7864984 | O69: 27.09.2026 14:14 · HTTP 200 · AÇIK | Q69: & Berufserfahrung zwischen EUR 3900 und EUR 4900 brutto / Monat (auf Vollzeitbasis). Klingt interessant? Am besten JETZT BEWERBEN und mehr über diese Position erfahren! Sollte es vorab Fragen geben, freut sich Verena Herrmann v.herrmann@kern-partner.at auf die Kontaktaufnahme. Jetzt Bewerben… | R69: Ağ / Firewall / VPN, Politika / uyum | S69: Azure / Entra ID, ANA ŞART: Container / IaC / DevOps | T69: 2.5 | U69: 4 | V69: 2 | W69: 3.5 | X69: 5 | Y69: 4 | Z69: =ROUND((T69*Özet!$C$14+U69*Özet!$C$15+V69*Özet!$C$16+W69*Özet!$C$17+X69*Özet!$C$18+Y69*Özet!$C$19)/5,4) -> 0.605 | AA69: =RANK(AE69,$AE$5:$AE$126)+COUNTIF($AE$5:AE69,AE69)-1 -> 65 | AB69: =IF(AND(OR(G69="EN",G69="EN (+DE artı)"),Z69>=0.7),"A – Hemen başvur (İngilizce)",IF(Z69>=0.7,"B – Başvur (Almanca gerekli)",IF(AND(OR(G69="EN",G69="EN (+DE artı)"),Z69>=0.6),"B – Başvur (İngilizce)","C – Opsiyonel"))) -> C – Opsiyonel | AC69: Almanca CV ile başvur; İngilizce yeterliliğini ve Almanca B1/B2'yi açıkça yaz · Personel danışmanı ilanı → danışmanı telefon/e-posta ile ara, diğer açık pozisyonlarını da sor · İletişim: v.herrmann@kern-partner.at | AD69: https://www.karriere.at/f/kern-engineering-careers | AE69: =Z69+IF(OR(G69="EN",G69="EN (+DE artı)"),1,0) -> 0.605
A70: 66 | B70: SPAR ICS – Information & Communication Services | C70: Techlead Database Platform (m/w/d) | D70: Salzburg (Stadt), Wien, Wernberg | E70: ≤30 dk (Salzburg / yakın çevre) | F70: Veritabanı | G70: DE C1 | H70: eng mit Fachbereichen und Infrastruktur-Teams zusammen Sehr guten Deutsch- und Englischkenntnissen Darauf kannst du dich freuen Arbeiten mit st | I70: — | J70: Kıdemli / yönetici | K70: ~€35k+/yıl (ilan: ab 35.000 € jährlich) | L70: 2026-09-23 | M70: karriere.at | N70: https://www.karriere.at/jobs/7868917 | O70: 27.09.2026 14:14 · HTTP 200 · AÇIK | P70: https://www.linkedin.com/jobs/view/4454710752 | Q70: Techlead Database Platform (m/w/d) Wir sind das "I" und "T" in Retail... Dienstort: Salzburg, Wernberg, Wien Ausmaß: Vollzeit SPAR ICS ist die IT-Gesellschaft der SPAR Österreich-Gruppe und kümmert sich um sämtliche IT-Belange von SPAR, INTERSPAR und SES Spar European Shopping Centers. Wir sind über 700 kluge Köpfe und haben zwei Agenden: Das reibungslose Einkaufserlebnis aller SPAR-Kund:innen in 5 Ländern und die di… | R70: Ağ / Firewall / VPN, SQL Server / DB, Tedarikçi yönetimi, Microsoft ortamı, Perakende / çok lokasyon | S70: Almanca C1 / çok iyi Almanca, Oracle | T70: 3.5 | U70: 4.5 | V70: 1 | W70: 5 | X70: 5 | Y70: 2.5 | Z70: =ROUND((T70*Özet!$C$14+U70*Özet!$C$15+V70*Özet!$C$16+W70*Özet!$C$17+X70*Özet!$C$18+Y70*Özet!$C$19)/5,4) -> 0.605 | AA70: =RANK(AE70,$AE$5:$AE$126)+COUNTIF($AE$5:AE70,AE70)-1 -> 66 | AB70: =IF(AND(OR(G70="EN",G70="EN (+DE artı)"),Z70>=0.7),"A – Hemen başvur (İngilizce)",IF(Z70>=0.7,"B – Başvur (Almanca gerekli)",IF(AND(OR(G70="EN",G70="EN (+DE artı)"),Z70>=0.6),"B – Başvur (İngilizce)","C – Opsiyonel"))) -> C – Opsiyonel | AC70: Almanca C1 isteniyor – yine de başvurmak istersen Almanca CV + dil planı (kurs/sertifika) belirt | AD70: https://www.karriere.at/f/spar-ics-information-communication-services | AE70: =Z70+IF(OR(G70="EN",G70="EN (+DE artı)"),1,0) -> 0.605
A71: 67 | B71: Lenzing AG | C71: IT Field Service Engineer (m/w/d) | D71: Lenzing | E71: 60–90 dk | F71: IT destek / service desk | G71: DE+EN | H71: İlan Almanca; seviye belirtilmemiş | I71: — | J71: Orta / giriş – aday overqualified | K71: ~€49k+/yıl (ilan: ab 3.500 € monatlich) | L71: 2026-09-21 | M71: karriere.at | N71: https://www.karriere.at/jobs/7878931 | O71: 27.09.2026 14:14 · HTTP 200 · AÇIK | Q71: und positionsrelevanten Berufserfahrung ist unsere Bereitschaft zur Überzahlung gegeben. Darüber hinaus nehmen Sie am Lenzing Bonussystem teil. Nutzen Sie diese Chance und gestalten Sie den Erfolg der Lenzing Gruppe mit! Ich freue mich über Ihre elektronische Onlinebewerbung. Ihr Ansprechpartner bei Fragen: Mag. Birgit Jedinger… | R71: — | S71: Belirgin teknik eksik yok | T71: 4 | U71: 3 | V71: 2 | W71: 4 | X71: 2 | Y71: 3.5 | Z71: =ROUND((T71*Özet!$C$14+U71*Özet!$C$15+V71*Özet!$C$16+W71*Özet!$C$17+X71*Özet!$C$18+Y71*Özet!$C$19)/5,4) -> 0.6 | AA71: =RANK(AE71,$AE$5:$AE$126)+COUNTIF($AE$5:AE71,AE71)-1 -> 67 | AB71: =IF(AND(OR(G71="EN",G71="EN (+DE artı)"),Z71>=0.7),"A – Hemen başvur (İngilizce)",IF(Z71>=0.7,"B – Başvur (Almanca gerekli)",IF(AND(OR(G71="EN",G71="EN (+DE artı)"),Z71>=0.6),"B – Başvur (İngilizce)","C – Opsiyonel"))) -> C – Opsiyonel | AC71: Almanca CV ile başvur; İngilizce yeterliliğini ve Almanca B1/B2'yi açıkça yaz | AD71: https://www.karriere.at/f/lenzing | AE71: =Z71+IF(OR(G71="EN",G71="EN (+DE artı)"),1,0) -> 0.6
A72: 68 | B72: x-tention Informationstechnologie GmbH | C72: Security Awareness Specialist (m/w/d) | D72: Klagenfurt am Wörthersee, Wien, St. Peter in der Au, Graz, Wels, Salzburg (Stadt) | E72: ≤30 dk (Salzburg / yakın çevre) | F72: Cyber Security – teknik | G72: DE C1 | H72: und hohes Maß an Verantwortungsbewusstsein Sehr gute Deutsch- und Englischkenntnisse in Wort und Schrift Deine Benefits | I72: — | J72: Uzman (mid-senior) | K72: ~€46k+/yıl (ilan: 3.300 € – 4.000 € monatlich) | L72: 2026-09-22 | M72: karriere.at | N72: https://www.karriere.at/jobs/10033437 | O72: 27.09.2026 14:13 · HTTP 200 · AÇIK | Q72: und Erfahrung bewegt sich dein monatliches Bruttogehalt zwischen EUR 3.300,- und EUR 4.000,- 3.300 EUR 4.000 EUR Benefits Aus- und Weiterbildung Die Zukunft der Healthcare-IT kann man nur gestalten, wenn man immer up-to-date bleibt. Darum ermöglichen wir dir gerne individuelle Aus- und Weiterbildungen, Seminare und Schulungen. Die Zukunft der Healthcare-IT kann man nur gestalten, wenn man immer up-to-date bleibt. Dar… | R72: Perakende / çok lokasyon | S72: Almanca C1 / çok iyi Almanca | T72: 3.5 | U72: 4 | V72: 1 | W72: 4 | X72: 5 | Y72: 3.5 | Z72: =ROUND((T72*Özet!$C$14+U72*Özet!$C$15+V72*Özet!$C$16+W72*Özet!$C$17+X72*Özet!$C$18+Y72*Özet!$C$19)/5,4) -> 0.6 | AA72: =RANK(AE72,$AE$5:$AE$126)+COUNTIF($AE$5:AE72,AE72)-1 -> 68 | AB72: =IF(AND(OR(G72="EN",G72="EN (+DE artı)"),Z72>=0.7),"A – Hemen başvur (İngilizce)",IF(Z72>=0.7,"B – Başvur (Almanca gerekli)",IF(AND(OR(G72="EN",G72="EN (+DE artı)"),Z72>=0.6),"B – Başvur (İngilizce)","C – Opsiyonel"))) -> C – Opsiyonel | AC72: Almanca C1 isteniyor – yine de başvurmak istersen Almanca CV + dil planı (kurs/sertifika) belirt | AD72: https://www.karriere.at/f/x-tention-informationstechnologie | AE72: =Z72+IF(OR(G72="EN",G72="EN (+DE artı)"),1,0) -> 0.6
A73: 69 | B73: Simplify Hospitality GmbH | C73: Support Specialist (m/w/d) | D73: Salzburg (Stadt), Wien 4. Bezirk (Wieden) | E73: ≤30 dk (Salzburg / yakın çevre) | F73: IT destek / service desk | G73: DE C1 | H73: lösungsorientierte und zuverlässige Arbeitsweise Fließende Deutschkenntnisse in Wort und Schrift Lernbereitschaft und Interesse an Softw | I73: — | J73: Orta / giriş – aday overqualified | K73: Sadece KV asgarisi: ~€37k/yıl (ab 2.676 € monatlich) – gerçek maaş belirtilmemiş, genelde üstünde | L73: 2026-09-11 | M73: karriere.at | N73: https://www.karriere.at/jobs/10032590 | O73: 27.09.2026 14:14 · HTTP 200 · AÇIK | Q73: Technische Ausbildung oder vergleichbare praktische Erfahrung Erfahrung im Kundenservice, Anwendersupport oder technischen Support Freude daran, komplexe Sachverhalte verständlich zu erklären Strukturierte, lösungsorientierte und zuverlässige Arbeitsweise Fließende Deutschkenntnisse in Wort und Schrift Lernbereitschaft und Interesse an Software und technischen Zusammenhängen Serviceorientierung und einen ruhigen Umga… | R73: Perakende / çok lokasyon | S73: Almanca C1 / çok iyi Almanca | T73: 4 | U73: 3 | V73: 1 | W73: 5 | X73: 5 | Y73: 3 | Z73: =ROUND((T73*Özet!$C$14+U73*Özet!$C$15+V73*Özet!$C$16+W73*Özet!$C$17+X73*Özet!$C$18+Y73*Özet!$C$19)/5,4) -> 0.6 | AA73: =RANK(AE73,$AE$5:$AE$126)+COUNTIF($AE$5:AE73,AE73)-1 -> 69 | AB73: =IF(AND(OR(G73="EN",G73="EN (+DE artı)"),Z73>=0.7),"A – Hemen başvur (İngilizce)",IF(Z73>=0.7,"B – Başvur (Almanca gerekli)",IF(AND(OR(G73="EN",G73="EN (+DE artı)"),Z73>=0.6),"B – Başvur (İngilizce)","C – Opsiyonel"))) -> C – Opsiyonel | AC73: Almanca C1 isteniyor – yine de başvurmak istersen Almanca CV + dil planı (kurs/sertifika) belirt | AD73: https://www.karriere.at/f/gastrodat | AE73: =Z73+IF(OR(G73="EN",G73="EN (+DE artı)"),1,0) -> 0.6
A74: 70 | B74: KTM AG | C74: Internal Control System (ICS) Specialist* | D74: Mattighofen, Upper Austria, Austria | E74: 45–60 dk | F74: Risk / uyum / iç kontrol | G74: DE C1 | H74: insbesondere Excel und PowerPoint ausgezeichnete Deutsch- und verhandlungssichere Englischkenntnisse ausgeprägte analytische u | I74: — | J74: Uzman (mid-senior) | K74: ~€57k+/yıl (ilan metninden) | L74: 2026-09-09 | M74: LinkedIn | N74: https://www.linkedin.com/jobs/view/4465016911 | O74: 27.09.2026 14:14 · HTTP 200 · AÇIK | Q74: und Best Practices Unterstützung bei der Durchführung von internen Audits und Sonderprüfungen Erstellung aussagekräftiger Berichte und Management-Reports für Vorstand und Führungskräfte Ansprechpartner für interne und externe Prüfer im Zusammenhang mit IKS- und Audit-Themen Dein Profil abgeschlossenes Studium der Betriebswirtschaft, Wirtschaftswissenschaften, Wirtschaftsprüfung, Finance, Risikomanagement oder verglei… | R74: Ekip liderliği, Risk yönetimi, Politika / uyum, Denetim / audit, Microsoft ortamı | S74: Almanca C1 / çok iyi Almanca | T74: 4 | U74: 4 | V74: 1 | W74: 4 | X74: 3 | Y74: 4 | Z74: =ROUND((T74*Özet!$C$14+U74*Özet!$C$15+V74*Özet!$C$16+W74*Özet!$C$17+X74*Özet!$C$18+Y74*Özet!$C$19)/5,4) -> 0.6 | AA74: =RANK(AE74,$AE$5:$AE$126)+COUNTIF($AE$5:AE74,AE74)-1 -> 70 | AB74: =IF(AND(OR(G74="EN",G74="EN (+DE artı)"),Z74>=0.7),"A – Hemen başvur (İngilizce)",IF(Z74>=0.7,"B – Başvur (Almanca gerekli)",IF(AND(OR(G74="EN",G74="EN (+DE artı)"),Z74>=0.6),"B – Başvur (İngilizce)","C – Opsiyonel"))) -> C – Opsiyonel | AC74: Almanca C1 isteniyor – yine de başvurmak istersen Almanca CV + dil planı (kurs/sertifika) belirt | AD74: https://at.linkedin.com/company/ktm-ag | AE74: =Z74+IF(OR(G74="EN",G74="EN (+DE artı)"),1,0) -> 0.6
A75: 71 | B75: Salzburger Festspielfonds | C75: IT System Administrator – Schwerpunkt Netzwerk und Sicherheit (m/w/d) | D75: Salzburg | E75: ≤30 dk (Salzburg / yakın çevre) | F75: Cyber Security – teknik | G75: DE C1 | H75: gute Deutschkenntnisse in Wort und Schrift sowie gute Englischkenntnisse | I75: — | J75: Uzman (mid-senior) | K75: ~€52k+/yıl (ilan: ab 3.699 € monatlich) | L75: 2026-09-24 | M75: karriere.at | N75: https://www.karriere.at/jobs/10031930 | O75: 27.09.2026 14:13 · HTTP 200 · AÇIK | Q75: Abgeschlossene technische Ausbildung (IT-Lehre), Studium im Bereich Informatik, Netzwerktechnik, IT-Security (FH oder Universität), oder eine vergleichbare Qualifikation mit entsprechender Berufserfahrung; Fundierte Kenntnisse in der Konfiguration und Administration von Switches, Routern und Firewalls, vorzugsweise mit Cisco- und Fortinet-Technologien; Mindestens fünf Jahre einschlägige Berufserfahrung in einer verg… | R75: Ağ / Firewall / VPN, Proje yönetimi, Ekip liderliği, Perakende / çok lokasyon | S75: Almanca C1 / çok iyi Almanca, Ağ üreticisi sertifikası (Cisco/Fortinet/Palo Alto) | T75: 3.5 | U75: 4 | V75: 1 | W75: 3.5 | X75: 5 | Y75: 3.5 | Z75: =ROUND((T75*Özet!$C$14+U75*Özet!$C$15+V75*Özet!$C$16+W75*Özet!$C$17+X75*Özet!$C$18+Y75*Özet!$C$19)/5,4) -> 0.595 | AA75: =RANK(AE75,$AE$5:$AE$126)+COUNTIF($AE$5:AE75,AE75)-1 -> 71 | AB75: =IF(AND(OR(G75="EN",G75="EN (+DE artı)"),Z75>=0.7),"A – Hemen başvur (İngilizce)",IF(Z75>=0.7,"B – Başvur (Almanca gerekli)",IF(AND(OR(G75="EN",G75="EN (+DE artı)"),Z75>=0.6),"B – Başvur (İngilizce)","C – Opsiyonel"))) -> C – Opsiyonel | AC75: Almanca C1 isteniyor – yine de başvurmak istersen Almanca CV + dil planı (kurs/sertifika) belirt | AD75: https://www.karriere.at/f/salzburger-festspielfonds | AE75: =Z75+IF(OR(G75="EN",G75="EN (+DE artı)"),1,0) -> 0.595
A76: 72 | B76: epunkt GmbH | C76: IT System Administrator (w/m/x) | D76: Salzburg | E76: ≤30 dk (Salzburg / yakın çevre) | F76: Sistem / altyapı | G76: DE C1 | H76: gute Deutsch- und gute Englischkenntnisse | I76: — | J76: Uzman (mid-senior) | K76: ~€49k+/yıl (ilan: 3.500 € – 4.200 € monatlich) | L76: 2026-09-27 | M76: karriere.at | N76: https://www.karriere.at/jobs/7785812 | O76: 27.09.2026 14:13 · HTTP 200 · AÇIK | Q76: & Erfahrung zwischen 3.500 EUR und 4.200 EUR brutto / Monat (auf Vollzeitbasis). Brutto Netto Rechner Das Unternehmen Unser Kunde ist die österreichische Einheit eines international tätigen Konzerns und zählt zu den weltweit führenden Anbietern von Lösungen im Pool- und Wellnessbereich. Die österreichische Einheit agiert als spezialisierter Großhändler und Partner für den Fachhandel und bietet ein breites Portfolio a… | R76: Tedarikçi yönetimi, Ekip liderliği, Perakende / çok lokasyon | S76: Almanca C1 / çok iyi Almanca, ANA ŞART: İş uygulaması alanı (CRM/ERP/Legal/ServiceNow…) | T76: 3.5 | U76: 4 | V76: 1 | W76: 3.5 | X76: 5 | Y76: 3.5 | Z76: =ROUND((T76*Özet!$C$14+U76*Özet!$C$15+V76*Özet!$C$16+W76*Özet!$C$17+X76*Özet!$C$18+Y76*Özet!$C$19)/5,4) -> 0.595 | AA76: =RANK(AE76,$AE$5:$AE$126)+COUNTIF($AE$5:AE76,AE76)-1 -> 72 | AB76: =IF(AND(OR(G76="EN",G76="EN (+DE artı)"),Z76>=0.7),"A – Hemen başvur (İngilizce)",IF(Z76>=0.7,"B – Başvur (Almanca gerekli)",IF(AND(OR(G76="EN",G76="EN (+DE artı)"),Z76>=0.6),"B – Başvur (İngilizce)","C – Opsiyonel"))) -> C – Opsiyonel | AC76: Almanca C1 isteniyor – yine de başvurmak istersen Almanca CV + dil planı (kurs/sertifika) belirt · Personel danışmanı ilanı → danışmanı telefon/e-posta ile ara, diğer açık pozisyonlarını da sor | AD76: https://www.karriere.at/f/epunkt-linz | AE76: =Z76+IF(OR(G76="EN",G76="EN (+DE artı)"),1,0) -> 0.595
A77: 73 | B77: x-tention Informationstechnologie GmbH | C77: Senior Cybersecurity Analyst (m/w/d) | D77: Klagenfurt am Wörthersee, Wien, St. Peter in der Au, Graz, Wels, Salzburg (Stadt) | E77: ≤30 dk (Salzburg / yakın çevre) | F77: Cyber Security – teknik | G77: DE+EN | H77: Arbeitsweise sowie ausgeprägte Kommunikationsfähigkeiten in Deutsch und Englisch Deine Benefits | I77: — | J77: Kıdemli / yönetici | K77: ~€56k+/yıl (ilan: 4.000 € – 5.200 € monatlich) | L77: 2026-09-25 | M77: karriere.at | N77: https://www.karriere.at/jobs/10030769 | O77: 27.09.2026 14:13 · HTTP 200 · AÇIK | Q77: sowie mehrjährige Erfahrung im Bereich Security Operations, SOC oder Incident Response Fundierte praktische Erfahrung in der Analyse und Bearbeitung von Security Incidents in einem SOC-Umfeld Sehr gutes Verständnis von Angriffsvektoren, TTPs und gängigen Bedrohungsszenarien sowie Erfahrung mit Frameworks wie MITRE ATT&CK Erfahrung mit SIEM- und Security-Tools (z. B. Elastic Security) sowie sicherer Umgang mit Loganal… | R77: ITIL / ITSM, Windows Server, Backup / DR, Ağ / Firewall / VPN, Ekip liderliği, Perakende / çok lokasyon | S77: ANA ŞART: Scripting / otomasyon (PowerShell vb.), Linux, ANA ŞART: SIEM / SOC / EDR | T77: 2 | U77: 4.5 | V77: 2 | W77: 4 | X77: 5 | Y77: 4 | Z77: =ROUND((T77*Özet!$C$14+U77*Özet!$C$15+V77*Özet!$C$16+W77*Özet!$C$17+X77*Özet!$C$18+Y77*Özet!$C$19)/5,4) -> 0.595 | AA77: =RANK(AE77,$AE$5:$AE$126)+COUNTIF($AE$5:AE77,AE77)-1 -> 73 | AB77: =IF(AND(OR(G77="EN",G77="EN (+DE artı)"),Z77>=0.7),"A – Hemen başvur (İngilizce)",IF(Z77>=0.7,"B – Başvur (Almanca gerekli)",IF(AND(OR(G77="EN",G77="EN (+DE artı)"),Z77>=0.6),"B – Başvur (İngilizce)","C – Opsiyonel"))) -> C – Opsiyonel | AC77: Almanca CV ile başvur; İngilizce yeterliliğini ve Almanca B1/B2'yi açıkça yaz | AD77: https://www.karriere.at/f/x-tention-informationstechnologie | AE77: =Z77+IF(OR(G77="EN",G77="EN (+DE artı)"),1,0) -> 0.595
A78: 74 | B78: ACP Gruppe | C78: Senior Operations Workplace Engineer m, w, d | D78: Salzburg | E78: ≤30 dk (Salzburg / yakın çevre) | F78: Sistem / altyapı | G78: DE C1 | H78: gute Deutsch- und Englischkenntnisse sowie die Fähigkeit, technische Inhalte klar | I78: — | J78: Kıdemli / yönetici | K78: ~€55k+/yıl (ilan: ab 55.000 € jährlich) | L78: 2026-09-22 | M78: karriere.at | N78: https://www.karriere.at/jobs/7839089 | O78: 27.09.2026 14:13 · HTTP 200 · AÇIK | P78: https://bewerbung.acp-gruppe.com/at/rx/1178 | Q78: Mehrjährige Erfahrung in Microsoft Intune, Endpoint Manager und Microsoft 365, inklusive Architektur, Automatisierung und komplexen Konfigurationen. Fundierte Kenntnisse in Windows Deployment, Autopilot, Security Policies sowie PowerShell‑Automatisierung. Umfangreiche Erfahrung in der Verwaltung und Absicherung von iOS- und Android-Geräten über Intune, inklusive App‑Management und Compliance‑Konzepten. Fähigkeit, kom… | R78: Windows Server, Tedarikçi yönetimi, Ekip liderliği, Politika / uyum, Microsoft ortamı | S78: Almanca C1 / çok iyi Almanca, ANA ŞART: Intune / M365 admin, ANA ŞART: Scripting / otomasyon (PowerShell vb.) | T78: 3 | U78: 4.5 | V78: 1 | W78: 4 | X78: 5 | Y78: 4 | Z78: =ROUND((T78*Özet!$C$14+U78*Özet!$C$15+V78*Özet!$C$16+W78*Özet!$C$17+X78*Özet!$C$18+Y78*Özet!$C$19)/5,4) -> 0.595 | AA78: =RANK(AE78,$AE$5:$AE$126)+COUNTIF($AE$5:AE78,AE78)-1 -> 74 | AB78: =IF(AND(OR(G78="EN",G78="EN (+DE artı)"),Z78>=0.7),"A – Hemen başvur (İngilizce)",IF(Z78>=0.7,"B – Başvur (Almanca gerekli)",IF(AND(OR(G78="EN",G78="EN (+DE artı)"),Z78>=0.6),"B – Başvur (İngilizce)","C – Opsiyonel"))) -> C – Opsiyonel | AC78: Almanca C1 isteniyor – yine de başvurmak istersen Almanca CV + dil planı (kurs/sertifika) belirt | AD78: https://www.karriere.at/f/acp-gruppe | AE78: =Z78+IF(OR(G78="EN",G78="EN (+DE artı)"),1,0) -> 0.595
A79: 75 | B79: Otto Austria Group | C79: Release & Change Manager (m/w/x) – Microsoft Dynamics 365 Business Central | D79: Wals-Siezenheim, Salzburg, Austria | E79: ≤30 dk (Salzburg / yakın çevre) | F79: Cyber Security – teknik | G79: DE C1 | H79: Deutschkenntnisse für die Abstimmung mit unseren internen Stakeholdern | I79: — | J79: Kıdemli / yönetici | K79: Sadece KV asgarisi: ~€35k/yıl (ilan metni) – gerçek maaş belirtilmemiş, genelde üstünde | L79: 2026-09-17 | M79: LinkedIn | N79: https://www.linkedin.com/jobs/view/4467166977 | O79: 27.09.2026 14:14 · HTTP 200 · AÇIK | Q79: im Dynamics 365 BC-Umfeld vorzubereiten. Releasemanagement: Du planst, koordinierst und überwachst die Bereitstellung neuer Funktionen und Updates über verschiedene Umgebungen hinweg (DEV, STAGE, Produktion). Testmanagement: Du definierst geeignete Testverfahren, planst und kontrollierst die Testdurchführung und sicherst so die hohe Qualität unserer Softwarefunktionen. Stakeholder-Management: Du bist die zentrale Sch… | R79: ITIL / ITSM, Tedarikçi yönetimi, Ekip liderliği, Microsoft ortamı, Perakende / çok lokasyon | S79: Almanca C1 / çok iyi Almanca, ANA ŞART: İş uygulaması alanı (CRM/ERP/Legal/ServiceNow…) | T79: 3 | U79: 4.5 | V79: 1 | W79: 5 | X79: 5 | Y79: 3.5 | Z79: =ROUND((T79*Özet!$C$14+U79*Özet!$C$15+V79*Özet!$C$16+W79*Özet!$C$17+X79*Özet!$C$18+Y79*Özet!$C$19)/5,4) -> 0.595 | AA79: =RANK(AE79,$AE$5:$AE$126)+COUNTIF($AE$5:AE79,AE79)-1 -> 75 | AB79: =IF(AND(OR(G79="EN",G79="EN (+DE artı)"),Z79>=0.7),"A – Hemen başvur (İngilizce)",IF(Z79>=0.7,"B – Başvur (Almanca gerekli)",IF(AND(OR(G79="EN",G79="EN (+DE artı)"),Z79>=0.6),"B – Başvur (İngilizce)","C – Opsiyonel"))) -> C – Opsiyonel | AC79: Almanca C1 isteniyor – yine de başvurmak istersen Almanca CV + dil planı (kurs/sertifika) belirt | AD79: https://at.linkedin.com/company/ottoaustriagroup | AE79: =Z79+IF(OR(G79="EN",G79="EN (+DE artı)"),1,0) -> 0.595
A80: 76 | B80: BWT Holding GmbH | C80: IT Service Desk Engineer (m/w/d) | D80: Mondsee, Raum Salzburg | E80: ≤30 dk (Salzburg / yakın çevre) | F80: IT destek / service desk | G80: DE C1 | H80: Windows Client Betriebssystem, Azure Cloud von Vorteil) Sehr gute Deutsch- und Englischkenntnisse in Wort und Schrift Kommunikative und selbsts | I80: — | J80: Orta / giriş – aday overqualified | K80: ~€41k+/yıl (ilan: ab 41.300 € jährlich) | L80: 2026-09-23 | M80: karriere.at | N80: https://www.karriere.at/jobs/7864783 | O80: 27.09.2026 14:13 · HTTP 200 · AÇIK | P80: https://www.linkedin.com/jobs/view/4457605563 | Q80: Technische Ausbildung (Lehre, HTL, FH/Uni) mit Schwerpunkt IT oder Quereinsteiger mit mehreren Jahren Berufserfahrung Sorgfältige, strukturierte und selbständige Arbeitsweise Begeisterungsfähigkeit für technische Herausforderungen und hohe Einsatzbereitschaft Gute Kenntnisse im Microsoft-Umfeld (z.B. Windows Server, Active Directory, Windows Client Betriebssystem, Azure Cloud von Vorteil) Sehr gute Deutsch- und Engli… | R80: Active Directory, Windows Server, Microsoft ortamı, Perakende / çok lokasyon | S80: Almanca C1 / çok iyi Almanca, Azure / Entra ID | T80: 4 | U80: 3 | V80: 1 | W80: 4 | X80: 5 | Y80: 3 | Z80: =ROUND((T80*Özet!$C$14+U80*Özet!$C$15+V80*Özet!$C$16+W80*Özet!$C$17+X80*Özet!$C$18+Y80*Özet!$C$19)/5,4) -> 0.59 | AA80: =RANK(AE80,$AE$5:$AE$126)+COUNTIF($AE$5:AE80,AE80)-1 -> 76 | AB80: =IF(AND(OR(G80="EN",G80="EN (+DE artı)"),Z80>=0.7),"A – Hemen başvur (İngilizce)",IF(Z80>=0.7,"B – Başvur (Almanca gerekli)",IF(AND(OR(G80="EN",G80="EN (+DE artı)"),Z80>=0.6),"B – Başvur (İngilizce)","C – Opsiyonel"))) -> C – Opsiyonel | AC80: Almanca C1 isteniyor – yine de başvurmak istersen Almanca CV + dil planı (kurs/sertifika) belirt | AD80: https://www.karriere.at/f/bwt-holding-gmbh | AE80: =Z80+IF(OR(G80="EN",G80="EN (+DE artı)"),1,0) -> 0.59
A81: 77 | B81: Vesterling AG | C81: EntraID - Administrator | Microsoft Exchange, Active Directory, Mittelstand | Inhouse (mwd) | D81: Braunau am Inn, Upper Austria, Austria | E81: 60–90 dk | F81: Cyber Security – teknik | G81: DE+EN | H81: Profil Mehrjährige Berufserfahrung im Umfeld von EntraID Gute Deutsch- und Englischkenntnisse Benefits Die Philosophie unseres Kunden laute | I81: — | J81: Uzman (mid-senior) | K81: İlanda belirtilmemiş | L81: 2026-09-24 | M81: LinkedIn | N81: https://www.linkedin.com/jobs/view/4079343035 | O81: 27.09.2026 14:14 · HTTP 200 · AÇIK | Q81: Mehrjährige Berufserfahrung im Umfeld von EntraID Gute Deutsch- und Englischkenntnisse Benefits Die Philosophie unseres Kunden lautet "erfinden - innovieren - umsetzen". Unzählige Erfindungen und Patente zeugen vom Erfindergeist und der Innovationskraft des Unternehmens. Die Weiterentwicklung der Technologie hat oberste Priorität, um gemeinsam mit den Kunden des Unternehmens auf dem Markt erfolgreich zu sein. Zufried… | R81: Active Directory, Windows Server, Tedarikçi yönetimi, Microsoft ortamı | S81: Azure / Entra ID | T81: 3.5 | U81: 4 | V81: 2 | W81: 4 | X81: 2 | Y81: 3 | Z81: =ROUND((T81*Özet!$C$14+U81*Özet!$C$15+V81*Özet!$C$16+W81*Özet!$C$17+X81*Özet!$C$18+Y81*Özet!$C$19)/5,4) -> 0.59 | AA81: =RANK(AE81,$AE$5:$AE$126)+COUNTIF($AE$5:AE81,AE81)-1 -> 77 | AB81: =IF(AND(OR(G81="EN",G81="EN (+DE artı)"),Z81>=0.7),"A – Hemen başvur (İngilizce)",IF(Z81>=0.7,"B – Başvur (Almanca gerekli)",IF(AND(OR(G81="EN",G81="EN (+DE artı)"),Z81>=0.6),"B – Başvur (İngilizce)","C – Opsiyonel"))) -> C – Opsiyonel | AC81: Almanca CV ile başvur; İngilizce yeterliliğini ve Almanca B1/B2'yi açıkça yaz · Personel danışmanı ilanı → danışmanı telefon/e-posta ile ara, diğer açık pozisyonlarını da sor | AD81: https://de.linkedin.com/company/vesterling | AE81: =Z81+IF(OR(G81="EN",G81="EN (+DE artı)"),1,0) -> 0.59
A82: 78 | B82: SCRI-LIMCR gem. GmbH | C82: IT Systems & Database Administrator (m/w/d) 20 Stunden | D82: Innsbruck, Salzburg (Stadt) | E82: ≤30 dk (Salzburg / yakın çevre) | F82: Sistem / altyapı | G82: DE | H82: İlan Almanca; seviye belirtilmemiş | I82: — | J82: Yarı zamanlı (20 saat) | K82: ~€24k+/yıl (ilan: ab 1.700 € monatlich) | L82: 2026-09-22 | M82: karriere.at | N82: https://www.karriere.at/jobs/10028895 | O82: 27.09.2026 14:13 · HTTP 200 · AÇIK | Q82: Ausbildung: Abgeschlossene technische Ausbildung (HTL, Fachschule oder Lehre mit einschlägiger Berufserfahrung). Erfahrung: Mindestens 2-3 Jahre Praxis in der Systemadministration oder im Datenbankumfeld. Tech-Stack: Sicherer Umgang mit Datenbank-Abfragen (SQL), Backup-Lösungen sowie gängigen Windows- und Office-Umgebungen. Persönlichkeit: Sie bewahren auch bei komplexen Support-Anfragen einen kühlen Kopf und arbeite… | R82: Windows Server, Backup / DR, SQL Server / DB, Politika / uyum, Denetim / audit, Perakende / çok lokasyon | S82: Oracle | T82: 4 | U82: 2.5 | V82: 1.5 | W82: 3.5 | X82: 5 | Y82: 2.5 | Z82: =ROUND((T82*Özet!$C$14+U82*Özet!$C$15+V82*Özet!$C$16+W82*Özet!$C$17+X82*Özet!$C$18+Y82*Özet!$C$19)/5,4) -> 0.59 | AA82: =RANK(AE82,$AE$5:$AE$126)+COUNTIF($AE$5:AE82,AE82)-1 -> 78 | AB82: =IF(AND(OR(G82="EN",G82="EN (+DE artı)"),Z82>=0.7),"A – Hemen başvur (İngilizce)",IF(Z82>=0.7,"B – Başvur (Almanca gerekli)",IF(AND(OR(G82="EN",G82="EN (+DE artı)"),Z82>=0.6),"B – Başvur (İngilizce)","C – Opsiyonel"))) -> C – Opsiyonel | AC82: Almanca CV + Anschreiben ile başvur (Almanca B1/B2 belirt) | AD82: https://www.karriere.at/f/scri-limcr-gem | AE82: =Z82+IF(OR(G82="EN",G82="EN (+DE artı)"),1,0) -> 0.59
A83: 79 | B83: Career Advisor | C83: IT-Systemtechniker / Microsoft-Umgebung (m/w/d) | D83: Salzburg, Austria | E83: ≤30 dk (Salzburg / yakın çevre) | F83: Sistem / altyapı | G83: DE C1 | H83: und Hands-on-Mentalität Freude am Austausch im Team Sehr gute Deutschkenntnisse sowie gutes Englisch Das erwartet dich Moderne Technologien | I83: — | J83: Uzman (mid-senior) | K83: ~€65k+/yıl (ilan metninden) | L83: 2026-09-17 | M83: LinkedIn | N83: https://www.linkedin.com/jobs/view/4467812372 | O83: 27.09.2026 14:14 · HTTP 200 · AÇIK | Q83: Abgeschlossene IT-Ausbildung (Lehre, Fachschule, HTL oder vergleichbar) Mehrjährige Erfahrung im IT-Betrieb, in der Systemadministration oder im Infrastructure Engineering Sehr gutes Know-how in Microsoft-Technologien: Windows Server & Windows Client Active Directory / Azure AD Microsoft 365 Exchange, Teams, SharePoint Installation, Konfiguration & Administration moderner Microsoft-Umgebungen Strukturierte und lösung… | R83: Active Directory, Windows Server, Microsoft ortamı | S83: Almanca C1 / çok iyi Almanca, Azure / Entra ID, ANA ŞART: Intune / M365 admin | T83: 3 | U83: 4 | V83: 1 | W83: 3.5 | X83: 5 | Y83: 4.5 | Z83: =ROUND((T83*Özet!$C$14+U83*Özet!$C$15+V83*Özet!$C$16+W83*Özet!$C$17+X83*Özet!$C$18+Y83*Özet!$C$19)/5,4) -> 0.585 | AA83: =RANK(AE83,$AE$5:$AE$126)+COUNTIF($AE$5:AE83,AE83)-1 -> 79 | AB83: =IF(AND(OR(G83="EN",G83="EN (+DE artı)"),Z83>=0.7),"A – Hemen başvur (İngilizce)",IF(Z83>=0.7,"B – Başvur (Almanca gerekli)",IF(AND(OR(G83="EN",G83="EN (+DE artı)"),Z83>=0.6),"B – Başvur (İngilizce)","C – Opsiyonel"))) -> C – Opsiyonel | AC83: Almanca C1 isteniyor – yine de başvurmak istersen Almanca CV + dil planı (kurs/sertifika) belirt · Personel danışmanı ilanı → danışmanı telefon/e-posta ile ara, diğer açık pozisyonlarını da sor | AD83: https://ro.linkedin.com/company/career-advisor | AE83: =Z83+IF(OR(G83="EN",G83="EN (+DE artı)"),1,0) -> 0.585
A84: 80 | B84: NTS | C84: IT Architect and Consultant (m/w/d) | D84: Dornbirn, Innsbruck, Klagenfurt am Wörthersee, Salzburg, Wien, Graz, Linz | E84: ≤30 dk (Salzburg / yakın çevre) | F84: Uygulama / iş uygulamaları | G84: DE C1 | H84: und Teamfähigkeit Sie verfügen über sehr gute Deutsch- & gute Englischkenntnisse in Wort und Schrift Angebot Die Mitarbeit | I84: — | J84: Kıdemli / yönetici | K84: ~€70k+/yıl (ilan: ab 70.000 € jährlich) | L84: 2026-09-23 | M84: karriere.at | N84: https://www.karriere.at/jobs/7876942 | O84: 27.09.2026 14:13 · HTTP 200 · AÇIK | P84: https://www.linkedin.com/jobs/view/4466532375 | Q84: und Berufserfahrung sind wir zu einer Überzahlung bereit. Jetzt bewerben und Teil unseres Teams werden! Gleich bewerben » Dornbirn, Innsbruck, Klagenfurt am Wörthersee, Salzburg, Wien, Graz, Linz » Vollzeit GROW » Aus- und Weiterbildungsangebote » NTS Campus » Individuelle Karrierepfade » Zertifizierungen SOCIAL » Events » Vergünstigungen & Prämien » Mentor*innenprogramm » Coaching RELAX » Shiatsu » Jobbike » Getränk… | R84: ISO 27001 / ISMS, Ağ / Firewall / VPN, Ekip liderliği, Politika / uyum | S84: Almanca C1 / çok iyi Almanca, NIS-2 / DORA / TISAX, OT / SCADA güvenliği, AI / ML | T84: 2.5 | U84: 4.5 | V84: 1 | W84: 4 | X84: 5 | Y84: 5 | Z84: =ROUND((T84*Özet!$C$14+U84*Özet!$C$15+V84*Özet!$C$16+W84*Özet!$C$17+X84*Özet!$C$18+Y84*Özet!$C$19)/5,4) -> 0.585 | AA84: =RANK(AE84,$AE$5:$AE$126)+COUNTIF($AE$5:AE84,AE84)-1 -> 80 | AB84: =IF(AND(OR(G84="EN",G84="EN (+DE artı)"),Z84>=0.7),"A – Hemen başvur (İngilizce)",IF(Z84>=0.7,"B – Başvur (Almanca gerekli)",IF(AND(OR(G84="EN",G84="EN (+DE artı)"),Z84>=0.6),"B – Başvur (İngilizce)","C – Opsiyonel"))) -> C – Opsiyonel | AC84: Almanca C1 isteniyor – yine de başvurmak istersen Almanca CV + dil planı (kurs/sertifika) belirt | AD84: https://www.karriere.at/f/nts | AE84: =Z84+IF(OR(G84="EN",G84="EN (+DE artı)"),1,0) -> 0.585
A85: 81 | B85: KERN engineering careers GmbH | C85: IT Support Engineer (w/m/d) | D85: Linz-Land, Graz, Salzburg | E85: ≤30 dk (Salzburg / yakın çevre) | F85: IT destek / service desk | G85: DE C1 | H85: strukturiert und lösungsorientiert Du verfügst über sehr gute Deutsch - und Englischkenntnisse in Wort und Schrift Gegenüber den Kund:innen | I85: — | J85: Orta / giriş – aday overqualified | K85: Sadece KV asgarisi: ~€41k/yıl (2.900 € – 3.500 € monatlich) – gerçek maaş belirtilmemiş, genelde üstünde | L85: 2026-09-23 | M85: karriere.at | N85: https://www.karriere.at/jobs/7852112 | O85: 27.09.2026 14:13 · HTTP 200 · AÇIK | P85: https://www.karriere.at/jobs/7877971 | Q85: & Berufserfahrung zwischen EUR 2900 und EUR 3500 brutto / Monat (auf Vollzeitbasis). Klingt interessant? Am besten JETZT BEWERBEN und mehr über diese Position erfahren! Sollte es vorab Fragen geben, freut sich Verena Herrmann v.herrmann@kern-partner.at auf die Kontaktaufnahme. Jetzt Bewerben… | R85: Ağ / Firewall / VPN, Microsoft ortamı, Perakende / çok lokasyon | S85: Almanca C1 / çok iyi Almanca | T85: 4 | U85: 3 | V85: 1 | W85: 3.5 | X85: 5 | Y85: 3 | Z85: =ROUND((T85*Özet!$C$14+U85*Özet!$C$15+V85*Özet!$C$16+W85*Özet!$C$17+X85*Özet!$C$18+Y85*Özet!$C$19)/5,4) -> 0.585 | AA85: =RANK(AE85,$AE$5:$AE$126)+COUNTIF($AE$5:AE85,AE85)-1 -> 81 | AB85: =IF(AND(OR(G85="EN",G85="EN (+DE artı)"),Z85>=0.7),"A – Hemen başvur (İngilizce)",IF(Z85>=0.7,"B – Başvur (Almanca gerekli)",IF(AND(OR(G85="EN",G85="EN (+DE artı)"),Z85>=0.6),"B – Başvur (İngilizce)","C – Opsiyonel"))) -> C – Opsiyonel | AC85: Almanca C1 isteniyor – yine de başvurmak istersen Almanca CV + dil planı (kurs/sertifika) belirt · Personel danışmanı ilanı → danışmanı telefon/e-posta ile ara, diğer açık pozisyonlarını da sor · İletişim: v.herrmann@kern-partner.at | AD85: https://www.karriere.at/f/kern-engineering-careers | AE85: =Z85+IF(OR(G85="EN",G85="EN (+DE artı)"),1,0) -> 0.585
A86: 82 | B86: ip50 Personalberatung (müşteri gizli: ‘Weltmarktführer’, Hallein) | C86: Service Desk Mitarbeiter (w/m/d) | D86: Hallein, Salzburg, Austria | E86: ≤30 dk (Salzburg / yakın çevre) | F86: IT destek / service desk | G86: DE C1 | H86: in Netzwerken, Servern und Betriebssystemen ausgezeichnete Deutsch- und sehr gute Englischkenntnisse Mitarbeit bei diversen IT-Projekten | I86: — | J86: Orta / giriş – aday overqualified | K86: İlanda belirtilmemiş | L86: 2026-09-25 | M86: LinkedIn | N86: https://www.linkedin.com/jobs/view/4471875916 | O86: 27.09.2026 14:14 · HTTP 200 · AÇIK | Q86: Abgeschlossene Ausbildung, Studium oder eine Umschulung im Bereich Informatik Berufserfahrung in diesem Bereich von Vorteil Technisches Verständnis von Hard- und Software Grundkenntnisse in Netzwerken, Servern und Betriebssystemen ausgezeichnete Deutsch- und sehr gute Englischkenntnisse Mitarbeit bei diversen IT-Projekten Benefits Geboten wird eine langfristige Perspektive in einem wirtschaftlich äußerst stabilen Umf… | R86: Ağ / Firewall / VPN, SQL Server / DB | S86: Almanca C1 / çok iyi Almanca | T86: 4 | U86: 3 | V86: 1 | W86: 3.5 | X86: 5 | Y86: 3 | Z86: =ROUND((T86*Özet!$C$14+U86*Özet!$C$15+V86*Özet!$C$16+W86*Özet!$C$17+X86*Özet!$C$18+Y86*Özet!$C$19)/5,4) -> 0.585 | AA86: =RANK(AE86,$AE$5:$AE$126)+COUNTIF($AE$5:AE86,AE86)-1 -> 82 | AB86: =IF(AND(OR(G86="EN",G86="EN (+DE artı)"),Z86>=0.7),"A – Hemen başvur (İngilizce)",IF(Z86>=0.7,"B – Başvur (Almanca gerekli)",IF(AND(OR(G86="EN",G86="EN (+DE artı)"),Z86>=0.6),"B – Başvur (İngilizce)","C – Opsiyonel"))) -> C – Opsiyonel | AC86: Almanca C1 isteniyor – yine de başvurmak istersen Almanca CV + dil planı (kurs/sertifika) belirt · Personel danışmanı ilanı → danışmanı telefon/e-posta ile ara, diğer açık pozisyonlarını da sor | AD86: https://www.linkedin.com/company/ip50 | AE86: =Z86+IF(OR(G86="EN",G86="EN (+DE artı)"),1,0) -> 0.585
A87: 83 | B87: ACP Gruppe | C87: IT Onsite Client Support 1st & 2nd Level | D87: Ranshofen | E87: 60–90 dk | F87: IT destek / service desk | G87: DE+EN | H87: & Englisch Unser Angebot Es erwartet dich eine verantwortungsvolle Tä | I87: — | J87: Orta / giriş – aday overqualified | K87: ~€35k+/yıl (ilan: ab 2.500 € monatlich) | L87: 2026-09-26 | M87: karriere.at | N87: https://www.karriere.at/jobs/7830557 | O87: 27.09.2026 14:14 · HTTP 200 · AÇIK | Q87: Eine abgeschlossene IT-Ausbildung oder entsprechende Berufserfahrung im IT-Support Gute Kenntnisse in den gängigen Betriebssystemen (Windows, iOS, Android) und im Bereich Client-Hardware Eine strukturierte, zuverlässige Arbeitsweise und Freude am direkten Kundenkontakt Präsenz-Mentalität: Du schätzt den direkten Austausch im Team und die Arbeit vor Ort beim Kunden. Führerschein B Sprache: Deutsch & Englisch Unser Ang… | R87: Windows Server, Tedarikçi yönetimi, Perakende / çok lokasyon | S87: Belirgin teknik eksik yok | T87: 4 | U87: 3 | V87: 2 | W87: 4 | X87: 2 | Y87: 2.5 | Z87: =ROUND((T87*Özet!$C$14+U87*Özet!$C$15+V87*Özet!$C$16+W87*Özet!$C$17+X87*Özet!$C$18+Y87*Özet!$C$19)/5,4) -> 0.58 | AA87: =RANK(AE87,$AE$5:$AE$126)+COUNTIF($AE$5:AE87,AE87)-1 -> 83 | AB87: =IF(AND(OR(G87="EN",G87="EN (+DE artı)"),Z87>=0.7),"A – Hemen başvur (İngilizce)",IF(Z87>=0.7,"B – Başvur (Almanca gerekli)",IF(AND(OR(G87="EN",G87="EN (+DE artı)"),Z87>=0.6),"B – Başvur (İngilizce)","C – Opsiyonel"))) -> C – Opsiyonel | AC87: Almanca CV ile başvur; İngilizce yeterliliğini ve Almanca B1/B2'yi açıkça yaz | AD87: https://www.karriere.at/f/acp-gruppe | AE87: =Z87+IF(OR(G87="EN",G87="EN (+DE artı)"),1,0) -> 0.58
A88: 84 | B88: Hemmersbach | C88: Onsite IT-Support 2nd Level (m/w/d) - Eggelsberg | D88: Eggelsberg, Upper Austria, Austria | E88: 45–60 dk | F88: IT destek / service desk | G88: DE+EN | H88: Kommunikationsfähigkeiten in Deutsch und Englisch (mit IT-Schwerpunkt) Führerschein der Klasse B Allrounde | I88: — | J88: Orta / giriş – aday overqualified | K88: Sadece KV asgarisi: ~€36k/yıl (ilan metni) – gerçek maaş belirtilmemiş, genelde üstünde | L88: 2026-09-22 | M88: LinkedIn | N88: https://www.linkedin.com/jobs/view/4443244554 | O88: 27.09.2026 14:14 · HTTP 200 · AÇIK | Q88: gute Kommunikationsfähigkeiten in Deutsch und Englisch (mit IT-Schwerpunkt) Führerschein der Klasse B Allrounder Kenntnisse im Bereich Hardware und Software Quereinsteiger mit 2 bis 4 Jahren Berufserfahrung in der IT oder abgeschlossene IT-spezifische Ausbildung (Lehre, HTL, Studium/Fachhochschule) Erfahrungen mit Snow/ServiceNow sind von Vorteil Freundliches, verständnisvolles und gepflegtes Auftreten Erfahrung mit… | R88: Active Directory, Windows Server, Ağ / Firewall / VPN, Microsoft ortamı | S88: Intune / M365 admin, İş uygulaması alanı (CRM/ERP/Legal/ServiceNow…) | T88: 3.5 | U88: 3 | V88: 2 | W88: 4 | X88: 3 | Y88: 3 | Z88: =ROUND((T88*Özet!$C$14+U88*Özet!$C$15+V88*Özet!$C$16+W88*Özet!$C$17+X88*Özet!$C$18+Y88*Özet!$C$19)/5,4) -> 0.58 | AA88: =RANK(AE88,$AE$5:$AE$126)+COUNTIF($AE$5:AE88,AE88)-1 -> 84 | AB88: =IF(AND(OR(G88="EN",G88="EN (+DE artı)"),Z88>=0.7),"A – Hemen başvur (İngilizce)",IF(Z88>=0.7,"B – Başvur (Almanca gerekli)",IF(AND(OR(G88="EN",G88="EN (+DE artı)"),Z88>=0.6),"B – Başvur (İngilizce)","C – Opsiyonel"))) -> C – Opsiyonel | AC88: Almanca CV ile başvur; İngilizce yeterliliğini ve Almanca B1/B2'yi açıkça yaz | AD88: https://de.linkedin.com/company/hemmersbach | AE88: =Z88+IF(OR(G88="EN",G88="EN (+DE artı)"),1,0) -> 0.58
A89: 85 | B89: Standout GmbH | C89: ERP Application Manager (m/w/d) | D89: Salzburg (Stadt) | E89: ≤30 dk (Salzburg / yakın çevre) | F89: Uygulama / iş uygulamaları | G89: DE C1 | H89: CAD - Anwendungskenntnisse wünschenswert Sehr gute Deutschkenntnisse und gute Englischkenntnisse Kommunikative und proaktive Per | I89: — | J89: Kıdemli / yönetici | K89: Sadece KV asgarisi: ~€35k/yıl (ilan metni) – gerçek maaş belirtilmemiş, genelde üstünde | L89: 2026-09-25 | M89: karriere.at | N89: https://www.karriere.at/jobs/10031586 | O89: 27.09.2026 14:14 · HTTP 200 · AÇIK | Q89: , einschlägiger Berufserfahrung und anrechenbaren Vordienstzeiten besteht eine deutliche Bereitschaft zur Überzahlung. KV Mindestgehalt 2.528,04 EUR Benefits Aus- und Weiterbildung Home Office Gute Anbindung Parkplatz Kantine Essenszulage Alle Benefits anzeigen Weniger Benefits anzeigen Aus- und Weiterbildung Home Office Gute Anbindung Parkplatz Kantine Essenszulage Alle Benefits anzeigen Weniger Benefits anzeigen We… | R89: SQL Server / DB, Proje yönetimi, Tedarikçi yönetimi, Ekip liderliği, Perakende / çok lokasyon | S89: Almanca C1 / çok iyi Almanca, ANA ŞART: İş uygulaması alanı (CRM/ERP/Legal/ServiceNow…) | T89: 3 | U89: 4.5 | V89: 1 | W89: 3.5 | X89: 5 | Y89: 3.5 | Z89: =ROUND((T89*Özet!$C$14+U89*Özet!$C$15+V89*Özet!$C$16+W89*Özet!$C$17+X89*Özet!$C$18+Y89*Özet!$C$19)/5,4) -> 0.58 | AA89: =RANK(AE89,$AE$5:$AE$126)+COUNTIF($AE$5:AE89,AE89)-1 -> 85 | AB89: =IF(AND(OR(G89="EN",G89="EN (+DE artı)"),Z89>=0.7),"A – Hemen başvur (İngilizce)",IF(Z89>=0.7,"B – Başvur (Almanca gerekli)",IF(AND(OR(G89="EN",G89="EN (+DE artı)"),Z89>=0.6),"B – Başvur (İngilizce)","C – Opsiyonel"))) -> C – Opsiyonel | AC89: Almanca C1 isteniyor – yine de başvurmak istersen Almanca CV + dil planı (kurs/sertifika) belirt | AD89: https://www.karriere.at/f/standout-gmbh | AE89: =Z89+IF(OR(G89="EN",G89="EN (+DE artı)"),1,0) -> 0.58
A90: 86 | B90: KPMG Österreich | C90: Senior Spezialist:in Cybersecurity Beratung | D90: Wien, Graz, Innsbruck, Klagenfurt, Linz, Salzburg | E90: ≤30 dk (Salzburg / yakın çevre) | F90: Cyber Security – yönetişim / ISMS | G90: DE C1 | H90: Sehr gute Deutsch- und Englischkenntnisse in Wort und Schrift Reisebereitschaft (primär | I90: — | J90: Kıdemli / yönetici | K90: ~€58k+/yıl (ilan: ab 58.000 € jährlich) | L90: 2026-09-21 | M90: karriere.at | N90: https://www.karriere.at/jobs/7879333 | O90: 27.09.2026 14:14 · HTTP 200 · AÇIK | Q90: und Berufserfahrung besteht die Bereitschaft zur Überzahlung. Weiters kannst du mit einer leistungsabhängigen, individuellen Prämie rechnen. Kontakt Kontaktdaten Recruiter:innen: Schäfler Jasmin:+43 (664) 2101840 Unsere Benefits Afterwork & Firmenfeiern Ausbildung Betriebsrestaurant Diversity Ermäßigungen Fitnesscenterzuschuss Flexible Arbeitszeiten Freizeitclubs Gesundheit & Wohlbefinden Homeoffice Leasing-Fahrrad Ö… | R90: ISO 27001 / ISMS, ITIL / ITSM, Proje yönetimi, Ekip liderliği, Denetim / audit, Perakende / çok lokasyon | S90: Almanca C1 / çok iyi Almanca, Scripting / otomasyon (PowerShell vb.), Linux, Container / IaC / DevOps, Programlama, CISSP / CISM / CISA, OT / SCADA güvenliği, Pentest, ANA ŞART: AI / ML | T90: 2.5 | U90: 5 | V90: 1 | W90: 4 | X90: 5 | Y90: 4 | Z90: =ROUND((T90*Özet!$C$14+U90*Özet!$C$15+V90*Özet!$C$16+W90*Özet!$C$17+X90*Özet!$C$18+Y90*Özet!$C$19)/5,4) -> 0.58 | AA90: =RANK(AE90,$AE$5:$AE$126)+COUNTIF($AE$5:AE90,AE90)-1 -> 86 | AB90: =IF(AND(OR(G90="EN",G90="EN (+DE artı)"),Z90>=0.7),"A – Hemen başvur (İngilizce)",IF(Z90>=0.7,"B – Başvur (Almanca gerekli)",IF(AND(OR(G90="EN",G90="EN (+DE artı)"),Z90>=0.6),"B – Başvur (İngilizce)","C – Opsiyonel"))) -> C – Opsiyonel | AC90: Almanca C1 isteniyor – yine de başvurmak istersen Almanca CV + dil planı (kurs/sertifika) belirt | AD90: https://www.karriere.at/f/kpmg-%C3%B6sterreich | AE90: =Z90+IF(OR(G90="EN",G90="EN (+DE artı)"),1,0) -> 0.58
A91: 87 | B91: Peneder Unternehmensgruppe | C91: IT-Infrastruktur Engineer / System Engineer 3rd Level | D91: Atzbach | E91: 60–90 dk | F91: Sistem / altyapı | G91: DE C1 | H91: voranzutreiben und nachhaltige Lösungen zu entwickeln Sehr gute Deutschkenntnisse in Wort und Schrift, gute Englischkenntnisse Führerschein B | I91: — | J91: Uzman (mid-senior) | K91: ~€56k+/yıl (ilan: ab 4.000 € monatlich) | L91: 2026-09-22 | M91: karriere.at | N91: https://www.karriere.at/jobs/7875835 | O91: 27.09.2026 14:14 · HTTP 200 · AÇIK | P91: https://www.linkedin.com/jobs/view/4466158169 | Q91: Mehrjährige Berufserfahrung in der Administration und Betreuung von IT-Infrastrukturen Sehr gute Kenntnisse in Windows Server, Active Directory, Microsoft 365 und PowerShell Fundierte Kenntnisse in Netzwerkadministration, TCP/IP, VLAN, Routing, Firewalls, VPN und WLAN Gute Kenntnisse in Virtualisierung, Storage-, Backup- und Recovery-Lösungen Know-how in IT-Sicherheit, Monitoring, Patchmanagement und Hochverfügbarkei… | R91: Active Directory, Windows Server, Sanallaştırma (Hyper-V/Proxmox), Backup / DR, Ağ / Firewall / VPN, Microsoft ortamı, Perakende / çok lokasyon | S91: Almanca C1 / çok iyi Almanca, Intune / M365 admin, Scripting / otomasyon (PowerShell vb.) | T91: 4 | U91: 4 | V91: 1 | W91: 4 | X91: 2 | Y91: 4 | Z91: =ROUND((T91*Özet!$C$14+U91*Özet!$C$15+V91*Özet!$C$16+W91*Özet!$C$17+X91*Özet!$C$18+Y91*Özet!$C$19)/5,4) -> 0.58 | AA91: =RANK(AE91,$AE$5:$AE$126)+COUNTIF($AE$5:AE91,AE91)-1 -> 87 | AB91: =IF(AND(OR(G91="EN",G91="EN (+DE artı)"),Z91>=0.7),"A – Hemen başvur (İngilizce)",IF(Z91>=0.7,"B – Başvur (Almanca gerekli)",IF(AND(OR(G91="EN",G91="EN (+DE artı)"),Z91>=0.6),"B – Başvur (İngilizce)","C – Opsiyonel"))) -> C – Opsiyonel | AC91: Almanca C1 isteniyor – yine de başvurmak istersen Almanca CV + dil planı (kurs/sertifika) belirt | AD91: https://www.karriere.at/f/peneder-unternehmensgruppe | AE91: =Z91+IF(OR(G91="EN",G91="EN (+DE artı)"),1,0) -> 0.58
A92: 88 | B92: ÖWD Security & Services | C92: IT-Administrator & Systembetreuer (m/w/d) | D92: Salzburg | E92: ≤30 dk (Salzburg / yakın çevre) | F92: Sistem / altyapı | G92: DE C1 | H92: Arbeitsweise mit analytischen Fähigkeiten Sehr gute Deutsch- und Englischkenntnisse Jetzt bewerben | I92: — | J92: Uzman (mid-senior) | K92: ~€55k+/yıl (ilan: ab 55.000 € jährlich) | L92: 2026-09-27 | M92: karriere.at | N92: https://www.karriere.at/jobs/7831022 | O92: 27.09.2026 14:13 · HTTP 200 · AÇIK | Q92: vorgesehen. Das bringe ich mit: Abgeschlossene technische Ausbildung mit Schwerpunkt IT (Lehre, HTL, FH) Berufserfahrung in der System- und ggf. Applikationsbetreuung mit breitgefächertem Wissen zu Betriebssystemen am Backend und Frontend Interesse an Geschäftsprozessen und deren Abbildung in IT-Systemen Teamplayer, Leidenschaft für IT-Projekte und eigenverantwortlicher Arbeitsstil Service- und kundenorientierte Arbe… | R92: Sanallaştırma (Hyper-V/Proxmox), Ağ / Firewall / VPN, Ekip liderliği | S92: Almanca C1 / çok iyi Almanca, Azure / Entra ID, Intune / M365 admin, Scripting / otomasyon (PowerShell vb.), İş uygulaması alanı (CRM/ERP/Legal/ServiceNow…), AI / ML | T92: 3 | U92: 4 | V92: 1 | W92: 3.5 | X92: 5 | Y92: 4 | Z92: =ROUND((T92*Özet!$C$14+U92*Özet!$C$15+V92*Özet!$C$16+W92*Özet!$C$17+X92*Özet!$C$18+Y92*Özet!$C$19)/5,4) -> 0.575 | AA92: =RANK(AE92,$AE$5:$AE$126)+COUNTIF($AE$5:AE92,AE92)-1 -> 88 | AB92: =IF(AND(OR(G92="EN",G92="EN (+DE artı)"),Z92>=0.7),"A – Hemen başvur (İngilizce)",IF(Z92>=0.7,"B – Başvur (Almanca gerekli)",IF(AND(OR(G92="EN",G92="EN (+DE artı)"),Z92>=0.6),"B – Başvur (İngilizce)","C – Opsiyonel"))) -> C – Opsiyonel | AC92: Almanca C1 isteniyor – yine de başvurmak istersen Almanca CV + dil planı (kurs/sertifika) belirt | AD92: https://www.karriere.at/f/%C3%B6wd-security-services | AE92: =Z92+IF(OR(G92="EN",G92="EN (+DE artı)"),1,0) -> 0.575
A93: 89 | B93: Salzburg AG für Energie, Verkehr und Telekommunikation | C93: Firewall & Network Security Engineer (all genders) | D93: Salzburg | E93: ≤30 dk (Salzburg / yakın çevre) | F93: Cyber Security – teknik | G93: DE | H93: İlan Almanca; seviye belirtilmemiş | I93: — | J93: Uzman (mid-senior) | K93: ~€55k+/yıl (ilan: ab 3.927,14 € monatlich) | L93: 2026-09-22 | M93: karriere.at | N93: https://www.karriere.at/jobs/7839275 | O93: 27.09.2026 14:14 · HTTP 200 · AÇIK | Q93: von heute und morgen. Aufgabenbereich Umsetzung, Qualitätssicherung und Dokumentation von Changes an Firewall‑Systemen (Policy‑Anpassungen, NAT, VPN, Zonen-/Segmentierung) entsprechend der Security‑ und Compliance‑Vorgaben (Audit‑Readiness) Analyse und Behebung von Incidents und Problems inkl. Root‑Cause‑Analysen, Eskalationsmanagement und Lessons Learned Technisches Kapazitäts‑, Lifecycle‑ und Patch‑Management (Imag… | R93: ISO 27001 / ISMS, ITIL / ITSM, Ağ / Firewall / VPN, Ekip liderliği, Politika / uyum, Denetim / audit | S93: ANA ŞART: Scripting / otomasyon (PowerShell vb.), Container / IaC / DevOps, NIS-2 / DORA / TISAX | T93: 2.5 | U93: 4 | V93: 1.5 | W93: 3.5 | X93: 5 | Y93: 4 | Z93: =ROUND((T93*Özet!$C$14+U93*Özet!$C$15+V93*Özet!$C$16+W93*Özet!$C$17+X93*Özet!$C$18+Y93*Özet!$C$19)/5,4) -> 0.575 | AA93: =RANK(AE93,$AE$5:$AE$126)+COUNTIF($AE$5:AE93,AE93)-1 -> 89 | AB93: =IF(AND(OR(G93="EN",G93="EN (+DE artı)"),Z93>=0.7),"A – Hemen başvur (İngilizce)",IF(Z93>=0.7,"B – Başvur (Almanca gerekli)",IF(AND(OR(G93="EN",G93="EN (+DE artı)"),Z93>=0.6),"B – Başvur (İngilizce)","C – Opsiyonel"))) -> C – Opsiyonel | AC93: Almanca CV + Anschreiben ile başvur (Almanca B1/B2 belirt) | AD93: https://www.karriere.at/f/salzburg-f%C3%BCr-energie-verkehr-und-telekommunikation | AE93: =Z93+IF(OR(G93="EN",G93="EN (+DE artı)"),1,0) -> 0.575
A94: 90 | B94: eworx Network & Internet GmbH | C94: Microsoft 365 & Azure Consultant (m/w/d) | D94: Salzburg, Austria | E94: ≤30 dk (Salzburg / yakın çevre) | F94: Uygulama / iş uygulamaları | G94: DE | H94: İlan Almanca; seviye belirtilmemiş | I94: — | J94: Kıdemli / yönetici | K94: ~€65k+/yıl (ilan metninden) | L94: 2026-09-21 | M94: LinkedIn | N94: https://www.linkedin.com/jobs/view/4468177192 | O94: 27.09.2026 14:14 · HTTP 200 · AÇIK | Q94: zu analysieren und daraus gute Lösungen für Kund:innen zu entwickeln Selbstständige und strukturierte Arbeitsweise Kommunikationsstärke und Freude am direkten Kundenkontakt Interesse daran, neue Microsoft-Technologien kennenzulernen und praktisch einzusetzen Eine klassische IT-Ausbildung oder ein Studium ist für uns weniger entscheidend als deine praktische Erfahrung, dein technisches Verständnis und deine Begeisteru… | R94: Backup / DR, Ağ / Firewall / VPN, Tedarikçi yönetimi, Ekip liderliği, Microsoft ortamı | S94: ANA ŞART: Azure / Entra ID, ANA ŞART: Intune / M365 admin, SIEM / SOC / EDR | T94: 2 | U94: 4.5 | V94: 1.5 | W94: 4 | X94: 5 | Y94: 4.5 | Z94: =ROUND((T94*Özet!$C$14+U94*Özet!$C$15+V94*Özet!$C$16+W94*Özet!$C$17+X94*Özet!$C$18+Y94*Özet!$C$19)/5,4) -> 0.575 | AA94: =RANK(AE94,$AE$5:$AE$126)+COUNTIF($AE$5:AE94,AE94)-1 -> 90 | AB94: =IF(AND(OR(G94="EN",G94="EN (+DE artı)"),Z94>=0.7),"A – Hemen başvur (İngilizce)",IF(Z94>=0.7,"B – Başvur (Almanca gerekli)",IF(AND(OR(G94="EN",G94="EN (+DE artı)"),Z94>=0.6),"B – Başvur (İngilizce)","C – Opsiyonel"))) -> C – Opsiyonel | AC94: Almanca CV + Anschreiben ile başvur (Almanca B1/B2 belirt) · İletişim: me@eworx.at | AD94: https://at.linkedin.com/company/eworx-at | AE94: =Z94+IF(OR(G94="EN",G94="EN (+DE artı)"),1,0) -> 0.575
A95: 91 | B95: x-tention Informationstechnologie GmbH | C95: Security Systems Engineer (m/w/d) | D95: Klagenfurt am Wörthersee, Wien, St. Peter in der Au, Graz, Wels, Salzburg (Stadt) | E95: ≤30 dk (Salzburg / yakın çevre) | F95: Cyber Security – teknik | G95: DE | H95: İlan Almanca; seviye belirtilmemiş | I95: — | J95: Uzman (mid-senior) | K95: ~€50k+/yıl (ilan: 3.600 € – 5.000 € monatlich) | L95: 2026-09-26 | M95: karriere.at | N95: https://www.karriere.at/jobs/10030035 | O95: 27.09.2026 14:13 · HTTP 200 · AÇIK | Q95: Berufserfahrung im Bereich IT-Security, Netzwerk- oder Systemadministration Fundierte Kenntnisse in den Bereichen Netzwerksicherheit, Firewalls, VPN, Reverse Proxy und Load Balancing Idealerweise Erfahrung im Gesundheitswesen oder in einem anderen regulierten Umfeld Selbstständige, strukturierte und lösungsorientierte Arbeitsweise sowie Freude an der Zusammenarbeit im Team Interesse daran, Verantwortung für sichere u… | R95: Ağ / Firewall / VPN, Perakende / çok lokasyon | S95: ANA ŞART: Ağ üreticisi sertifikası (Cisco/Fortinet/Palo Alto), Citrix | T95: 2.5 | U95: 4 | V95: 1.5 | W95: 4 | X95: 5 | Y95: 3.5 | Z95: =ROUND((T95*Özet!$C$14+U95*Özet!$C$15+V95*Özet!$C$16+W95*Özet!$C$17+X95*Özet!$C$18+Y95*Özet!$C$19)/5,4) -> 0.57 | AA95: =RANK(AE95,$AE$5:$AE$126)+COUNTIF($AE$5:AE95,AE95)-1 -> 91 | AB95: =IF(AND(OR(G95="EN",G95="EN (+DE artı)"),Z95>=0.7),"A – Hemen başvur (İngilizce)",IF(Z95>=0.7,"B – Başvur (Almanca gerekli)",IF(AND(OR(G95="EN",G95="EN (+DE artı)"),Z95>=0.6),"B – Başvur (İngilizce)","C – Opsiyonel"))) -> C – Opsiyonel | AC95: Almanca CV + Anschreiben ile başvur (Almanca B1/B2 belirt) | AD95: https://www.karriere.at/f/x-tention-informationstechnologie | AE95: =Z95+IF(OR(G95="EN",G95="EN (+DE artı)"),1,0) -> 0.57
A96: 92 | B96: BEKO Solutions GmbH | C96: IT Administrator (w/m/x) | D96: Vöcklabruck | E96: 60–90 dk | F96: Sistem / altyapı | G96: DE+EN | H96: und der kontinuierlichen fachlichen Weiterentwicklung Gute Deutsch- und Englischkenntnisse Das ist von Vorteil Erfahrung mit ERP-Systeme | I96: — | J96: Uzman (mid-senior) | K96: ~€46k+/yıl (ilan: ab 3.300 € monatlich) | L96: 2026-09-26 | M96: karriere.at | N96: https://www.karriere.at/jobs/7861873 | O96: 27.09.2026 14:14 · HTTP 200 · AÇIK | Q96: Abgeschlossene Ausbildung im IT-Bereich (Lehre, HTL, FH oder vergleichbare Qualifikation) Mehrjährige Erfahrung in der Systemadministration bzw. IT-Infrastruktur Fundierte Kenntnisse in Microsoft-Server-Umgebungen und Linux-Systemen Praxis im Umgang mit Virtualisierungslösungen wie VMware ESX oder Hyper-V Gute Kenntnisse in Active Directory, Netzwerktechnik, IT-Security und Datenbanken Strukturierte und eigenverantwo… | R96: Active Directory, Sanallaştırma (Hyper-V/Proxmox), Ağ / Firewall / VPN, SQL Server / DB, Tedarikçi yönetimi, Microsoft ortamı, Perakende / çok lokasyon | S96: Linux, VMware, ANA ŞART: İş uygulaması alanı (CRM/ERP/Legal/ServiceNow…) | T96: 3 | U96: 4 | V96: 2 | W96: 4 | X96: 2 | Y96: 3.5 | Z96: =ROUND((T96*Özet!$C$14+U96*Özet!$C$15+V96*Özet!$C$16+W96*Özet!$C$17+X96*Özet!$C$18+Y96*Özet!$C$19)/5,4) -> 0.57 | AA96: =RANK(AE96,$AE$5:$AE$126)+COUNTIF($AE$5:AE96,AE96)-1 -> 92 | AB96: =IF(AND(OR(G96="EN",G96="EN (+DE artı)"),Z96>=0.7),"A – Hemen başvur (İngilizce)",IF(Z96>=0.7,"B – Başvur (Almanca gerekli)",IF(AND(OR(G96="EN",G96="EN (+DE artı)"),Z96>=0.6),"B – Başvur (İngilizce)","C – Opsiyonel"))) -> C – Opsiyonel | AC96: Almanca CV ile başvur; İngilizce yeterliliğini ve Almanca B1/B2'yi açıkça yaz | AD96: https://www.karriere.at/f/beko-engineering-informatik-wien | AE96: =Z96+IF(OR(G96="EN",G96="EN (+DE artı)"),1,0) -> 0.57
A97: 93 | B97: Raiffeisen Oberösterreich | C97: Application Workload Manager:in – Data Warehouse | D97: Linz, Graz, Salzburg | E97: ≤30 dk (Salzburg / yakın çevre) | F97: Uygulama / iş uygulamaları | G97: DE C1 | H97: offen und adressatengerecht und bringst dafür sehr gute Deutschkenntnisse mit | I97: — | J97: Kıdemli / yönetici | K97: ~€46k+/yıl (ilan: ab 45.800 € jährlich) | L97: 2026-09-23 | M97: karriere.at | N97: https://www.karriere.at/jobs/7833350 | O97: 27.09.2026 14:14 · HTTP 200 · AÇIK | Q97: technisches Verständnis, Lernbereitschaft und klare Kommunikation. Du hast bereits mit Datenbanken (z. B. Microsoft SQL Server) gearbeitet und bringst idealerweise erste Erfahrung mit PowerShell oder einer vergleichbaren Skriptsprache mit. Du interessierst dich für Tools wie Connect:Direct oder BMC Control-M (Managed File Transfer) und konntest bereits praktische Erfahrungen damit sammeln. Du arbeitest strukturiert,… | R97: Ağ / Firewall / VPN, SQL Server / DB, Microsoft ortamı, Perakende / çok lokasyon | S97: Almanca C1 / çok iyi Almanca, Scripting / otomasyon (PowerShell vb.), İş uygulaması alanı (CRM/ERP/Legal/ServiceNow…) | T97: 3 | U97: 4.5 | V97: 1 | W97: 3.5 | X97: 5 | Y97: 3 | Z97: =ROUND((T97*Özet!$C$14+U97*Özet!$C$15+V97*Özet!$C$16+W97*Özet!$C$17+X97*Özet!$C$18+Y97*Özet!$C$19)/5,4) -> 0.57 | AA97: =RANK(AE97,$AE$5:$AE$126)+COUNTIF($AE$5:AE97,AE97)-1 -> 93 | AB97: =IF(AND(OR(G97="EN",G97="EN (+DE artı)"),Z97>=0.7),"A – Hemen başvur (İngilizce)",IF(Z97>=0.7,"B – Başvur (Almanca gerekli)",IF(AND(OR(G97="EN",G97="EN (+DE artı)"),Z97>=0.6),"B – Başvur (İngilizce)","C – Opsiyonel"))) -> C – Opsiyonel | AC97: Almanca C1 isteniyor – yine de başvurmak istersen Almanca CV + dil planı (kurs/sertifika) belirt | AD97: https://www.karriere.at/f/raiffeisen-ober%C3%B6sterreich | AE97: =Z97+IF(OR(G97="EN",G97="EN (+DE artı)"),1,0) -> 0.57
A98: 94 | B98: Windhager Home & Garden | C98: Business Application Manager (m/w/d) | D98: Thalgau | E98: 30–45 dk | F98: Uygulama / iş uygulamaları | G98: DE | H98: İlan Almanca; seviye belirtilmemiş | I98: — | J98: Kıdemli / yönetici | K98: ~€42k+/yıl (ilan: ab 42.000 € jährlich) | L98: 2026-09-26 | M98: karriere.at | N98: https://www.karriere.at/jobs/7857257 | O98: 27.09.2026 14:13 · HTTP 200 · AÇIK | Q98: inkl. Spezifikation, Abstimmung mit Partnern sowie Testkoordination und Go-Live-Begleitung. Schnittstellen & Datenintegration Betreuung und Optimierung von EDI-, API- und Datenbank-Schnittstellen sowie Analyse und Behebung von Fehlern in Datenflüssen und Integrationsprozessen. Prozessoptimierung & Automatisierung Analyse operativer Geschäftsprozesse, Umsetzung technischer Optimierungen (z. B. SQL, Workflows, Automati… | R98: SQL Server / DB, Perakende / çok lokasyon | S98: Scripting / otomasyon (PowerShell vb.), İş uygulaması alanı (CRM/ERP/Legal/ServiceNow…) | T98: 2.5 | U98: 4.5 | V98: 1.5 | W98: 5 | X98: 4 | Y98: 3 | Z98: =ROUND((T98*Özet!$C$14+U98*Özet!$C$15+V98*Özet!$C$16+W98*Özet!$C$17+X98*Özet!$C$18+Y98*Özet!$C$19)/5,4) -> 0.565 | AA98: =RANK(AE98,$AE$5:$AE$126)+COUNTIF($AE$5:AE98,AE98)-1 -> 94 | AB98: =IF(AND(OR(G98="EN",G98="EN (+DE artı)"),Z98>=0.7),"A – Hemen başvur (İngilizce)",IF(Z98>=0.7,"B – Başvur (Almanca gerekli)",IF(AND(OR(G98="EN",G98="EN (+DE artı)"),Z98>=0.6),"B – Başvur (İngilizce)","C – Opsiyonel"))) -> C – Opsiyonel | AC98: Almanca CV + Anschreiben ile başvur (Almanca B1/B2 belirt) | AD98: https://www.karriere.at/f/windhager-handelsgesmbh | AE98: =Z98+IF(OR(G98="EN",G98="EN (+DE artı)"),1,0) -> 0.565
A99: 95 | B99: SPAR ICS – Information & Communication Services | C99: Senior Linux Expert POS-Systems (m/w/d) | D99: Salzburg (Stadt), Wien, Wernberg | E99: ≤30 dk (Salzburg / yakın çevre) | F99: Sistem / altyapı | G99: DE C1 | H99: Kommunikation auch in kritischen Störungssituationen Fließenden Deutsch- und guten Englischkenntnissen sowie österreichweiter Reisebereitscha | I99: — | J99: Kıdemli / yönetici | K99: ~€50k+/yıl (ilan: ab 50.000 € jährlich) | L99: 2026-09-27 | M99: karriere.at | N99: https://www.karriere.at/jobs/7875151 | O99: 27.09.2026 14:13 · HTTP 200 · AÇIK | P99: https://www.linkedin.com/jobs/view/4466047572 | Q99: sowie mehrjähriger einschlägiger Berufserfahrung Sehr guten Linux-Kenntnissen in Administration, Betrieb und Troubleshooting, idealerweise in den Bereichen Prozesse, Dienste, Dateisysteme, Benutzer- und Berechtigungsverwaltung sowie Paketmanagement Grundkenntnissen in der Netzwerktechnik; Verständnis von TCP/IP, DNS, Routing, Firewalls und der Analyse verteilter Systemlandschaften von Vorteil Idealerweise Erfahrung m… | R99: Ağ / Firewall / VPN, Tedarikçi yönetimi, Perakende / çok lokasyon | S99: Almanca C1 / çok iyi Almanca, ANA ŞART: Scripting / otomasyon (PowerShell vb.), ANA ŞART: Linux | T99: 2.5 | U99: 4.5 | V99: 1 | W99: 5 | X99: 5 | Y99: 3.5 | Z99: =ROUND((T99*Özet!$C$14+U99*Özet!$C$15+V99*Özet!$C$16+W99*Özet!$C$17+X99*Özet!$C$18+Y99*Özet!$C$19)/5,4) -> 0.565 | AA99: =RANK(AE99,$AE$5:$AE$126)+COUNTIF($AE$5:AE99,AE99)-1 -> 95 | AB99: =IF(AND(OR(G99="EN",G99="EN (+DE artı)"),Z99>=0.7),"A – Hemen başvur (İngilizce)",IF(Z99>=0.7,"B – Başvur (Almanca gerekli)",IF(AND(OR(G99="EN",G99="EN (+DE artı)"),Z99>=0.6),"B – Başvur (İngilizce)","C – Opsiyonel"))) -> C – Opsiyonel | AC99: Almanca C1 isteniyor – yine de başvurmak istersen Almanca CV + dil planı (kurs/sertifika) belirt | AD99: https://www.karriere.at/f/spar-ics-information-communication-services | AE99: =Z99+IF(OR(G99="EN",G99="EN (+DE artı)"),1,0) -> 0.565
A100: 96 | B100: KERN engineering careers GmbH | C100: IT Systemadministrator (w/m/d) | D100: Vöcklabruck | E100: 60–90 dk | F100: Sistem / altyapı | G100: DE C1 | H100: Eigenständigkeit, sehr gute Deutschkenntnisse und Führerschein Klasse B Worauf man sich freuen kann Dein | I100: — | J100: Uzman (mid-senior) | K100: ~€49k+/yıl (ilan: 3.500 € – 5.000 € monatlich) | L100: 2026-09-26 | M100: karriere.at | N100: https://www.karriere.at/jobs/7877968 | O100: 27.09.2026 14:14 · HTTP 200 · AÇIK | Q100: & Berufserfahrung zwischen EUR 3500 und EUR 5000 brutto / Monat (auf Vollzeitbasis). Klingt interessant? Am besten JETZT BEWERBEN und mehr über diese Position erfahren! Sollte es vorab Fragen geben, freut sich Jennifer Stillfried j.stillfried@kern-partner.at auf die Kontaktaufnahme. Jetzt Bewerben… | R100: Active Directory, Windows Server, Ağ / Firewall / VPN, Tedarikçi yönetimi, Microsoft ortamı | S100: Almanca C1 / çok iyi Almanca, VMware, Ağ üreticisi sertifikası (Cisco/Fortinet/Palo Alto) | T100: 4 | U100: 4 | V100: 1 | W100: 3.5 | X100: 2 | Y100: 3.5 | Z100: =ROUND((T100*Özet!$C$14+U100*Özet!$C$15+V100*Özet!$C$16+W100*Özet!$C$17+X100*Özet!$C$18+Y100*Özet!$C$19)/5,4) -> 0.565 | AA100: =RANK(AE100,$AE$5:$AE$126)+COUNTIF($AE$5:AE100,AE100)-1 -> 96 | AB100: =IF(AND(OR(G100="EN",G100="EN (+DE artı)"),Z100>=0.7),"A – Hemen başvur (İngilizce)",IF(Z100>=0.7,"B – Başvur (Almanca gerekli)",IF(AND(OR(G100="EN",G100="EN (+DE artı)"),Z100>=0.6),"B – Başvur (İngilizce)","C – Opsiyonel"))) -> C – Opsiyonel | AC100: Almanca C1 isteniyor – yine de başvurmak istersen Almanca CV + dil planı (kurs/sertifika) belirt · Personel danışmanı ilanı → danışmanı telefon/e-posta ile ara, diğer açık pozisyonlarını da sor · İletişim: j.stillfried@kern-partner.at | AD100: https://www.karriere.at/f/kern-engineering-careers | AE100: =Z100+IF(OR(G100="EN",G100="EN (+DE artı)"),1,0) -> 0.565
...

Sheet Firmalar
A1: Firmalar – bu taramada aktif ilanı olan işverenler ve personel danışmanları
A2: İlan sayısı ve en yüksek uyum İlanlar sayfasından formülle hesaplanır · 'Tüm açık ilanları' = karriere.at firma sayfası veya LinkedIn şirket sayfası (test edildi)
A4: Firma (ilandaki adıyla) | B4: Sektör / tür | C4: Lokasyon(lar) | D4: Bu listedeki ilan sayısı | E4: En yüksek uyum | F4: Pozisyonlar | G4: Firmanın tüm açık ilanları | H4: Kariyer portalı (test edildi)
A5: Red Bull | B5: Perakende / FMCG / tüketici | C5: Elsbethen; Thalgau | D5: =COUNTIF(İlanlar!$B$5:$B$126,A5) -> 9 | E5: =_xlfn.MAXIFS(İlanlar!$Z$5:$Z$126,İlanlar!$B$5:$B$126,A5) -> 0.91 | F5: IT Sales Applications Project Manager · IT Project Manager - Legal Solutions · Project Manager (Portfolio Management) · Application Security Service Manager · IT Team Manager - Global Field Sales Applications · IT Project / Application Manager - Production Application · IT Infrastructure Engineer · IT Project Manager - Sales Applications · IT Project Manager – Finance Applications | G5: https://www.karriere.at/f/red-bull | H5: https://jobs.redbull.com/at-de
A6: SKIDATA GmbH | B6: Sanayi / üretim | C6: Wals | D6: =COUNTIF(İlanlar!$B$5:$B$126,A6) -> 1 | E6: =_xlfn.MAXIFS(İlanlar!$Z$5:$Z$126,İlanlar!$B$5:$B$126,A6) -> 0.87 | F6: Senior Project Manager - Delivery Execution & Multi-Team Governance (m/f/d) | G6: https://www.karriere.at/f/skidata
A7: TransUnion | B7: IT hizmetleri / danışmanlık | C7: Salzburg, Salzburg, Austria | D7: =COUNTIF(İlanlar!$B$5:$B$126,A7) -> 2 | E7: =_xlfn.MAXIFS(İlanlar!$Z$5:$Z$126,İlanlar!$B$5:$B$126,A7) -> 0.84 | F7: Technical Project Manager · Senior Systems Administrator | G7: https://www.linkedin.com/company/transunion | H7: https://transunion.wd5.myworkdayjobs.com/TransUnion
A8: Amer Sports | B8: Sanayi / üretim | C8: Altenmarkt im Pongau, Salzburg, Austria | D8: =COUNTIF(İlanlar!$B$5:$B$126,A8) -> 1 | E8: =_xlfn.MAXIFS(İlanlar!$Z$5:$Z$126,İlanlar!$B$5:$B$126,A8) -> 0.81 | F8: OT-Security Domain Manager(m/f/d) | G8: https://fi.linkedin.com/company/amer-sports
A9: epunkt GmbH | B9: Personel danışmanlığı / diğer | C9: Bezirk Vöcklabruck; Salzburg; Salzburg (Stadt) | D9: =COUNTIF(İlanlar!$B$5:$B$126,A9) -> 3 | E9: =_xlfn.MAXIFS(İlanlar!$Z$5:$Z$126,İlanlar!$B$5:$B$126,A9) -> 0.805 | F9: IT Allrounder (w/m/x) · IT System Administrator (w/m/x) · (Senior) Firewall & Network Security Engineer (w/m/x) | G9: https://www.karriere.at/f/epunkt-linz | H9: https://job.epunkt.com/jobs/
A10: Rehrl+Partner Personalberatung GmbH | B10: Personel danışmanlığı / diğer | C10: Salzburg, Salzburg, Austria | D10: =COUNTIF(İlanlar!$B$5:$B$126,A10) -> 1 | E10: =_xlfn.MAXIFS(İlanlar!$Z$5:$Z$126,İlanlar!$B$5:$B$126,A10) -> 0.775 | F10: Leitung IT-Infrastruktur (m/w/d) | G10: https://at.linkedin.com/company/rehrl-partner-personalberatung-gmbh | H10: https://www.rehrl.at/jobs/
A11: KERN engineering careers GmbH | B11: Personel danışmanlığı / diğer | C11: Graz, Klagenfurt, Salzburg, Wels, Wien; Linz, Steyr, Salzburg, Wels, Wien; Linz-Land, Graz, Salzburg; Vöcklabruck | D11: =COUNTIF(İlanlar!$B$5:$B$126,A11) -> 4 | E11: =_xlfn.MAXIFS(İlanlar!$Z$5:$Z$126,İlanlar!$B$5:$B$126,A11) -> 0.775 | F11: Information Security Consultant (w/m/d) · Devops Engineer mit Security-Schwerpunkt (w/m/d) · IT Support Engineer (w/m/d) · IT Systemadministrator (w/m/d) | G11: https://www.karriere.at/f/kern-engineering-careers
A12: Salzburger Abfallbeseitigung GmbH | B12: Sanayi / üretim | C12: Salzburg (Stadt) | D12: =COUNTIF(İlanlar!$B$5:$B$126,A12) -> 1 | E12: =_xlfn.MAXIFS(İlanlar!$Z$5:$Z$126,İlanlar!$B$5:$B$126,A12) -> 0.77 | F12: Koordinator für Informationssicherheit und Managementsysteme (m/w/d) | G12: https://www.karriere.at/f/salzburger-abfallbeseitigung | H12: https://www.salzburg-ag.at/karriere/wir-als-arbeitgeber.html
A13: PALFINGER | B13: Sanayi / üretim | C13: Bergheim, Salzburg, Austria | D13: =COUNTIF(İlanlar!$B$5:$B$126,A13) -> 1 | E13: =_xlfn.MAXIFS(İlanlar!$Z$5:$Z$126,İlanlar!$B$5:$B$126,A13) -> 0.76 | F13: Cyber Security Engineer (f/m/d) | G13: https://at.linkedin.com/company/palfinger | H13: https://www.palfinger.com/worldwide/en/career.html
A14: Xenium AG | B14: IT hizmetleri / danışmanlık | C14: Salzburg, Austria | D14: =COUNTIF(İlanlar!$B$5:$B$126,A14) -> 1 | E14: =_xlfn.MAXIFS(İlanlar!$Z$5:$Z$126,İlanlar!$B$5:$B$126,A14) -> 0.75 | F14: Lead IT Consultant Digitalisierung & Projektleitung (m/w/d) | G14: https://de.linkedin.com/company/xenium-ag
A15: Aptean | B15: IT hizmetleri / danışmanlık | C15: Salzburg, Austria | D15: =COUNTIF(İlanlar!$B$5:$B$126,A15) -> 1 | E15: =_xlfn.MAXIFS(İlanlar!$Z$5:$Z$126,İlanlar!$B$5:$B$126,A15) -> 0.74 | F15: ERP Customer Support Consultant | G15: https://www.linkedin.com/company/aptean
A16: x-tention Informationstechnologie GmbH | B16: IT hizmetleri / danışmanlık | C16: Klagenfurt am Wörthersee, Wien, St. Peter in der Au, Graz, Wels, Salzburg (Stadt); Wien, Wels, Salzburg (Stadt) | D16: =COUNTIF(İlanlar!$B$5:$B$126,A16) -> 6 | E16: =_xlfn.MAXIFS(İlanlar!$Z$5:$Z$126,İlanlar!$B$5:$B$126,A16) -> 0.74 | F16: Senior Cyber Security Consultant & Project Manager (m/w/d) · Senior Enterprise Network Engineer (m/w/d) · Datacenter Systems Engineer (m/w/d) · Security Awareness Specialist (m/w/d) · Senior Cybersecurity Analyst (m/w/d) · Security Systems Engineer (m/w/d) | G16: https://www.karriere.at/f/x-tention-informationstechnologie | H16: https://x-tention.com/en/career
A17: Soulkitchen Group | B17: Perakende / FMCG / tüketici | C17: Salzburg, Salzburg, Austria | D17: =COUNTIF(İlanlar!$B$5:$B$126,A17) -> 1 | E17: =_xlfn.MAXIFS(İlanlar!$Z$5:$Z$126,İlanlar!$B$5:$B$126,A17) -> 0.74 | F17: IT-Manager (m/w/d) | G17: https://at.linkedin.com/company/soulkitchen-group
A18: HR Consulting Ines Schöffmann GmbH | B18: Personel danışmanlığı / diğer | C18: Zell Am See, Salzburg, Austria | D18: =COUNTIF(İlanlar!$B$5:$B$126,A18) -> 1 | E18: =_xlfn.MAXIFS(İlanlar!$Z$5:$Z$126,İlanlar!$B$5:$B$126,A18) -> 0.735 | F18: IT-Sicherheitsarchitekt:in | G18: https://www.linkedin.com/company/hr-consulting-ines-sch%C3%B6ffmann-gmbh | H18: https://hr-schoeffmann.at/
A19: SPAR ICS – Information & Communication Services | B19: Perakende / FMCG / tüketici | C19: Salzburg (Stadt), Wien, Wernberg; Wien, Salzburg (Stadt) | D19: =COUNTIF(İlanlar!$B$5:$B$126,A19) -> 5 | E19: =_xlfn.MAXIFS(İlanlar!$Z$5:$Z$126,İlanlar!$B$5:$B$126,A19) -> 0.72 | F19: Product Lead IT Network (m/w/d) · Security Consultant - Vulnerability- und Exposure-Management (m/w/d) · Teamlead IT Service Desk (m/w/d) · Techlead Database Platform (m/w/d) · Senior Linux Expert POS-Systems (m/w/d) | G19: https://www.karriere.at/f/spar-ics-information-communication-services
A20: Deloitte | B20: IT hizmetleri / danışmanlık | C20: Salzburg, Salzburg, Austria | D20: =COUNTIF(İlanlar!$B$5:$B$126,A20) -> 1 | E20: =_xlfn.MAXIFS(İlanlar!$Z$5:$Z$126,İlanlar!$B$5:$B$126,A20) -> 0.71 | F20: (Senior) Manager ServiceNow Architekt (all genders) | G20: https://www.linkedin.com/company/deloitte
A21: SKIDATA | B21: Sanayi / üretim | C21: Grödig, Salzburg, Austria; Wals-Siezenheim, Salzburg, Austria | D21: =COUNTIF(İlanlar!$B$5:$B$126,A21) -> 2 | E21: =_xlfn.MAXIFS(İlanlar!$Z$5:$Z$126,İlanlar!$B$5:$B$126,A21) -> 0.71 | F21: Product Security Engineer (mfd) · IT Support Technician (mwd) | G21: https://at.linkedin.com/company/skidata-ag
A22: ReqPOOL GmbH | B22: IT hizmetleri / danışmanlık | C22: Linz, Wien, Salzburg (Stadt) | D22: =COUNTIF(İlanlar!$B$5:$B$126,A22) -> 1 | E22: =_xlfn.MAXIFS(İlanlar!$Z$5:$Z$126,İlanlar!$B$5:$B$126,A22) -> 0.71 | F22: Projektmanager Beratung mit PO-Erfahrung für Software & Digitalisierung (m/w/d) im Bereich Energy | G22: https://www.karriere.at/f/reqpool
A23: KTM AG | B23: Sanayi / üretim | C23: Mattighofen; Mattighofen, Upper Austria, Austria | D23: =COUNTIF(İlanlar!$B$5:$B$126,A23) -> 2 | E23: =_xlfn.MAXIFS(İlanlar!$Z$5:$Z$126,İlanlar!$B$5:$B$126,A23) -> 0.71 | F23: Head of IT Infrastructure & Operations* · Internal Control System (ICS) Specialist* | G23: https://www.karriere.at/f/ktm
A24: ACP Gruppe | B24: IT hizmetleri / danışmanlık | C24: Ranshofen; Salzburg; Salzburg (Stadt) | D24: =COUNTIF(İlanlar!$B$5:$B$126,A24) -> 7 | E24: =_xlfn.MAXIFS(İlanlar!$Z$5:$Z$126,İlanlar!$B$5:$B$126,A24) -> 0.695 | F24: Senior Operations Engineer m, w, d · Netzwerk Systems Engineer / Consultant · (Senior) Systems Engineer m, w, d · IT Operations Engineer · Senior Operations Workplace Engineer m, w, d · IT Onsite Client Support 1st & 2nd Level · Cloud Engineer | G24: https://www.karriere.at/f/acp-gruppe | H24: https://bewerbung.acp-gruppe.com/at
